Workbook

Sheet Sheet
A1: title | B1: creator | C1: subject | D1: publisher | E1: type | F1: digital object identifier | G1: physical object identifier | H1: URL | I1: language | J1: date | K1: relation | L1: coverage | M1: OCR URL | N1: OCR found?
A2: Abrégé de toutes les sciences, ou encyclopédie des enfants; mise dans un nouvel ordre,... | B2: Buqcellos, ...; Blocquel, Simon | C2: Kinder- und Jugendbücher; Historische Drucke | D2: Delarue ;; Castiaux | E2: monograph; text | F2: PPN766849139 | G2: PPN548262071 | H2: http://resolver.staatsbibliothek-berlin.de/SBB0000F13000000000 | I2: fre | J2: 1816 | K2: WegehauptDigital | L2: Paris; Lille | M2: empty | N2: no
A3: Naturgeschichte für Kinder | B3: Raff, Georg Christian | C3: Kinder- und Jugendbücher; Historische Drucke | D3: Sammer | E3: monograph; text | F3: PPN749770333 | G3: PPN279536941 | H3: http://resolver.staatsbibliothek-berlin.de/SBB0000E0AE00000000 | I3: ger | J3: 1846 | K3: WegehauptDigital | L3: Wien | M3: empty | N3: no
A4: Die Entstehung der Erde | B4: Kranz, Wilhelm; Meyer, Max Wilhelm | C4: Kinder- und Jugendbücher; Historische Drucke | D4: Paetel | E4: monograph; text | F4: PPN741297272 | G4: PPN276525892 | H4: http://resolver.staatsbibliothek-berlin.de/SBB0000CFAB00000000 | I4: ger | J4: 1907 | K4: WegehauptDigital | L4: Berlin | M4: https://content.staatsbibliothek-berlin.de/dc/741297272.ocr.zip | N4: yes
A5: Die Schulwerkstatt; ein Leitfaden zur Einführung der technischen Arbeiten in die Schule | B5: Barth, Ernst; Niederley, W. | C5: Kinder- und Jugendbücher; Historische Drucke | D5: Velhagen & Klasing | E5: monograph; text | F5: PPN745116574 | G5: PPN453868991 | H5: http://resolver.staatsbibliothek-berlin.de/SBB0000D59B00000000 | I5: ger | J5: 1882 | K5: WegehauptDigital | L5: Bielefeld [u.a.] | M5: https://content.staatsbibliothek-berlin.de/dc/745116574.ocr.zip | N5: yes
A6: Der junge Eisenbahnbauer; eine Anleitung zur Selbstherstellung von Modelleisenbahnen ; mit 118 Abb. | B6: Hermuth, Paul | C6: Kinder- und Jugendbücher; Historische Drucke | D6: Union Dt. Verl.-Gesellsch. | E6: monograph; text | F6: PPN744069432 | G6: PPN559338228 | H6: http://resolver.staatsbibliothek-berlin.de/SBB0000D52F00000000 | I6: ger | J6: 1916 | K6: WegehauptDigital | L6: Stuttgart [u.a.] | M6: https://content.staatsbibliothek-berlin.de/dc/744069432.ocr.zip | N6: yes
A7: Neuer Räthselschatz; für die Jugend zur Übung im Denken und zur belehrenden Unterhaltung | B7: Schäffer, W. | C7: Kinder- und Jugendbücher; Historische Drucke | D7: Oehmigke | E7: monograph; text | F7: PPN745271243 | G7: PPN573465517 | H7: http://resolver.staatsbibliothek-berlin.de/SBB0000D67F00000000 | I7: ger | J7: 1865 | K7: WegehauptDigital | L7: Neu-Ruppin | M7: https://content.staatsbibliothek-berlin.de/dc/745271243.ocr.zip | N7: yes
A8: Wander- und Spielbüchlein für Schüler und Schülerinnen | B8: Matzdorf, Paul | C8: Kinder- und Jugendbücher | D8: Strauch | E8: monograph; text | F8: PPN745123694 | G8: PPN56682809X | H8: http://resolver.staatsbibliothek-berlin.de/SBB0000D5AD00000000 | I8: ger | J8: 1910 | K8: WegehauptDigital | L8: Leipzig | M8: https://content.staatsbibliothek-berlin.de/dc/745123694.ocr.zip | N8: yes
A9: Causeries sur la science; illustrées de 94 gravures | B9: Tissandier, Gaston | C9: Kinder- und Jugendbücher; Historische Drucke | D9: Hachette | E9: monograph; text | F9: PPN745272312 | G9: PPN578011344 | H9: http://resolver.staatsbibliothek-berlin.de/SBB0000D68300000000 | I9: fre | J9: 1880 | K9: WegehauptDigital | L9: Paris | M9: https://content.staatsbibliothek-berlin.de/dc/745272312.ocr.zip | N9: yes
A10: Der unerschöpfliche Maître de Plaisir; oder die Kunst, in allen Jahreszeiten, im Freien und zu Hause, so wie an allen nur denkbaren Freudentagen die unterhaltendsten und belustigendsten Parthieen anzuordnen ; Enthaltend die besten Spiele, Lieder, Declamir- und Kunststücke, Räthsel, Charaden [et]c. Ein unentbehrliches Haus- und Handbuch für alle lebensfrohe deutsche Familien | C10: Kinder- und Jugendbücher; Historische Drucke | D10: Voigt | E10: monograph; text | F10: PPN767042255 | G10: PPN280073852 | H10: http://resolver.staatsbibliothek-berlin.de/SBB0000F1B700000000 | I10: ger | J10: 1822 | K10: WegehauptDigital | L10: Nordhausen; Sondershausen | M10: empty | N10: no
A11: Im Grünen oder Die kleinen Pflanzenfreunde; kleine Erzählungen aus dem Pflanzenreich | B11: Wagner, Hermann | C11: Kinder- und Jugendbücher | D11: Spamer | E11: monograph; text | F11: PPN743675703 | G11: PPN578788829 | H11: http://resolver.staatsbibliothek-berlin.de/SBB0000D31400000000 | I11: ger | J11: 1878 | K11: WegehauptDigital | L11: Leipzig | M11: https://content.staatsbibliothek-berlin.de/dc/743675703.ocr.zip | N11: yes
A12: Das Buch der Gesellschaftsspiele | B12: Weller, Hermine | C12: Kinder- und Jugendbücher | D12: Fischer | E12: monograph; text | F12: PPN745213553 | G12: PPN581117719 | H12: http://resolver.staatsbibliothek-berlin.de/SBB0000D65A00000000 | I12: ger | J12: 1910 | K12: WegehauptDigital | L12: Dresden | M12: https://content.staatsbibliothek-berlin.de/dc/745213553.ocr.zip | N12: yes
A13: Der gelehrte Spielkamerad; Anleitung für kleine Physiker, Chemiker, Botaniker und Naturfreunde zum Experimentieren, zur Anlage von Pflanzen-, Stein-, Muschel-, Insekten-, Schmetterling-, Vogel-, Briefmarken-Sammlungen ect. sowie zur Pflege der Hausthiere und des Hausgartens ; ein Supplement zum "Spielbuch für Knaben" | B13: Wagner, Hermann | C13: Kinder- und Jugendbücher | D13: Spamer | E13: monograph; text | F13: PPN74270906X | G13: PPN578814706 | H13: http://resolver.staatsbibliothek-berlin.de/SBB0000D2AA00000000 | I13: ger | J13: 1877 | K13: WegehauptDigital | L13: Leipzig | M13: https://content.staatsbibliothek-berlin.de/dc/74270906X.ocr.zip | N13: yes
A14: Des fleißigen Mädchens Koch-Büchlein für die Puppen-Küche | C14: Kinder- und Jugendbücher; Historische Drucke | D14: Meisel | E14: monograph; text | F14: PPN745432069 | G14: PPN278721036 | H14: http://resolver.staatsbibliothek-berlin.de/SBB0000D6A800000000 | I14: ger | J14: 1876 | K14: WegehauptDigital | L14: Leipzig; Herisau; Stuttgart | M14: https://content.staatsbibliothek-berlin.de/dc/745432069.ocr.zip | N14: yes
A15: Naturgeschichte für Kinder, von M. Georg Christian Raff, ordentlichen Lehrer der Geschichte und Geographie auf dem Lyceum zu Göttingen. Mit vierzehn Kupfertafeln | B15: Raff, Georg Christian | C15: Kinder- und Jugendbücher; Historische Drucke | E15: monograph; text | F15: PPN769119182 | G15: PPN571683770 | H15: http://resolver.staatsbibliothek-berlin.de/SBB0000F8A900000000 | I15: ger | J15: 1802 | K15: WegehauptDigital | L15: Frankfurt; Leipzig | M15: empty | N15: no
A16: Kleine Bilderschule für die Jugend | B16: Hausius, Karl Gottlob | C16: Kinder- und Jugendbücher; Historische Drucke | D16: Voß | E16: monograph; text | F16: PPN757417825 | G16: PPN55916422X | H16: http://resolver.staatsbibliothek-berlin.de/SBB0000ED8900000000 | I16: ger | J16: 1807 | K16: WegehauptDigital | L16: Leipzig | M16: empty | N16: no
A17: Vollständiges Giftbuch oder Unterricht, die Giftpflanzen, Giftminerale und Giftthiere kennen zu lernen, und Gesundheit und Leben gegen Vergiftungs-Gefahren sicher zu stellen | C17: Kinder- und Jugendbücher | D17: Voigt | E17: monograph; text | F17: PPN770137474 | G17: PPN406020620 | H17: http://resolver.staatsbibliothek-berlin.de/SBB0001031A00000000 | I17: ger | J17: 1817 | K17: WegehauptDigital | L17: Sondershausen | M17: empty | N17: no
A18: Schneiders Typen-Atlas; naturwissenschaftlich-geographischer Hand-Atlas für Schule und Haus | B18: Schneider, Oskar; Claudius, W.; Leutemann, H.; Mützel, G.; Seidel, C. F. | C18: Kinder- und Jugendbücher | D18: Meinhold | E18: monograph; text | F18: PPN743969359 | G18: PPN574227601 | H18: http://resolver.staatsbibliothek-berlin.de/SBB0000D4C500000000 | I18: ger | J18: 1885 | K18: WegehauptDigital | L18: Dresden | M18: https://content.staatsbibliothek-berlin.de/dc/743969359.ocr.zip | N18: yes
A19: Das Buch wunderbarer Erfindungen; in Schilderungen f. d. reifere Jugend : mit 125 Abb. u. 1 Titelbild. | B19: Thomas, Louis | C19: Kinder- und Jugendbücher; Historische Drucke | D19: Spamer | E19: monograph; text | F19: PPN756689090 | G19: PPN578154765 | H19: http://resolver.staatsbibliothek-berlin.de/SBB0000EBC100000000 | I19: ger | J19: 1860 | K19: WegehauptDigital | L19: Leipzig | M19: https://content.staatsbibliothek-berlin.de/dc/756689090.ocr.zip | N19: yes
A20: Naturgeschichte der Vögel; mit besonderer Berücksichtigung der in Deutschland vorkommenden Vögel und Belehrung über Zucht und Wartung der Haus- und Stubenvögel | B20: Abendroth, Carl | C20: Kinder- und Jugendbücher | D20: Baensch | E20: monograph; text | F20: PPN744053714 | G20: PPN538752823 | H20: http://resolver.staatsbibliothek-berlin.de/SBB0000D51E00000000 | I20: ger | J20: 1870 | K20: WegehauptDigital | L20: Leipzig | M20: https://content.staatsbibliothek-berlin.de/dc/744053714.ocr.zip | N20: yes
A21: Abrégé de toutes les sciences à l'usage des enfans de six ans jusqu' a douze; on y a joint un abrégé de l'histoire de Brandebourg | B21: Formey, Jean-Henri-Samuel | C21: Kinder- und Jugendbücher; Historische Drucke | D21: Horvath | E21: monograph; text | F21: PPN76623858X | G21: PPN557396433 | H21: http://resolver.staatsbibliothek-berlin.de/SBB0000EE5000000000 | I21: fre | J21: 1803 | K21: WegehauptDigital | L21: Potsdam | M21: empty | N21: no
A22: Jagden-Bilderbuch für die liebe Jugend; mit 9 lithographirten Darstellungen | C22: Kinder- und Jugendbücher | E22: monograph; text | F22: PPN770079113 | G22: PPN491349475 | H22: http://resolver.staatsbibliothek-berlin.de/SBB000102A700000000 | I22: ger | J22: 1860 | K22: WegehauptDigital | L22: [S.l.] | M22: https://content.staatsbibliothek-berlin.de/dc/770079113.ocr.zip | N22: yes
A23: Neues und bewährtes illustriertes Kochbuch für alle Stände; zuverlässige Anleitung zur Bereitung der verschiedenartigsten Speisen, Backwerke, Getränke etc. ; nach eigener, vieljähriger Erfahrung | B23: Davithis, H. | C23: Kinder- und Jugendbücher; Historische Drucke | D23: Enßlin und Laiblin | E23: monograph; text | F23: PPN745127495 | G23: PPN278540538 | H23: http://resolver.staatsbibliothek-berlin.de/SBB0000D5C100000000 | I23: ger | J23: 1905 | K23: WegehauptDigital | L23: Reutlingen | M23: https://content.staatsbibliothek-berlin.de/dc/745127495.ocr.zip | N23: yes
A24: An der Werkbank; Anleitung zur Handfertigkeit mit besonderer Berücksichtigung der Herstellung physikalischer Apparate ; für mittlere und reife Schüler | B24: Gscheidlen, Emanuel | C24: Kinder- und Jugendbücher; Historische Drucke | D24: Teubner | E24: monograph; text | F24: PPN745118615 | G24: PPN223999733 | H24: http://resolver.staatsbibliothek-berlin.de/SBB0000D59F00000000 | I24: ger | J24: 1912 | K24: WegehauptDigital | L24: Berlin; Leipzig | M24: https://content.staatsbibliothek-berlin.de/dc/745118615.ocr.zip | N24: yes
A25: Die Schöpfung der Erde; die Urwelt und die Urgeschöpfe bis zum Auftreten des Menschen ; Blicke in das Erdinnere ; Wanderungen in die Gebirgswelt, namentlich unsres Veterlandes, nach Kreuz und Quer ; mit reiferen Schülern unternommen | B25: Hintze, Eduard | C25: Kinder- und Jugendbücher | D25: Spamer | E25: monograph; text | F25: PPN742493695 | G25: PPN341499900 | H25: http://resolver.staatsbibliothek-berlin.de/SBB0000D1BE00000000 | I25: ger | J25: 1885 | K25: WegehauptDigital | L25: Leipzig, Berlin | M25: https://content.staatsbibliothek-berlin.de/dc/742493695.ocr.zip | N25: yes
A26: Der Weltspiegel; das Wissenswürdigste vom Weltgebäude, von der Erde, von den Völkern der Erde | B26: Hoffmann, Friedrich | C26: Kinder- und Jugendbücher; Historische Drucke | D26: Schmidt & Spring; Lithographische Anstalt von Engelhorn und Hochdanz | E26: monograph; text | F26: PPN766156990 | G26: PPN279154607 | H26: http://resolver.staatsbibliothek-berlin.de/SBB0000EE1D00000000 | I26: ger | J26: 1844 | K26: WegehauptDigital | L26: Stuttgart; Stuttgart | M26: empty | N26: no
A27: Naturgeschichte; der Jugend gewidmet | B27: Wagner, Hermann | C27: Kinder- und Jugendbücher | D27: Hoffmann | E27: monograph; text | F27: PPN770457983 | G27: PPN408013931 | H27: http://resolver.staatsbibliothek-berlin.de/SBB0001049700000000 | I27: ger | J27: 1870 | K27: WegehauptDigital | L27: Stuttgart | M27: https://content.staatsbibliothek-berlin.de/dc/770457983.ocr.zip | N27: yes
A28: Lehrbuch der Sternkunde; für Schulen und zum Selbstunterrichte | B28: Schubert, Gotthilf Heinrich | C28: Kinder- und Jugendbücher; Historische Drucke | D28: Weber | E28: monograph; text | F28: PPN750739150 | G28: PPN311822029 | H28: http://resolver.staatsbibliothek-berlin.de/SBB0000E3CF00000000 | I28: ger | J28: 1832 | K28: WegehauptDigital | L28: München | M28: empty | N28: no
A29: Leichte Künsteleien zum Vergnügen und zum Nutzen für Kinder und Nichtkinder; Ein Buch mannigfaltigen Inhaltes | B29: Rockstroh, Heinrich | C29: Kinder- und Jugendbücher; Historische Drucke | D29: Wittich | E29: monograph; text | F29: PPN767041380 | G29: PPN556113098 | H29: http://resolver.staatsbibliothek-berlin.de/SBB0000F1B600000000 | I29: ger | J29: 1819 | K29: WegehauptDigital | L29: Berlin | M29: empty | N29: no
A30: Europäische Bilder und Skizzen; zur Belehrung für die reifere Jugend | B30: Hoffmann, Julius; Hosemann, Theodor | C30: Kinder- und Jugendbücher | D30: Trewendt | E30: monograph; text | F30: PPN771014600 | G30: PPN265186358 | H30: http://resolver.staatsbibliothek-berlin.de/SBB00010A6400000000 | I30: ger | J30: 1858 | K30: WegehauptDigital | L30: Breslau | M30: https://content.staatsbibliothek-berlin.de/dc/771014600.ocr.zip | N30: yes
A31: Malerische Naturgeschichte der drei Reiche für Schule und Haus; Mit besonderer Beziehung auf das practische Leben bearbeitet von F[riedrich] W[ilhelm] Lindner; unter Mitwirkung von Dr. Fr. H. A. Lachmann | B31: Lachmann, Fr. H. A.; Lindner, Friedrich Wilhelm | C31: Kinder- und Jugendbücher; Historische Drucke | D31: Oehme & Müller | E31: monograph; text | F31: PPN770463371 | G31: PPN42077016X | H31: http://resolver.staatsbibliothek-berlin.de/SBB000104A200000000 | I31: ger | J31: 1840 | K31: WegehauptDigital | L31: Braunschweig | M31: empty | N31: no
A32: Allerlei schöne Bilderrätsel für Jung und Alt | C32: Kinder- und Jugendbücher; Historische Drucke | E32: monograph; text | F32: PPN74513548X | G32: PPN30847046X | H32: http://resolver.staatsbibliothek-berlin.de/SBB0000D5D100000000 | I32: ger | K32: WegehauptDigital | M32: https://content.staatsbibliothek-berlin.de/dc/74513548X.ocr.zip | N32: yes
A33: Der Hausbau; oder erste Begriffe von Staat und den vorzüglichsten Ständen, Handwerken, Fabriken, Künsten, Wissenschaften u. d. gl. für Kinder | B33: Werlich, August Karl Friedrich | C33: Kinder- und Jugendbücher; Historische Drucke | D33: Juniussische Buchhandlung | E33: monograph; text | F33: PPN756639891 | G33: PPN579566781 | H33: http://resolver.staatsbibliothek-berlin.de/SBB0000EB7900000000 | I33: ger | J33: 1804 | K33: WegehauptDigital | L33: Leipzig | M33: empty | N33: no
A34: Gemählde aus der Natur und dem Menschenleben, in einer Reihe von Schilderungen merkwürdiger Naturerscheinungen und gefahrvoller Reiseabentheuer; zum Nutzen und Vergnügen der Jugend | B34: Albertus, D. J. C. | C34: Kinder- und Jugendbücher | D34: Kaiser | E34: monograph; text | F34: PPN781283116 | G34: PPN541529498 | H34: http://resolver.staatsbibliothek-berlin.de/SBB0001555D00000000 | I34: ger | J34: 1830 | K34: WegehauptDigital | L34: Grätz | M34: empty | N34: no
A35: Kurzer Unterricht in der Naturwissenschaft für die Jugend | B35: Uihlein, Joseph | C35: Kinder- und Jugendbücher; Historische Drucke | D35: Andreä | E35: monograph; text | F35: PPN770157742 | G35: PPN366080202 | H35: http://resolver.staatsbibliothek-berlin.de/SBB0001033900000000 | I35: ger | J35: 1810 | K35: WegehauptDigital | L35: Frankfurt am Main | M35: empty | N35: no
A36: F. Martin's Naturgeschichte für die Jugend beiderlei Geschlechts; mit dreihundert Abbildungen und zwanzig Holzschnitten | B36: Kolb, Christian Friedrich August; Martin, F. | C36: Kinder- und Jugendbücher; Historische Drucke | D36: Schmidt & Spring | E36: monograph; text | F36: PPN741294397 | G36: PPN566740400 | H36: http://resolver.staatsbibliothek-berlin.de/SBB0000CFA500000000 | I36: ger | J36: 1880 | K36: WegehauptDigital | L36: Stuttgart | M36: https://content.staatsbibliothek-berlin.de/dc/741294397.ocr.zip | N36: yes
A37: Aus Werkstatt und Welt; eine Festgabe für die werkthätige Jugend dargereicht von Leipz. Fortbildungsschuldirektoren u.-Lehrern | C37: Kinder- und Jugendbücher; Historische Drucke | D37: Hahn; Schmidt | E37: monograph; text | F37: PPN770851347 | G37: PPN581182618 | H37: http://resolver.staatsbibliothek-berlin.de/SBB0001070300000000 | I37: ger | J37: 1901 | K37: WegehauptDigital | L37: Leipzig; Leipzig | M37: https://content.staatsbibliothek-berlin.de/dc/770851347.ocr.zip | N37: yes
A38: Mittheilungen aus dem Gebiet der Naturkunde und dem Menschenleben für die Jugend ; mit 25 col. Abb. | B38: Maukisch, Heinrich Eduard | C38: Kinder- und Jugendbücher; Historische Drucke | D38: Fischer u. Fuchs | E38: monograph; text | F38: PPN766619389 | G38: PPN566841444 | H38: http://resolver.staatsbibliothek-berlin.de/SBB0000F00A00000000 | I38: ger | J38: 1835 | K38: WegehauptDigital | L38: Leipzig | M38: empty | N38: no
A39: Čudesa bez čudesʹ; malenkaja fizika v priměnenii kʹ zabavamʹ/ sost. A. P. Nečaev. S 172 ris. | B39: Nečaev, A. P. | C39: Kinder- und Jugendbücher | D39: Lukovnikov | E39: monograph; text | F39: PPN742094227 | G39: PPN280334869 | H39: http://resolver.staatsbibliothek-berlin.de/SBB0000D0A100000000 | I39: rus | J39: 1911 | K39: WegehauptDigital | L39: Spb. [St. Petersburg] | M39: https://content.staatsbibliothek-berlin.de/dc/742094227.ocr.zip | N39: yes
A40: Nun rathe einmal!; Räthselbüchlein für Kinder von 5 - 10 Jahren | B40: Flinzer, Fedor | C40: Kinder- und Jugendbücher; Historische Drucke | D40: Focke | E40: monograph; text | F40: PPN745597041 | G40: PPN568651901 | H40: http://resolver.staatsbibliothek-berlin.de/SBB0000D6F200000000 | I40: ger | J40: 1864 | K40: WegehauptDigital | L40: Chemnitz | M40: https://content.staatsbibliothek-berlin.de/dc/745597041.ocr.zip | N40: yes
A41: Räthselkranz für Alt und Jung | B41: Ruhkopf, Julie | C41: Kinder- und Jugendbücher; Historische Drucke | D41: Flemming | E41: monograph; text | F41: PPN74623791X | G41: PPN476384494 | H41: http://resolver.staatsbibliothek-berlin.de/SBB0000D85700000000 | I41: ger | J41: 1861 | K41: WegehauptDigital | L41: Glogau | M41: https://content.staatsbibliothek-berlin.de/dc/74623791X.ocr.zip | N41: yes
A42: Merkwürdige Reisen der Gutmannschen Familie; ein Weihnachts- und Geburtstags-Geschenk für die Jugend | B42: Ramberg, H.; Boettger, G.; Dassel, Chr. | C42: Kinder- und Jugendbücher | D42: Brüder Hahn | E42: monograph; text | F42: PPN746870108 | G42: PPN363821880 | H42: http://resolver.staatsbibliothek-berlin.de/SBB0000DBD600000000 | I42: ger | J42: 1816 | K42: WegehauptDigital | L42: Hannover | M42: empty | N42: no
A43: Recipes | C43: Kinder- und Jugendbücher | D43: Orr | E43: monograph; text | F43: PPN746034628 | G43: PPN279781792 | H43: http://resolver.staatsbibliothek-berlin.de/SBB0000D7DD00000000 | I43: eng | J43: 1883 | K43: WegehauptDigital | L43: Springfield, Mass. | M43: https://content.staatsbibliothek-berlin.de/dc/746034628.ocr.zip | N43: yes
A44: Das Turnen in den Spielen der Mädchen; eine Auswahl nützlicher und passender Jugend- und Bewegungspiele ; zur geistigen und körperlichen Erholung des jüngeren Mädchenalters wie als Beitrag zu einer naturgemäßen Jugenderziehung | B44: Bürkner, Hugo; Kloss, Moritz | C44: Kinder- und Jugendbücher | D44: Schönfeld | E44: monograph; text | F44: PPN770493564 | G44: PPN27843424X | H44: http://resolver.staatsbibliothek-berlin.de/SBB000104D400000000 | I44: ger | J44: 1862 | K44: WegehauptDigital | L44: Dresden | M44: https://content.staatsbibliothek-berlin.de/dc/770493564.ocr.zip | N44: yes
A45: Das Ein-mal-Eins in Bilderpracht, wie es den Kindern Freude macht | B45: Reinhardt, Aug.; Reinhardt, V. | C45: Kinder- und Jugendbücher | D45: Kaufmann | E45: monograph; text | F45: PPN741360802 | G45: PPN572962495 | H45: http://resolver.staatsbibliothek-berlin.de/SBB0000CFF400000000 | I45: ger | J45: 1880 | K45: WegehauptDigital | L45: Dresden | M45: https://content.staatsbibliothek-berlin.de/dc/741360802.ocr.zip | N45: yes
A46: Natur-Paradoxe; ein Buch für die Jugend zur Erklärung von Erscheinungen, die mit der täglichen Erfahrung in Widerspruch zu stehen scheinen ; nach Dr. W. Hampson's 'Paradoxes of nature and science' | B46: Schäffer, C.; Hampson, William | C46: Kinder- und Jugendbücher | D46: Teubner | E46: monograph; text | F46: PPN741671417 | G46: PPN408347201 | H46: http://resolver.staatsbibliothek-berlin.de/SBB0000D04500000000 | I46: ger | J46: 1908 | K46: WegehauptDigital | L46: Leipzig; Berlin | M46: https://content.staatsbibliothek-berlin.de/dc/741671417.ocr.zip | N46: yes
A47: Die Meteorologie in Erklärungen und Erzählungen; ein nützliches und unterhaltendes Lesebuch für die reifere Jugend | B47: Moshamer, Joseph A. | C47: Kinder- und Jugendbücher | D47: Im Verl. der k. k. Schulbücher-Verschleiß-Administration | E47: monograph; text | F47: PPN770192904 | G47: PPN348919875 | H47: http://resolver.staatsbibliothek-berlin.de/SBB0001037500000000 | I47: ger | J47: 1844 | K47: WegehauptDigital | L47: Wien | M47: empty | N47: no
A48: Naturstudien im Hause; Plaudereien in der Dämmerstunde ; ein Buch für die Jugend | B48: Schwindrazheim, O.; Kraepelin, Karl | C48: Kinder- und Jugendbücher | D48: Teubner | E48: monograph; text | F48: PPN742265854 | G48: PPN075438097 | H48: http://resolver.staatsbibliothek-berlin.de/SBB0000D0DF00000000 | I48: ger | J48: 1901 | K48: WegehauptDigital | L48: Leipzig | M48: https://content.staatsbibliothek-berlin.de/dc/742265854.ocr.zip | N48: yes
A49: Peter Parley's Visit to London; during the coronation of Queen Victoria | B49: Viktoria < Großbritannien, Königin>; Parley, Peter | C49: Kinder- und Jugendbücher; Historische Drucke | D49: Tilt | E49: monograph; text | F49: PPN771192134 | G49: PPN27953969X | H49: http://resolver.staatsbibliothek-berlin.de/SBB0001262E00000000 | I49: eng | J49: 1839 | K49: WegehauptDigital | L49: London | M49: empty | N49: no
A50: Die kleinen Gärtner, oder Gartenbeschäftigungen für Kinder; enthält einen deutlichen Unterricht, wie Kinder einen kleinen Garten anlegen, behandeln und abwarten können, ohne dabey einen Gärtner zu Hülfe zu nehmen : mit Kupfern | B50: Poscharsky, Christian Friedrich | C50: Kinder- und Jugendbücher; Historische Drucke | D50: Friese | E50: monograph; text | F50: PPN769382053 | G50: PPN389953334 | H50: http://resolver.staatsbibliothek-berlin.de/SBB0000F96300000000 | I50: ger | J50: 1810 | K50: WegehauptDigital | L50: Pirna | M50: empty | N50: no
A51: Carl der Tausendkünstler, oder: Sammlung einfacher und künstlicher, großentheils neuer mechanischer, chemischer, magnetischer und Kartenkunststücke und arithmetischer Belustigungen zur angenehmen geselligen Unterhaltung | B51: Kerndörffer, Heinrich August | C51: Kinder- und Jugendbücher; Historische Drucke | D51: Cnobloch | E51: monograph; text | F51: PPN766428656 | G51: PPN560665571 | H51: http://resolver.staatsbibliothek-berlin.de/SBB0000EF3700000000 | I51: ger | J51: 1840 | K51: WegehauptDigital | L51: Leipzig | M51: empty | N51: no
A52: Der illustrirte Jugendfreund; Schilderungen des Weltgebäudes und seiner Wunder ; in Bilder aus der Natur, dem Leben der Menschen und der Thiere der Vergangenheit und Gegenwart | B52: Thomas, Louis | C52: Kinder- und Jugendbücher; Historische Drucke | D52: Spamer | E52: monograph; text | F52: PPN767132297 | G52: PPN578175231 | H52: http://resolver.staatsbibliothek-berlin.de/SBB0000F2BB00000000 | I52: ger | J52: 1852 | K52: WegehauptDigital | L52: Leipzig | M52: https://content.staatsbibliothek-berlin.de/dc/767132297.ocr.zip | N52: yes
A53: The Child's guide to knowledge; being a collection of useful and familiar questions and answers on every-day subjects; adapted for young persons, and arranged in the most simple and easy language ; by a Lady | C53: Kinder- und Jugendbücher; Historische Drucke | D53: Simpkin [u.a.] | E53: monograph; text | F53: PPN745137695 | G53: PPN550723854 | H53: http://resolver.staatsbibliothek-berlin.de/SBB0000D5D600000000 | I53: eng | J53: 1871 | K53: WegehauptDigital | L53: London | M53: https://content.staatsbibliothek-berlin.de/dc/745137695.ocr.zip | N53: yes
A54: Kleine Bilder-Encyclopedie; [für junge Knaben und Mädchen] | C54: Kinder- und Jugendbücher | D54: Rücker] | E54: monograph; text | F54: PPN770565247 | G54: PPN445549262 | H54: http://resolver.staatsbibliothek-berlin.de/SBB0001055A00000000 | I54: ger | J54: 1808 | K54: WegehauptDigital | L54: [Berlin | M54: empty | N54: no
A55: Naturgeschichte für Kinder | B55: Meyer, F. A. A.; Raff, Georg Christian | C55: Kinder- und Jugendbücher; Historische Drucke | D55: Dieterich | E55: monograph; text | F55: PPN769384986 | G55: PPN141087994 | H55: http://resolver.staatsbibliothek-berlin.de/SBB0000F96900000000 | I55: ger | J55: 1827 | K55: WegehauptDigital | L55: Göttingen | M55: empty | N55: no
A56: Kochbüchlein für die Puppenküche oder erste Anweisung zum Kochen; Für Mädchen von 8-14 Jahren | B56: Löffler, Henriette; Bimbach, Julie | C56: Kinder- und Jugendbücher | D56: Schreiber | E56: monograph; text | F56: PPN769117392 | G56: PPN548218307 | H56: http://resolver.staatsbibliothek-berlin.de/SBB0000F8A000000000 | I56: ger | J56: 1885 | K56: WegehauptDigital | L56: Eßlingen | M56: https://content.staatsbibliothek-berlin.de/dc/769117392.ocr.zip | N56: yes
A57: Naturgeschichte der deutschen Schmetterlinge für die Jugend; Nebst einer passenden Anweisung, sie zu fangen, zuzubereiten, zu ordnen und unbeschädigt zu erhalten | C57: Kinder- und Jugendbücher; Historische Drucke | D57: Groß | E57: monograph; text | F57: PPN75101611X | G57: PPN568829980 | H57: http://resolver.staatsbibliothek-berlin.de/SBB0000E42300000000 | I57: ger | J57: 1805 | K57: WegehauptDigital | L57: Halberstadt | M57: empty | N57: no
A58: Illustrirte Naturgeschichte für die Jugend; mit mehr als 200 color. Abb. | B58: Schubert, Ferdinand; Schubert, Carl | C58: Kinder- und Jugendbücher; Historische Drucke | D58: Sallmayer | E58: monograph; text | F58: PPN749885149 | G58: PPN574523774 | H58: http://resolver.staatsbibliothek-berlin.de/SBB0000E14B00000000 | I58: ger | J58: 1856 | K58: WegehauptDigital | L58: Wien | M58: https://content.staatsbibliothek-berlin.de/dc/749885149.ocr.zip | N58: yes
A59: Spielbuch; enthaltend Gesellschaftsspiele, Auslösen der Pfänder, Rätsel, Charaden | B59: Löwicke, Robert | C59: Kinder- und Jugendbücher; Historische Drucke | D59: Flemming | E59: monograph; text | F59: PPN745605478 | G59: PPN566420597 | H59: http://resolver.staatsbibliothek-berlin.de/SBB0000D71400000000 | I59: ger | J59: 1887 | K59: WegehauptDigital | L59: Glogau | M59: https://content.staatsbibliothek-berlin.de/dc/745605478.ocr.zip | N59: yes
A60: Reise einer Tante in vieler Herren Länder | B60: Bernhardi, Elisabeth Eleonore | C60: Kinder- und Jugendbücher | E60: monograph; text | F60: PPN77088976X | G60: PPN444747249 | H60: http://resolver.staatsbibliothek-berlin.de/SBB0001074200000000 | I60: ger | J60: 1817 | K60: WegehauptDigital | L60: [Freiberg] | M60: empty | N60: no
A61: Naturgeschichte der Insekten für die Jugend ; Mit Kupfern | C61: Kinder- und Jugendbücher | D61: Campe | E61: monograph; text | F61: PPN770372821 | G61: PPN32489211X | H61: http://resolver.staatsbibliothek-berlin.de/SBB0001046000000000 | I61: ger | J61: 1820 | K61: WegehauptDigital | L61: Nürnberg | M61: empty | N61: no
A62: Kleines Käferbuch für Knaben; eine Anleitung zur Kenntniß der Käfer im Allgemeinen wie auch zur Anlage und zweckmäßigen Einrichtung von Käfersammlungen ; mit 72 illuminierten Abbildungen auf 5 Tafeln | C62: Kinder- und Jugendbücher; Historische Drucke | D62: Hendel | E62: monograph; text | F62: PPN742562549 | G62: PPN560569718 | H62: http://resolver.staatsbibliothek-berlin.de/SBB0000D21A00000000 | I62: ger | J62: 1862 | K62: WegehauptDigital | L62: Halle | M62: https://content.staatsbibliothek-berlin.de/dc/742562549.ocr.zip | N62: yes
A63: Entdeckungsreisen in Haus und Hof; mit seinen jungen Freunden unternommen | B63: Wagner, H. | C63: Kinder- und Jugendbücher | D63: Spamer | E63: monograph; text | F63: PPN74364154X | G63: PPN270201556 | H63: http://resolver.staatsbibliothek-berlin.de/SBB0000D30500000000 | I63: ger | J63: 1866 | K63: WegehauptDigital | L63: Leipzig | M63: https://content.staatsbibliothek-berlin.de/dc/74364154X.ocr.zip | N63: yes
A64: [Rätselbuch] | C64: Kinder- und Jugendbücher; Historische Drucke | E64: monograph; text | F64: PPN766622541 | G64: PPN571694535 | H64: http://resolver.staatsbibliothek-berlin.de/SBB0000F01000000000 | I64: ger | J64: 1830 | K64: WegehauptDigital | L64: [S.l.] | M64: empty | N64: no
A65: Naturstudien im Garten; Plaudereien am Sonntag Nachmittag ; ein Buch für die Jugend | B65: Schwindrazheim, O.; Kraepelin, Karl | C65: Kinder- und Jugendbücher | D65: Teubner | E65: monograph; text | F65: PPN742297330 | G65: PPN075795655 | H65: http://resolver.staatsbibliothek-berlin.de/SBB0000D0EF00000000 | I65: ger | J65: 1901 | K65: WegehauptDigital | L65: Leipzig | M65: https://content.staatsbibliothek-berlin.de/dc/742297330.ocr.zip | N65: yes
A66: Charakterbilder aus der Thierwelt verschiedener Welttheile; zur Belehrung und Unterhaltung der Jugend | B66: Hoffmann, W. | C66: Kinder- und Jugendbücher | D66: Nitzschke | E66: monograph; text | F66: PPN743630491 | G66: PPN26518777X | H66: http://resolver.staatsbibliothek-berlin.de/SBB0000D2F600000000 | I66: ger | J66: 1862 | K66: WegehauptDigital | L66: Stuttgart | M66: https://content.staatsbibliothek-berlin.de/dc/743630491.ocr.zip | N66: yes
A67: Neue Wanderungen durch die Thierwelt; ein Buch für Knaben und Mädchen | B67: Kirchhoff, Johann; Reichenbach, A. B. | C67: Kinder- und Jugendbücher | D67: Kretzschmar | E67: monograph; text | F67: PPN770577199 | G67: PPN311107745 | H67: http://resolver.staatsbibliothek-berlin.de/SBB0001057F00000000 | I67: ger | J67: 1848 | K67: WegehauptDigital | L67: Leipzig | M67: empty | N67: no
A68: Reisen in die Ferne oder Vater Reinhold's Mittheilungen über die Erde und ihre Bewohner; ein Lese- und Bilderbuch zur Belehrung und Unterhaltung der Jugend in der Völkerkunde und Erdbeschreibung | B68: Geissler, ...; Boettger, Gottlieb; Maukisch, Heinrich Eduard | C68: Kinder- und Jugendbücher; Historische Drucke | D68: Taubert | E68: monograph; text | F68: PPN77101631X | G68: PPN278734375 | H68: http://resolver.staatsbibliothek-berlin.de/SBB00010A6800000000 | I68: ger | J68: 1836 | K68: WegehauptDigital | L68: Leipzig | M68: empty | N68: no
A69: Lustige Bilder-Räthsel für kluge Kinder | B69: Breitschwert, W. | C69: Kinder- und Jugendbücher | D69: Hoffmann <Thienemann> | E69: monograph; text | F69: PPN745436269 | G69: PPN279375425 | H69: http://resolver.staatsbibliothek-berlin.de/SBB0000D6B000000000 | I69: ger | J69: 1875 | K69: WegehauptDigital | L69: Stuttgart | M69: https://content.staatsbibliothek-berlin.de/dc/745436269.ocr.zip | N69: yes
A70: Wie viel sind's?; Ein Bilderbuch | B70: Schmidhammer, Arpad; Holst, Adolf | C70: Kinder- und Jugendbücher | D70: Scholz | E70: monograph; text | F70: PPN770464904 | G70: PPN57409041X | H70: http://resolver.staatsbibliothek-berlin.de/SBB000104A500000000 | I70: ger | J70: 1913 | K70: WegehauptDigital | L70: Mainz | M70: https://content.staatsbibliothek-berlin.de/dc/770464904.ocr.zip | N70: yes
A71: Nun rath' einmal!; Illustrirtes Räthselbuch für artige Kinder | B71: Gerstenberg, Karl | C71: Kinder- und Jugendbücher | D71: Schreiber | E71: monograph; text | F71: PPN745435734 | G71: PPN558101321 | H71: http://resolver.staatsbibliothek-berlin.de/SBB0000D6AE00000000 | I71: ger | J71: 1878 | K71: WegehauptDigital | L71: Eßlingen | M71: https://content.staatsbibliothek-berlin.de/dc/745435734.ocr.zip | N71: yes
A72: Der Thiergarten zu Lilienthal; Ein unterhaltendes naturgeschichtliches Bilder- und Lesebuch für die Jugend ... (Mit 12 großen u. 82 kleineren Abbildungen in schönem Farbendruck.) | B72: Beumer, Philipp Jakob | C72: Kinder- und Jugendbücher; Historische Drucke | D72: Bagel | E72: monograph; text | F72: PPN770507050 | G72: PPN44513125X | H72: http://resolver.staatsbibliothek-berlin.de/SBB000104E500000000 | I72: ger | J72: 1850 | K72: WegehauptDigital | L72: Wesel | M72: https://content.staatsbibliothek-berlin.de/dc/770507050.ocr.zip | N72: yes
A73: Zoologie du jeune age ou histoire naturelle des animaux; écrite pour la jeunesse | B73: Lereboullet, Auguste | C73: Kinder- und Jugendbücher; Historische Drucke | D73: Derivaux | E73: monograph; text | F73: PPN749918349 | G73: PPN280187092 | H73: http://resolver.staatsbibliothek-berlin.de/SBB0000E19400000000 | I73: fre | J73: 1860 | K73: WegehauptDigital | L73: Strasbourg | M73: https://content.staatsbibliothek-berlin.de/dc/749918349.ocr.zip | N73: yes
A74: Naturgeschichte der reißenden Thiere; Thierschilderungen für Freunde der Natur u. die Jugend aller Stände ; Mit 36 colorierten Taf. Original-Abb. | B74: Mann, Gustav | C74: Kinder- und Jugendbücher; Historische Drucke | D74: Schweizerbart | E74: monograph; text | F74: PPN757120954 | G74: PPN566464845 | H74: http://resolver.staatsbibliothek-berlin.de/SBB0000ECEC00000000 | I74: ger | J74: 1857 | K74: WegehauptDigital | L74: Stuttgart | M74: https://content.staatsbibliothek-berlin.de/dc/757120954.ocr.zip | N74: yes
A75: Die Naturgeschichte für Kinder und Elementarschüler; oder erster Unterricht über das Mineralreich, Pflanzenreich und Thierreich. Mit über 300 color. Abb. | C75: Kinder- und Jugendbücher | D75: Schreiber & Schill | E75: monograph; text | F75: PPN770201407 | G75: PPN389491020 | H75: http://resolver.staatsbibliothek-berlin.de/SBB0001039700000000 | I75: ger | J75: 1855 | K75: WegehauptDigital | L75: Stuttgart [u.a.] | M75: https://content.staatsbibliothek-berlin.de/dc/770201407.ocr.zip | N75: yes
A76: Neuer Orbis Pictus für die Jugend oder Schauplatz der Natur, der Kunst und des Menschenlebens in 322 lithographischen Abbildungen mit genauer Erklärung in deutscher, lateinischer, französischer und englischer Sprache | B76: Gailer, Jacob E.; Comenius, Johann Amos | C76: Kinder- und Jugendbücher; Historische Drucke | D76: Mäcken | E76: monograph; text | F76: PPN767066812 | G76: PPN230802753 | H76: http://resolver.staatsbibliothek-berlin.de/SBB0000F20600000000 | I76: eng | J76: 1835 | K76: WegehauptDigital | L76: Reutlingen | M76: empty | N76: no
A77: Biblische Naturgeschichte für Schulen und Familien | B77: Barth, Christian Gottlob | C77: Kinder- und Jugendbücher | D77: Vereinsbuchhandl. [usw.] | E77: monograph; text | F77: PPN743860241 | G77: PPN54707901X | H77: http://resolver.staatsbibliothek-berlin.de/SBB0000D35E00000000 | I77: ger | J77: 1874 | K77: WegehauptDigital | L77: Calw | M77: https://content.staatsbibliothek-berlin.de/dc/743860241.ocr.zip | N77: yes
A78: Die Schwarzwald-Reise; Eine christliche Erzählung und zugleich eine landschaftliche Beschreibung, natürliche Geographie und Geognosie des würtembergischen Schwarzwaldes ; Für die Jugend der höheren Stände | B78: Schwarz, Eduard | C78: Kinder- und Jugendbücher; Historische Drucke | D78: Balz | E78: monograph; text | F78: PPN77096351X | G78: PPN319610543 | H78: http://resolver.staatsbibliothek-berlin.de/SBB00010A1100000000 | I78: ger | J78: 1836 | K78: WegehauptDigital | L78: Stuttgart | M78: empty | N78: no
A79: Der aufrichtige Kalendermann; Ein gar kurioses und nützliches Buch Für die Jugend und den gemeinen Bürger und Bauersmann verfertiget | B79: Steinbeck, Christoph Gottlieb | C79: Kinder- und Jugendbücher; Historische Drucke; VD18 digital | D79: Steinbeck; Fleischer | E79: monograph; text | F79: PPN766725251 | G79: PPN663601738 | H79: http://resolver.staatsbibliothek-berlin.de/SBB0000F0B200000000 | I79: ger | J79: 1792 | K79: WegehauptDigital; VD18 digital | L79: Langenberg ohnweit Gera; Leipzig | M79: empty | N79: no
A80: Naturgeschichte des Pflanzenreiches in Bildern; nach der Anordnung des allgemein bekannten u. beliebten Lehrbuchs der Naturgeschichte von G[otthilf] H[einrich] v. Schubert | B80: Schubert, Gotthilf Heinrich; Hochstetter, Christian Ferdinand | C80: Kinder- und Jugendbücher; Historische Drucke | D80: Schreiber | E80: monograph; text | F80: PPN749900172 | G80: PPN568822358 | H80: http://resolver.staatsbibliothek-berlin.de/SBB0000E16800000000 | I80: fre | J80: 1865 | K80: WegehauptDigital | L80: Eßlingen a. N. | M80: https://content.staatsbibliothek-berlin.de/dc/749900172.ocr.zip | N80: yes
A81: Die Hausthiere nebst ihrer Beschäftigung und Verwendung; Ein nützliches und unterhaltendes Bilderbuch für die Jugend ; Mit 80 Haupt- und Nebenbildern und erklärendem Text | C81: Kinder- und Jugendbücher; Historische Drucke | D81: Zeh | E81: monograph; text | F81: PPN756434564 | G81: PPN559169582 | H81: http://resolver.staatsbibliothek-berlin.de/SBB0000EA8E00000000 | I81: ger | J81: 1846 | K81: WegehauptDigital | L81: Nürnberg | M81: empty | N81: no
A82: Die Jugendspiele; ein Leitfaden bei der Einführung und Übung von Turn- und Jugendspielen | B82: Eitner, Gustav | C82: Kinder- und Jugendbücher | D82: Voigtländer | E82: monograph; text | F82: PPN745185738 | G82: PPN236366599 | H82: http://resolver.staatsbibliothek-berlin.de/SBB0000D64600000000 | I82: ger | J82: 1890 | K82: WegehauptDigital | L82: Kreuznach [u.a.] | M82: https://content.staatsbibliothek-berlin.de/dc/745185738.ocr.zip | N82: yes
A83: Das Mikroskop; mit 90 Abbildungen | B83: Schertel, Sigmund | C83: Kinder- und Jugendbücher; Historische Drucke | D83: Union Dt. Verlagsges. | E83: monograph; text | F83: PPN741301490 | G83: PPN573714444 | H83: http://resolver.staatsbibliothek-berlin.de/SBB0000CFB500000000 | I83: ger | J83: 1900 | K83: WegehauptDigital | L83: Stuttgart [u.a.] | M83: https://content.staatsbibliothek-berlin.de/dc/741301490.ocr.zip | N83: yes
A84: Naturgeschichte für Kinder | B84: Lippold, Georg Heinrich Christian; Funke, Carl Philipp | C84: Kinder- und Jugendbücher; Historische Drucke | D84: Kummer | E84: monograph; text | F84: PPN769508758 | G84: PPN239889762 | H84: http://resolver.staatsbibliothek-berlin.de/SBB0000F99B00000000 | I84: ger | J84: 1827 | K84: WegehauptDigital | L84: Leipzig | M84: empty | N84: no
A85: Der gewandte Zauberkünstler und Hexenmeister in Familien- und Gesellschaftskreisen; in Darstellung der lehreichsten und unterhaltendsten Kunststücke auf dem Gebiete der natürlichen Magie, der Taschen- und Kartenspieler und der Rechenkunst ; mit Bildern | B85: Ortleb, Alexander | C85: Kinder- und Jugendbücher; Historische Drucke | D85: Linser | E85: monograph; text | F85: PPN745827632 | G85: PPN569413095 | H85: http://resolver.staatsbibliothek-berlin.de/SBB0000D75C00000000 | I85: ger | J85: 1897 | K85: WegehauptDigital | L85: Pankow-Berlin | M85: https://content.staatsbibliothek-berlin.de/dc/745827632.ocr.zip | N85: yes
A86: Der Schmetterlingsfreund; Beschreibung d. vorzügl. mitteleurop. Schmetterlinge nebst Anl. dieselben zu fangen, deren Puppen u. Raupen aufzuziehen u. eine Samml. anzulegen ; für d. Jugend verf. ; mit 236 Abb. auf 23 Taf. | B86: Hofmann, Ernst | C86: Kinder- und Jugendbücher | D86: Hoffmann | E86: monograph; text | F86: PPN769120490 | G86: PPN559723946 | H86: http://resolver.staatsbibliothek-berlin.de/SBB0000F8B000000000 | I86: ger | J86: 1883 | K86: WegehauptDigital | L86: Stuttgart | M86: https://content.staatsbibliothek-berlin.de/dc/769120490.ocr.zip | N86: yes
A87: Naturgeschichte Der Amphibien, Fische, Weich- und Schaalenthiere, Insekten, Würmer und Strahlenthiere in Bildern ... zum Anschauungs-Unterricht für die Jugend ... nach der ...Naturgeschichte für Schulen; mit erklärendem Texte in deutscher und französischer Sprache | B87: Schubert, Gotthilf Heinrich | C87: Kinder- und Jugendbücher; Historische Drucke | D87: Schreiber & Schill | E87: monograph; text | F87: PPN769048684 | G87: PPN568791290 | H87: http://resolver.staatsbibliothek-berlin.de/SBB0000F82200000000 | I87: ger | J87: 1849 | K87: WegehauptDigital | L87: Eßlingen; Stuttgart | M87: empty | N87: no
A88: Wald und Meer; Schilderungen aus dem Naturleben der Thiere und Pflanzen | B88: Ramberg, Heinrich; Jury, Wilhelm; Schasler, Max | C88: Kinder- und Jugendbücher; Historische Drucke | D88: Hasselberg | E88: monograph; text | F88: PPN749886765 | G88: PPN27954653X | H88: http://resolver.staatsbibliothek-berlin.de/SBB0000E15200000000 | I88: ger | J88: 1853 | K88: WegehauptDigital | L88: Berlin | M88: https://content.staatsbibliothek-berlin.de/dc/749886765.ocr.zip | N88: yes
A89: Naturhistorisches Bilder- und Lese-Buch oder Erzählungen über Gegenstände aus den drei Reichen der Natur; Nebst 300 illuminirten Abbildungen von [Konrad] Horny und einer kurzen Erklärung derselben in Versen | B89: Horny, Konrad; Glatz, Jakob | C89: Kinder- und Jugendbücher; Historische Drucke | D89: Frommann | E89: monograph; text | F89: PPN769046053 | G89: PPN371007631 | H89: http://resolver.staatsbibliothek-berlin.de/SBB0000F81F00000000 | I89: ger | J89: 1803 | K89: WegehauptDigital | L89: Jena | M89: empty | N89: no
A90: Das Spiel im Zimmer; eine reichhaltige Sammlung ausgewählter Spiele zum Gebrauche für jung und alt, für den Einzelnen, wie für kleinere und größere Kreise | B90: Mittenzwey, L. | C90: Kinder- und Jugendbücher | D90: Merseburger | E90: monograph; text | F90: PPN745139965 | G90: PPN567083055 | H90: http://resolver.staatsbibliothek-berlin.de/SBB0000D5E900000000 | I90: ger | J90: 1887 | K90: WegehauptDigital | L90: Leipzig | M90: https://content.staatsbibliothek-berlin.de/dc/745139965.ocr.zip | N90: yes
A91: Der Weltumsegler. Oder Reise durch alle fünf Theile der Erde mit vorzüglicher Hinsicht auf ihre Bewohner, auf die Schönheiten und Merkwürdigkeiten der Natur und Kunst [et]c.; Zum Selbstunterricht der Jugend zweckmäßig abgefasst | B91: Schäfer, Daniel F. | C91: Kinder- und Jugendbücher | D91: Oehmigke | E91: multivolume_work; text | F91: PPN727852981 | G91: PPN032135513 | H91: http://resolver.staatsbibliothek-berlin.de/SBB0001554600000000 | I91: ger | J91: 1801 | K91: WegehauptDigital | L91: Berlin | M91: empty | N91: no
A92: Reise durch das Berner Oberland nach Unterwalden; für die Jugend beschrieben | B92: Lory, G.; Burgdorfer, D.; Meisner, Friedrich | C92: Kinder- und Jugendbücher | D92: Burgdorfer | E92: volume; text | F92: PPN770944965 | G92: PPN282315799 | H92: http://resolver.staatsbibliothek-berlin.de/SBB000109F000020000 | I92: ger | J92: 1821 | K92: WegehauptDigital | L92: Bern | M92: empty | N92: no
A93: Conversations-Lexicon für die Jugend | C93: Kinder- und Jugendbücher; Historische Drucke | D93: Goedsche | E93: volume; text | F93: PPN766562786 | G93: PPN562017402 | H93: http://resolver.staatsbibliothek-berlin.de/SBB0000EF8800020000 | I93: ger | J93: 1840 | K93: WegehauptDigital | L93: Meissen | M93: empty | N93: no
A94: Bilderbuch zum Nutzen und Vergnügen der Jugend; enthaltend eine angenehme Sammlung von Thieren, Pflanzen, Blumen, Früchten, Mineralien, Trachten und allerhand andern unterrichtenden Gegenständen aus dem Reiche der Natur, der Künste und Wissenschaften ; alle nach den besten Originalen gewählt gestochen, und mit einer kurzen wissenschaftlichen und den Verstandeskräften der Jugend angemessenen Erklärung begleitet | B94: Bertuch, Friedrich Justin | C94: Kinder- und Jugendbücher; Historische Drucke | D94: Bohmann | E94: multivolume_work; text | F94: PPN803797397 | G94: PPN364483261 | H94: http://resolver.staatsbibliothek-berlin.de/SBB0001793700000000 | I94: ger | J94: 1822 | K94: WegehauptDigital | L94: Prag | M94: empty | N94: no
A95: Der kleine Physiker, oder Unterhaltungen über natürliche Dinge, für Kinder | B95: Höpfner, Adolf Friedrich | C95: Kinder- und Jugendbücher | D95: Keyser | E95: volume; text | F95: PPN746626002 | G95: PPN746625758 | H95: http://resolver.staatsbibliothek-berlin.de/SBB0000DB6F00020000 | I95: ger | J95: 1804 | K95: WegehauptDigital | L95: Erfurt | M95: empty | N95: no
A96: Der technologische Jugendfreund oder Unterhaltende Wanderungen in die Werkstätte der Künstler und Handwerker, zur nöthigen Kenntniß derselben | B96: Blasche, Bernhard Heinrich | C96: Kinder- und Jugendbücher | D96: Wilmans | E96: volume; text | F96: PPN770196195 | G96: PPN335885187 | H96: http://resolver.staatsbibliothek-berlin.de/SBB0001038200010000 | I96: ger | J96: 1804 | K96: WegehauptDigital | L96: Frankfurt am Mayn | M96: empty | N96: no
A97: Tempel der Natur und Kunst | B97: Hirschmann, C. A. | C97: Kinder- und Jugendbücher | D97: Tauchnitz | E97: volume; text | F97: PPN781903688 | G97: PPN563410795 | H97: http://resolver.staatsbibliothek-berlin.de/SBB0001568700050000 | I97: ger | J97: 1805 | K97: WegehauptDigital | L97: Leipzig | M97: empty | N97: no
A98: Der mechanische Jugendfreund oder faßliche und unterhaltende Darstellung der Lehre vom Gleichgewicht und der Bewegung, mit der Beschreibung der dazu gehörigen Maschinen und selbst mit Beyfügung mancher belustigenden mechanischen Kunststücke; Zweyter Theil ; Mit sieben Kupfertafeln | B98: Poppe, Johann Heinrich Moritz | C98: Kinder- und Jugendbücher; Historische Drucke | D98: Wilmans | E98: volume; text | F98: PPN746345666 | G98: PPN236461788 | H98: http://resolver.staatsbibliothek-berlin.de/SBB0000D8D300010000 | I98: ger | J98: 1821 | K98: WegehauptDigital | L98: Frankfurt am Main | M98: empty | N98: no
A99: Naturgeschichte für die deutsche Jugend | B99: Hochstetter, Christian Ferdinand; Gebauer, Christian August | C99: Kinder- und Jugendbücher; Historische Drucke | D99: Löflund | E99: volume; text | F99: PPN769087779 | G99: PPN557898129 | H99: http://resolver.staatsbibliothek-berlin.de/SBB0000F85900010000 | I99: ger | J99: 1829 | K99: WegehauptDigital | L99: Stuttgart | M99: empty | N99: no
A100: Spiel und Sport; das Buch der gesellschaftlichen Unterhaltungen und Vergnügungen, der körperlichen Uebungen, ritterlichen Erholungen und Künste ; in zwei Abtheilungen | B100: Georgens, Jan Daniel | C100: Kinder- und Jugendbücher | D100: Spamer | E100: multivolume_work; text | F100: PPN745169724 | G100: PPN369019458 | H100: http://resolver.staatsbibliothek-berlin.de/SBB0000D62500000000 | I100: ger | J100: 1882 | K100: WegehauptDigital | L100: Leipzig; Berlin | M100: empty | N100: no
...

Sheet types
A3: Zeilenbeschriftungen | B3: Anzahl von type
A4: monograph; text | B4: 888
A5: no | B5: 409
A6: yes | B6: 479
A7: multivolume_work; text | B7: 288
A8: no | B8: 288
A9: periodical; text | B9: 1
A10: no | B10: 1
A11: periodical_volume; text | B11: 7
A12: no | B12: 7
A13: volume; text | B13: 825
A14: no | B14: 622
A15: yes | B15: 203
A16: (Leer)
A17: (Leer)
A18: Gesamtergebnis | B18: 2009

Sheet monographs and volumes
A1: title | B1: creator | C1: subject | D1: publisher | E1: type | F1: digital object identifier | G1: physical object identifier | H1: URL | I1: language | J1: date | K1: relation | L1: coverage | M1: OCR URL | N1: OCR found?
A2: Abrégé de toutes les sciences, ou encyclopédie des enfants; mise dans un nouvel ordre,... | B2: Buqcellos, ...; Blocquel, Simon | C2: Kinder- und Jugendbücher; Historische Drucke | D2: Delarue ;; Castiaux | E2: monograph; text | F2: PPN766849139 | G2: PPN548262071 | H2: http://resolver.staatsbibliothek-berlin.de/SBB0000F13000000000 | I2: fre | J2: 1816 | K2: WegehauptDigital | L2: Paris; Lille | M2: empty | N2: no
A3: Naturgeschichte für Kinder | B3: Raff, Georg Christian | C3: Kinder- und Jugendbücher; Historische Drucke | D3: Sammer | E3: monograph; text | F3: PPN749770333 | G3: PPN279536941 | H3: http://resolver.staatsbibliothek-berlin.de/SBB0000E0AE00000000 | I3: ger | J3: 1846 | K3: WegehauptDigital | L3: Wien | M3: empty | N3: no
A4: Die Entstehung der Erde | B4: Kranz, Wilhelm; Meyer, Max Wilhelm | C4: Kinder- und Jugendbücher; Historische Drucke | D4: Paetel | E4: monograph; text | F4: PPN741297272 | G4: PPN276525892 | H4: http://resolver.staatsbibliothek-berlin.de/SBB0000CFAB00000000 | I4: ger | J4: 1907 | K4: WegehauptDigital | L4: Berlin | M4: https://content.staatsbibliothek-berlin.de/dc/741297272.ocr.zip | N4: yes
A5: Die Schulwerkstatt; ein Leitfaden zur Einführung der technischen Arbeiten in die Schule | B5: Barth, Ernst; Niederley, W. | C5: Kinder- und Jugendbücher; Historische Drucke | D5: Velhagen & Klasing | E5: monograph; text | F5: PPN745116574 | G5: PPN453868991 | H5: http://resolver.staatsbibliothek-berlin.de/SBB0000D59B00000000 | I5: ger | J5: 1882 | K5: WegehauptDigital | L5: Bielefeld [u.a.] | M5: https://content.staatsbibliothek-berlin.de/dc/745116574.ocr.zip | N5: yes
A6: Der junge Eisenbahnbauer; eine Anleitung zur Selbstherstellung von Modelleisenbahnen ; mit 118 Abb. | B6: Hermuth, Paul | C6: Kinder- und Jugendbücher; Historische Drucke | D6: Union Dt. Verl.-Gesellsch. | E6: monograph; text | F6: PPN744069432 | G6: PPN559338228 | H6: http://resolver.staatsbibliothek-berlin.de/SBB0000D52F00000000 | I6: ger | J6: 1916 | K6: WegehauptDigital | L6: Stuttgart [u.a.] | M6: https://content.staatsbibliothek-berlin.de/dc/744069432.ocr.zip | N6: yes
A7: Neuer Räthselschatz; für die Jugend zur Übung im Denken und zur belehrenden Unterhaltung | B7: Schäffer, W. | C7: Kinder- und Jugendbücher; Historische Drucke | D7: Oehmigke | E7: monograph; text | F7: PPN745271243 | G7: PPN573465517 | H7: http://resolver.staatsbibliothek-berlin.de/SBB0000D67F00000000 | I7: ger | J7: 1865 | K7: WegehauptDigital | L7: Neu-Ruppin | M7: https://content.staatsbibliothek-berlin.de/dc/745271243.ocr.zip | N7: yes
A8: Wander- und Spielbüchlein für Schüler und Schülerinnen | B8: Matzdorf, Paul | C8: Kinder- und Jugendbücher | D8: Strauch | E8: monograph; text | F8: PPN745123694 | G8: PPN56682809X | H8: http://resolver.staatsbibliothek-berlin.de/SBB0000D5AD00000000 | I8: ger | J8: 1910 | K8: WegehauptDigital | L8: Leipzig | M8: https://content.staatsbibliothek-berlin.de/dc/745123694.ocr.zip | N8: yes
A9: Causeries sur la science; illustrées de 94 gravures | B9: Tissandier, Gaston | C9: Kinder- und Jugendbücher; Historische Drucke | D9: Hachette | E9: monograph; text | F9: PPN745272312 | G9: PPN578011344 | H9: http://resolver.staatsbibliothek-berlin.de/SBB0000D68300000000 | I9: fre | J9: 1880 | K9: WegehauptDigital | L9: Paris | M9: https://content.staatsbibliothek-berlin.de/dc/745272312.ocr.zip | N9: yes
A10: Der unerschöpfliche Maître de Plaisir; oder die Kunst, in allen Jahreszeiten, im Freien und zu Hause, so wie an allen nur denkbaren Freudentagen die unterhaltendsten und belustigendsten Parthieen anzuordnen ; Enthaltend die besten Spiele, Lieder, Declamir- und Kunststücke, Räthsel, Charaden [et]c. Ein unentbehrliches Haus- und Handbuch für alle lebensfrohe deutsche Familien | C10: Kinder- und Jugendbücher; Historische Drucke | D10: Voigt | E10: monograph; text | F10: PPN767042255 | G10: PPN280073852 | H10: http://resolver.staatsbibliothek-berlin.de/SBB0000F1B700000000 | I10: ger | J10: 1822 | K10: WegehauptDigital | L10: Nordhausen; Sondershausen | M10: empty | N10: no
A11: Im Grünen oder Die kleinen Pflanzenfreunde; kleine Erzählungen aus dem Pflanzenreich | B11: Wagner, Hermann | C11: Kinder- und Jugendbücher | D11: Spamer | E11: monograph; text | F11: PPN743675703 | G11: PPN578788829 | H11: http://resolver.staatsbibliothek-berlin.de/SBB0000D31400000000 | I11: ger | J11: 1878 | K11: WegehauptDigital | L11: Leipzig | M11: https://content.staatsbibliothek-berlin.de/dc/743675703.ocr.zip | N11: yes
A12: Das Buch der Gesellschaftsspiele | B12: Weller, Hermine | C12: Kinder- und Jugendbücher | D12: Fischer | E12: monograph; text | F12: PPN745213553 | G12: PPN581117719 | H12: http://resolver.staatsbibliothek-berlin.de/SBB0000D65A00000000 | I12: ger | J12: 1910 | K12: WegehauptDigital | L12: Dresden | M12: https://content.staatsbibliothek-berlin.de/dc/745213553.ocr.zip | N12: yes
A13: Der gelehrte Spielkamerad; Anleitung für kleine Physiker, Chemiker, Botaniker und Naturfreunde zum Experimentieren, zur Anlage von Pflanzen-, Stein-, Muschel-, Insekten-, Schmetterling-, Vogel-, Briefmarken-Sammlungen ect. sowie zur Pflege der Hausthiere und des Hausgartens ; ein Supplement zum "Spielbuch für Knaben" | B13: Wagner, Hermann | C13: Kinder- und Jugendbücher | D13: Spamer | E13: monograph; text | F13: PPN74270906X | G13: PPN578814706 | H13: http://resolver.staatsbibliothek-berlin.de/SBB0000D2AA00000000 | I13: ger | J13: 1877 | K13: WegehauptDigital | L13: Leipzig | M13: https://content.staatsbibliothek-berlin.de/dc/74270906X.ocr.zip | N13: yes
A14: Des fleißigen Mädchens Koch-Büchlein für die Puppen-Küche | C14: Kinder- und Jugendbücher; Historische Drucke | D14: Meisel | E14: monograph; text | F14: PPN745432069 | G14: PPN278721036 | H14: http://resolver.staatsbibliothek-berlin.de/SBB0000D6A800000000 | I14: ger | J14: 1876 | K14: WegehauptDigital | L14: Leipzig; Herisau; Stuttgart | M14: https://content.staatsbibliothek-berlin.de/dc/745432069.ocr.zip | N14: yes
A15: Naturgeschichte für Kinder, von M. Georg Christian Raff, ordentlichen Lehrer der Geschichte und Geographie auf dem Lyceum zu Göttingen. Mit vierzehn Kupfertafeln | B15: Raff, Georg Christian | C15: Kinder- und Jugendbücher; Historische Drucke | E15: monograph; text | F15: PPN769119182 | G15: PPN571683770 | H15: http://resolver.staatsbibliothek-berlin.de/SBB0000F8A900000000 | I15: ger | J15: 1802 | K15: WegehauptDigital | L15: Frankfurt; Leipzig | M15: empty | N15: no
A16: Kleine Bilderschule für die Jugend | B16: Hausius, Karl Gottlob | C16: Kinder- und Jugendbücher; Historische Drucke | D16: Voß | E16: monograph; text | F16: PPN757417825 | G16: PPN55916422X | H16: http://resolver.staatsbibliothek-berlin.de/SBB0000ED8900000000 | I16: ger | J16: 1807 | K16: WegehauptDigital | L16: Leipzig | M16: empty | N16: no
A17: Vollständiges Giftbuch oder Unterricht, die Giftpflanzen, Giftminerale und Giftthiere kennen zu lernen, und Gesundheit und Leben gegen Vergiftungs-Gefahren sicher zu stellen | C17: Kinder- und Jugendbücher | D17: Voigt | E17: monograph; text | F17: PPN770137474 | G17: PPN406020620 | H17: http://resolver.staatsbibliothek-berlin.de/SBB0001031A00000000 | I17: ger | J17: 1817 | K17: WegehauptDigital | L17: Sondershausen | M17: empty | N17: no
A18: Schneiders Typen-Atlas; naturwissenschaftlich-geographischer Hand-Atlas für Schule und Haus | B18: Schneider, Oskar; Claudius, W.; Leutemann, H.; Mützel, G.; Seidel, C. F. | C18: Kinder- und Jugendbücher | D18: Meinhold | E18: monograph; text | F18: PPN743969359 | G18: PPN574227601 | H18: http://resolver.staatsbibliothek-berlin.de/SBB0000D4C500000000 | I18: ger | J18: 1885 | K18: WegehauptDigital | L18: Dresden | M18: https://content.staatsbibliothek-berlin.de/dc/743969359.ocr.zip | N18: yes
A19: Das Buch wunderbarer Erfindungen; in Schilderungen f. d. reifere Jugend : mit 125 Abb. u. 1 Titelbild. | B19: Thomas, Louis | C19: Kinder- und Jugendbücher; Historische Drucke | D19: Spamer | E19: monograph; text | F19: PPN756689090 | G19: PPN578154765 | H19: http://resolver.staatsbibliothek-berlin.de/SBB0000EBC100000000 | I19: ger | J19: 1860 | K19: WegehauptDigital | L19: Leipzig | M19: https://content.staatsbibliothek-berlin.de/dc/756689090.ocr.zip | N19: yes
A20: Naturgeschichte der Vögel; mit besonderer Berücksichtigung der in Deutschland vorkommenden Vögel und Belehrung über Zucht und Wartung der Haus- und Stubenvögel | B20: Abendroth, Carl | C20: Kinder- und Jugendbücher | D20: Baensch | E20: monograph; text | F20: PPN744053714 | G20: PPN538752823 | H20: http://resolver.staatsbibliothek-berlin.de/SBB0000D51E00000000 | I20: ger | J20: 1870 | K20: WegehauptDigital | L20: Leipzig | M20: https://content.staatsbibliothek-berlin.de/dc/744053714.ocr.zip | N20: yes
A21: Abrégé de toutes les sciences à l'usage des enfans de six ans jusqu' a douze; on y a joint un abrégé de l'histoire de Brandebourg | B21: Formey, Jean-Henri-Samuel | C21: Kinder- und Jugendbücher; Historische Drucke | D21: Horvath | E21: monograph; text | F21: PPN76623858X | G21: PPN557396433 | H21: http://resolver.staatsbibliothek-berlin.de/SBB0000EE5000000000 | I21: fre | J21: 1803 | K21: WegehauptDigital | L21: Potsdam | M21: empty | N21: no
A22: Jagden-Bilderbuch für die liebe Jugend; mit 9 lithographirten Darstellungen | C22: Kinder- und Jugendbücher | E22: monograph; text | F22: PPN770079113 | G22: PPN491349475 | H22: http://resolver.staatsbibliothek-berlin.de/SBB000102A700000000 | I22: ger | J22: 1860 | K22: WegehauptDigital | L22: [S.l.] | M22: https://content.staatsbibliothek-berlin.de/dc/770079113.ocr.zip | N22: yes
A23: Neues und bewährtes illustriertes Kochbuch für alle Stände; zuverlässige Anleitung zur Bereitung der verschiedenartigsten Speisen, Backwerke, Getränke etc. ; nach eigener, vieljähriger Erfahrung | B23: Davithis, H. | C23: Kinder- und Jugendbücher; Historische Drucke | D23: Enßlin und Laiblin | E23: monograph; text | F23: PPN745127495 | G23: PPN278540538 | H23: http://resolver.staatsbibliothek-berlin.de/SBB0000D5C100000000 | I23: ger | J23: 1905 | K23: WegehauptDigital | L23: Reutlingen | M23: https://content.staatsbibliothek-berlin.de/dc/745127495.ocr.zip | N23: yes
A24: An der Werkbank; Anleitung zur Handfertigkeit mit besonderer Berücksichtigung der Herstellung physikalischer Apparate ; für mittlere und reife Schüler | B24: Gscheidlen, Emanuel | C24: Kinder- und Jugendbücher; Historische Drucke | D24: Teubner | E24: monograph; text | F24: PPN745118615 | G24: PPN223999733 | H24: http://resolver.staatsbibliothek-berlin.de/SBB0000D59F00000000 | I24: ger | J24: 1912 | K24: WegehauptDigital | L24: Berlin; Leipzig | M24: https://content.staatsbibliothek-berlin.de/dc/745118615.ocr.zip | N24: yes
A25: Die Schöpfung der Erde; die Urwelt und die Urgeschöpfe bis zum Auftreten des Menschen ; Blicke in das Erdinnere ; Wanderungen in die Gebirgswelt, namentlich unsres Veterlandes, nach Kreuz und Quer ; mit reiferen Schülern unternommen | B25: Hintze, Eduard | C25: Kinder- und Jugendbücher | D25: Spamer | E25: monograph; text | F25: PPN742493695 | G25: PPN341499900 | H25: http://resolver.staatsbibliothek-berlin.de/SBB0000D1BE00000000 | I25: ger | J25: 1885 | K25: WegehauptDigital | L25: Leipzig, Berlin | M25: https://content.staatsbibliothek-berlin.de/dc/742493695.ocr.zip | N25: yes
A26: Der Weltspiegel; das Wissenswürdigste vom Weltgebäude, von der Erde, von den Völkern der Erde | B26: Hoffmann, Friedrich | C26: Kinder- und Jugendbücher; Historische Drucke | D26: Schmidt & Spring; Lithographische Anstalt von Engelhorn und Hochdanz | E26: monograph; text | F26: PPN766156990 | G26: PPN279154607 | H26: http://resolver.staatsbibliothek-berlin.de/SBB0000EE1D00000000 | I26: ger | J26: 1844 | K26: WegehauptDigital | L26: Stuttgart; Stuttgart | M26: empty | N26: no
A27: Naturgeschichte; der Jugend gewidmet | B27: Wagner, Hermann | C27: Kinder- und Jugendbücher | D27: Hoffmann | E27: monograph; text | F27: PPN770457983 | G27: PPN408013931 | H27: http://resolver.staatsbibliothek-berlin.de/SBB0001049700000000 | I27: ger | J27: 1870 | K27: WegehauptDigital | L27: Stuttgart | M27: https://content.staatsbibliothek-berlin.de/dc/770457983.ocr.zip | N27: yes
A28: Lehrbuch der Sternkunde; für Schulen und zum Selbstunterrichte | B28: Schubert, Gotthilf Heinrich | C28: Kinder- und Jugendbücher; Historische Drucke | D28: Weber | E28: monograph; text | F28: PPN750739150 | G28: PPN311822029 | H28: http://resolver.staatsbibliothek-berlin.de/SBB0000E3CF00000000 | I28: ger | J28: 1832 | K28: WegehauptDigital | L28: München | M28: empty | N28: no
A29: Leichte Künsteleien zum Vergnügen und zum Nutzen für Kinder und Nichtkinder; Ein Buch mannigfaltigen Inhaltes | B29: Rockstroh, Heinrich | C29: Kinder- und Jugendbücher; Historische Drucke | D29: Wittich | E29: monograph; text | F29: PPN767041380 | G29: PPN556113098 | H29: http://resolver.staatsbibliothek-berlin.de/SBB0000F1B600000000 | I29: ger | J29: 1819 | K29: WegehauptDigital | L29: Berlin | M29: empty | N29: no
A30: Europäische Bilder und Skizzen; zur Belehrung für die reifere Jugend | B30: Hoffmann, Julius; Hosemann, Theodor | C30: Kinder- und Jugendbücher | D30: Trewendt | E30: monograph; text | F30: PPN771014600 | G30: PPN265186358 | H30: http://resolver.staatsbibliothek-berlin.de/SBB00010A6400000000 | I30: ger | J30: 1858 | K30: WegehauptDigital | L30: Breslau | M30: https://content.staatsbibliothek-berlin.de/dc/771014600.ocr.zip | N30: yes
A31: Malerische Naturgeschichte der drei Reiche für Schule und Haus; Mit besonderer Beziehung auf das practische Leben bearbeitet von F[riedrich] W[ilhelm] Lindner; unter Mitwirkung von Dr. Fr. H. A. Lachmann | B31: Lachmann, Fr. H. A.; Lindner, Friedrich Wilhelm | C31: Kinder- und Jugendbücher; Historische Drucke | D31: Oehme & Müller | E31: monograph; text | F31: PPN770463371 | G31: PPN42077016X | H31: http://resolver.staatsbibliothek-berlin.de/SBB000104A200000000 | I31: ger | J31: 1840 | K31: WegehauptDigital | L31: Braunschweig | M31: empty | N31: no
A32: Allerlei schöne Bilderrätsel für Jung und Alt | C32: Kinder- und Jugendbücher; Historische Drucke | E32: monograph; text | F32: PPN74513548X | G32: PPN30847046X | H32: http://resolver.staatsbibliothek-berlin.de/SBB0000D5D100000000 | I32: ger | K32: WegehauptDigital | M32: https://content.staatsbibliothek-berlin.de/dc/74513548X.ocr.zip | N32: yes
A33: Der Hausbau; oder erste Begriffe von Staat und den vorzüglichsten Ständen, Handwerken, Fabriken, Künsten, Wissenschaften u. d. gl. für Kinder | B33: Werlich, August Karl Friedrich | C33: Kinder- und Jugendbücher; Historische Drucke | D33: Juniussische Buchhandlung | E33: monograph; text | F33: PPN756639891 | G33: PPN579566781 | H33: http://resolver.staatsbibliothek-berlin.de/SBB0000EB7900000000 | I33: ger | J33: 1804 | K33: WegehauptDigital | L33: Leipzig | M33: empty | N33: no
A34: Gemählde aus der Natur und dem Menschenleben, in einer Reihe von Schilderungen merkwürdiger Naturerscheinungen und gefahrvoller Reiseabentheuer; zum Nutzen und Vergnügen der Jugend | B34: Albertus, D. J. C. | C34: Kinder- und Jugendbücher | D34: Kaiser | E34: monograph; text | F34: PPN781283116 | G34: PPN541529498 | H34: http://resolver.staatsbibliothek-berlin.de/SBB0001555D00000000 | I34: ger | J34: 1830 | K34: WegehauptDigital | L34: Grätz | M34: empty | N34: no
A35: Kurzer Unterricht in der Naturwissenschaft für die Jugend | B35: Uihlein, Joseph | C35: Kinder- und Jugendbücher; Historische Drucke | D35: Andreä | E35: monograph; text | F35: PPN770157742 | G35: PPN366080202 | H35: http://resolver.staatsbibliothek-berlin.de/SBB0001033900000000 | I35: ger | J35: 1810 | K35: WegehauptDigital | L35: Frankfurt am Main | M35: empty | N35: no
A36: F. Martin's Naturgeschichte für die Jugend beiderlei Geschlechts; mit dreihundert Abbildungen und zwanzig Holzschnitten | B36: Kolb, Christian Friedrich August; Martin, F. | C36: Kinder- und Jugendbücher; Historische Drucke | D36: Schmidt & Spring | E36: monograph; text | F36: PPN741294397 | G36: PPN566740400 | H36: http://resolver.staatsbibliothek-berlin.de/SBB0000CFA500000000 | I36: ger | J36: 1880 | K36: WegehauptDigital | L36: Stuttgart | M36: https://content.staatsbibliothek-berlin.de/dc/741294397.ocr.zip | N36: yes
A37: Aus Werkstatt und Welt; eine Festgabe für die werkthätige Jugend dargereicht von Leipz. Fortbildungsschuldirektoren u.-Lehrern | C37: Kinder- und Jugendbücher; Historische Drucke | D37: Hahn; Schmidt | E37: monograph; text | F37: PPN770851347 | G37: PPN581182618 | H37: http://resolver.staatsbibliothek-berlin.de/SBB0001070300000000 | I37: ger | J37: 1901 | K37: WegehauptDigital | L37: Leipzig; Leipzig | M37: https://content.staatsbibliothek-berlin.de/dc/770851347.ocr.zip | N37: yes
A38: Mittheilungen aus dem Gebiet der Naturkunde und dem Menschenleben für die Jugend ; mit 25 col. Abb. | B38: Maukisch, Heinrich Eduard | C38: Kinder- und Jugendbücher; Historische Drucke | D38: Fischer u. Fuchs | E38: monograph; text | F38: PPN766619389 | G38: PPN566841444 | H38: http://resolver.staatsbibliothek-berlin.de/SBB0000F00A00000000 | I38: ger | J38: 1835 | K38: WegehauptDigital | L38: Leipzig | M38: empty | N38: no
A39: Čudesa bez čudesʹ; malenkaja fizika v priměnenii kʹ zabavamʹ/ sost. A. P. Nečaev. S 172 ris. | B39: Nečaev, A. P. | C39: Kinder- und Jugendbücher | D39: Lukovnikov | E39: monograph; text | F39: PPN742094227 | G39: PPN280334869 | H39: http://resolver.staatsbibliothek-berlin.de/SBB0000D0A100000000 | I39: rus | J39: 1911 | K39: WegehauptDigital | L39: Spb. [St. Petersburg] | M39: https://content.staatsbibliothek-berlin.de/dc/742094227.ocr.zip | N39: yes
A40: Nun rathe einmal!; Räthselbüchlein für Kinder von 5 - 10 Jahren | B40: Flinzer, Fedor | C40: Kinder- und Jugendbücher; Historische Drucke | D40: Focke | E40: monograph; text | F40: PPN745597041 | G40: PPN568651901 | H40: http://resolver.staatsbibliothek-berlin.de/SBB0000D6F200000000 | I40: ger | J40: 1864 | K40: WegehauptDigital | L40: Chemnitz | M40: https://content.staatsbibliothek-berlin.de/dc/745597041.ocr.zip | N40: yes
A41: Räthselkranz für Alt und Jung | B41: Ruhkopf, Julie | C41: Kinder- und Jugendbücher; Historische Drucke | D41: Flemming | E41: monograph; text | F41: PPN74623791X | G41: PPN476384494 | H41: http://resolver.staatsbibliothek-berlin.de/SBB0000D85700000000 | I41: ger | J41: 1861 | K41: WegehauptDigital | L41: Glogau | M41: https://content.staatsbibliothek-berlin.de/dc/74623791X.ocr.zip | N41: yes
A42: Merkwürdige Reisen der Gutmannschen Familie; ein Weihnachts- und Geburtstags-Geschenk für die Jugend | B42: Ramberg, H.; Boettger, G.; Dassel, Chr. | C42: Kinder- und Jugendbücher | D42: Brüder Hahn | E42: monograph; text | F42: PPN746870108 | G42: PPN363821880 | H42: http://resolver.staatsbibliothek-berlin.de/SBB0000DBD600000000 | I42: ger | J42: 1816 | K42: WegehauptDigital | L42: Hannover | M42: empty | N42: no
A43: Recipes | C43: Kinder- und Jugendbücher | D43: Orr | E43: monograph; text | F43: PPN746034628 | G43: PPN279781792 | H43: http://resolver.staatsbibliothek-berlin.de/SBB0000D7DD00000000 | I43: eng | J43: 1883 | K43: WegehauptDigital | L43: Springfield, Mass. | M43: https://content.staatsbibliothek-berlin.de/dc/746034628.ocr.zip | N43: yes
A44: Das Turnen in den Spielen der Mädchen; eine Auswahl nützlicher und passender Jugend- und Bewegungspiele ; zur geistigen und körperlichen Erholung des jüngeren Mädchenalters wie als Beitrag zu einer naturgemäßen Jugenderziehung | B44: Bürkner, Hugo; Kloss, Moritz | C44: Kinder- und Jugendbücher | D44: Schönfeld | E44: monograph; text | F44: PPN770493564 | G44: PPN27843424X | H44: http://resolver.staatsbibliothek-berlin.de/SBB000104D400000000 | I44: ger | J44: 1862 | K44: WegehauptDigital | L44: Dresden | M44: https://content.staatsbibliothek-berlin.de/dc/770493564.ocr.zip | N44: yes
A45: Das Ein-mal-Eins in Bilderpracht, wie es den Kindern Freude macht | B45: Reinhardt, Aug.; Reinhardt, V. | C45: Kinder- und Jugendbücher | D45: Kaufmann | E45: monograph; text | F45: PPN741360802 | G45: PPN572962495 | H45: http://resolver.staatsbibliothek-berlin.de/SBB0000CFF400000000 | I45: ger | J45: 1880 | K45: WegehauptDigital | L45: Dresden | M45: https://content.staatsbibliothek-berlin.de/dc/741360802.ocr.zip | N45: yes
A46: Natur-Paradoxe; ein Buch für die Jugend zur Erklärung von Erscheinungen, die mit der täglichen Erfahrung in Widerspruch zu stehen scheinen ; nach Dr. W. Hampson's 'Paradoxes of nature and science' | B46: Schäffer, C.; Hampson, William | C46: Kinder- und Jugendbücher | D46: Teubner | E46: monograph; text | F46: PPN741671417 | G46: PPN408347201 | H46: http://resolver.staatsbibliothek-berlin.de/SBB0000D04500000000 | I46: ger | J46: 1908 | K46: WegehauptDigital | L46: Leipzig; Berlin | M46: https://content.staatsbibliothek-berlin.de/dc/741671417.ocr.zip | N46: yes
A47: Die Meteorologie in Erklärungen und Erzählungen; ein nützliches und unterhaltendes Lesebuch für die reifere Jugend | B47: Moshamer, Joseph A. | C47: Kinder- und Jugendbücher | D47: Im Verl. der k. k. Schulbücher-Verschleiß-Administration | E47: monograph; text | F47: PPN770192904 | G47: PPN348919875 | H47: http://resolver.staatsbibliothek-berlin.de/SBB0001037500000000 | I47: ger | J47: 1844 | K47: WegehauptDigital | L47: Wien | M47: empty | N47: no
A48: Naturstudien im Hause; Plaudereien in der Dämmerstunde ; ein Buch für die Jugend | B48: Schwindrazheim, O.; Kraepelin, Karl | C48: Kinder- und Jugendbücher | D48: Teubner | E48: monograph; text | F48: PPN742265854 | G48: PPN075438097 | H48: http://resolver.staatsbibliothek-berlin.de/SBB0000D0DF00000000 | I48: ger | J48: 1901 | K48: WegehauptDigital | L48: Leipzig | M48: https://content.staatsbibliothek-berlin.de/dc/742265854.ocr.zip | N48: yes
A49: Peter Parley's Visit to London; during the coronation of Queen Victoria | B49: Viktoria < Großbritannien, Königin>; Parley, Peter | C49: Kinder- und Jugendbücher; Historische Drucke | D49: Tilt | E49: monograph; text | F49: PPN771192134 | G49: PPN27953969X | H49: http://resolver.staatsbibliothek-berlin.de/SBB0001262E00000000 | I49: eng | J49: 1839 | K49: WegehauptDigital | L49: London | M49: empty | N49: no
A50: Die kleinen Gärtner, oder Gartenbeschäftigungen für Kinder; enthält einen deutlichen Unterricht, wie Kinder einen kleinen Garten anlegen, behandeln und abwarten können, ohne dabey einen Gärtner zu Hülfe zu nehmen : mit Kupfern | B50: Poscharsky, Christian Friedrich | C50: Kinder- und Jugendbücher; Historische Drucke | D50: Friese | E50: monograph; text | F50: PPN769382053 | G50: PPN389953334 | H50: http://resolver.staatsbibliothek-berlin.de/SBB0000F96300000000 | I50: ger | J50: 1810 | K50: WegehauptDigital | L50: Pirna | M50: empty | N50: no
A51: Carl der Tausendkünstler, oder: Sammlung einfacher und künstlicher, großentheils neuer mechanischer, chemischer, magnetischer und Kartenkunststücke und arithmetischer Belustigungen zur angenehmen geselligen Unterhaltung | B51: Kerndörffer, Heinrich August | C51: Kinder- und Jugendbücher; Historische Drucke | D51: Cnobloch | E51: monograph; text | F51: PPN766428656 | G51: PPN560665571 | H51: http://resolver.staatsbibliothek-berlin.de/SBB0000EF3700000000 | I51: ger | J51: 1840 | K51: WegehauptDigital | L51: Leipzig | M51: empty | N51: no
A52: Der illustrirte Jugendfreund; Schilderungen des Weltgebäudes und seiner Wunder ; in Bilder aus der Natur, dem Leben der Menschen und der Thiere der Vergangenheit und Gegenwart | B52: Thomas, Louis | C52: Kinder- und Jugendbücher; Historische Drucke | D52: Spamer | E52: monograph; text | F52: PPN767132297 | G52: PPN578175231 | H52: http://resolver.staatsbibliothek-berlin.de/SBB0000F2BB00000000 | I52: ger | J52: 1852 | K52: WegehauptDigital | L52: Leipzig | M52: https://content.staatsbibliothek-berlin.de/dc/767132297.ocr.zip | N52: yes
A53: The Child's guide to knowledge; being a collection of useful and familiar questions and answers on every-day subjects; adapted for young persons, and arranged in the most simple and easy language ; by a Lady | C53: Kinder- und Jugendbücher; Historische Drucke | D53: Simpkin [u.a.] | E53: monograph; text | F53: PPN745137695 | G53: PPN550723854 | H53: http://resolver.staatsbibliothek-berlin.de/SBB0000D5D600000000 | I53: eng | J53: 1871 | K53: WegehauptDigital | L53: London | M53: https://content.staatsbibliothek-berlin.de/dc/745137695.ocr.zip | N53: yes
A54: Kleine Bilder-Encyclopedie; [für junge Knaben und Mädchen] | C54: Kinder- und Jugendbücher | D54: Rücker] | E54: monograph; text | F54: PPN770565247 | G54: PPN445549262 | H54: http://resolver.staatsbibliothek-berlin.de/SBB0001055A00000000 | I54: ger | J54: 1808 | K54: WegehauptDigital | L54: [Berlin | M54: empty | N54: no
A55: Naturgeschichte für Kinder | B55: Meyer, F. A. A.; Raff, Georg Christian | C55: Kinder- und Jugendbücher; Historische Drucke | D55: Dieterich | E55: monograph; text | F55: PPN769384986 | G55: PPN141087994 | H55: http://resolver.staatsbibliothek-berlin.de/SBB0000F96900000000 | I55: ger | J55: 1827 | K55: WegehauptDigital | L55: Göttingen | M55: empty | N55: no
A56: Kochbüchlein für die Puppenküche oder erste Anweisung zum Kochen; Für Mädchen von 8-14 Jahren | B56: Löffler, Henriette; Bimbach, Julie | C56: Kinder- und Jugendbücher | D56: Schreiber | E56: monograph; text | F56: PPN769117392 | G56: PPN548218307 | H56: http://resolver.staatsbibliothek-berlin.de/SBB0000F8A000000000 | I56: ger | J56: 1885 | K56: WegehauptDigital | L56: Eßlingen | M56: https://content.staatsbibliothek-berlin.de/dc/769117392.ocr.zip | N56: yes
A57: Naturgeschichte der deutschen Schmetterlinge für die Jugend; Nebst einer passenden Anweisung, sie zu fangen, zuzubereiten, zu ordnen und unbeschädigt zu erhalten | C57: Kinder- und Jugendbücher; Historische Drucke | D57: Groß | E57: monograph; text | F57: PPN75101611X | G57: PPN568829980 | H57: http://resolver.staatsbibliothek-berlin.de/SBB0000E42300000000 | I57: ger | J57: 1805 | K57: WegehauptDigital | L57: Halberstadt | M57: empty | N57: no
A58: Illustrirte Naturgeschichte für die Jugend; mit mehr als 200 color. Abb. | B58: Schubert, Ferdinand; Schubert, Carl | C58: Kinder- und Jugendbücher; Historische Drucke | D58: Sallmayer | E58: monograph; text | F58: PPN749885149 | G58: PPN574523774 | H58: http://resolver.staatsbibliothek-berlin.de/SBB0000E14B00000000 | I58: ger | J58: 1856 | K58: WegehauptDigital | L58: Wien | M58: https://content.staatsbibliothek-berlin.de/dc/749885149.ocr.zip | N58: yes
A59: Spielbuch; enthaltend Gesellschaftsspiele, Auslösen der Pfänder, Rätsel, Charaden | B59: Löwicke, Robert | C59: Kinder- und Jugendbücher; Historische Drucke | D59: Flemming | E59: monograph; text | F59: PPN745605478 | G59: PPN566420597 | H59: http://resolver.staatsbibliothek-berlin.de/SBB0000D71400000000 | I59: ger | J59: 1887 | K59: WegehauptDigital | L59: Glogau | M59: https://content.staatsbibliothek-berlin.de/dc/745605478.ocr.zip | N59: yes
A60: Reise einer Tante in vieler Herren Länder | B60: Bernhardi, Elisabeth Eleonore | C60: Kinder- und Jugendbücher | E60: monograph; text | F60: PPN77088976X | G60: PPN444747249 | H60: http://resolver.staatsbibliothek-berlin.de/SBB0001074200000000 | I60: ger | J60: 1817 | K60: WegehauptDigital | L60: [Freiberg] | M60: empty | N60: no
A61: Naturgeschichte der Insekten für die Jugend ; Mit Kupfern | C61: Kinder- und Jugendbücher | D61: Campe | E61: monograph; text | F61: PPN770372821 | G61: PPN32489211X | H61: http://resolver.staatsbibliothek-berlin.de/SBB0001046000000000 | I61: ger | J61: 1820 | K61: WegehauptDigital | L61: Nürnberg | M61: empty | N61: no
A62: Kleines Käferbuch für Knaben; eine Anleitung zur Kenntniß der Käfer im Allgemeinen wie auch zur Anlage und zweckmäßigen Einrichtung von Käfersammlungen ; mit 72 illuminierten Abbildungen auf 5 Tafeln | C62: Kinder- und Jugendbücher; Historische Drucke | D62: Hendel | E62: monograph; text | F62: PPN742562549 | G62: PPN560569718 | H62: http://resolver.staatsbibliothek-berlin.de/SBB0000D21A00000000 | I62: ger | J62: 1862 | K62: WegehauptDigital | L62: Halle | M62: https://content.staatsbibliothek-berlin.de/dc/742562549.ocr.zip | N62: yes
A63: Entdeckungsreisen in Haus und Hof; mit seinen jungen Freunden unternommen | B63: Wagner, H. | C63: Kinder- und Jugendbücher | D63: Spamer | E63: monograph; text | F63: PPN74364154X | G63: PPN270201556 | H63: http://resolver.staatsbibliothek-berlin.de/SBB0000D30500000000 | I63: ger | J63: 1866 | K63: WegehauptDigital | L63: Leipzig | M63: https://content.staatsbibliothek-berlin.de/dc/74364154X.ocr.zip | N63: yes
A64: [Rätselbuch] | C64: Kinder- und Jugendbücher; Historische Drucke | E64: monograph; text | F64: PPN766622541 | G64: PPN571694535 | H64: http://resolver.staatsbibliothek-berlin.de/SBB0000F01000000000 | I64: ger | J64: 1830 | K64: WegehauptDigital | L64: [S.l.] | M64: empty | N64: no
A65: Naturstudien im Garten; Plaudereien am Sonntag Nachmittag ; ein Buch für die Jugend | B65: Schwindrazheim, O.; Kraepelin, Karl | C65: Kinder- und Jugendbücher | D65: Teubner | E65: monograph; text | F65: PPN742297330 | G65: PPN075795655 | H65: http://resolver.staatsbibliothek-berlin.de/SBB0000D0EF00000000 | I65: ger | J65: 1901 | K65: WegehauptDigital | L65: Leipzig | M65: https://content.staatsbibliothek-berlin.de/dc/742297330.ocr.zip | N65: yes
A66: Charakterbilder aus der Thierwelt verschiedener Welttheile; zur Belehrung und Unterhaltung der Jugend | B66: Hoffmann, W. | C66: Kinder- und Jugendbücher | D66: Nitzschke | E66: monograph; text | F66: PPN743630491 | G66: PPN26518777X | H66: http://resolver.staatsbibliothek-berlin.de/SBB0000D2F600000000 | I66: ger | J66: 1862 | K66: WegehauptDigital | L66: Stuttgart | M66: https://content.staatsbibliothek-berlin.de/dc/743630491.ocr.zip | N66: yes
A67: Neue Wanderungen durch die Thierwelt; ein Buch für Knaben und Mädchen | B67: Kirchhoff, Johann; Reichenbach, A. B. | C67: Kinder- und Jugendbücher | D67: Kretzschmar | E67: monograph; text | F67: PPN770577199 | G67: PPN311107745 | H67: http://resolver.staatsbibliothek-berlin.de/SBB0001057F00000000 | I67: ger | J67: 1848 | K67: WegehauptDigital | L67: Leipzig | M67: empty | N67: no
A68: Reisen in die Ferne oder Vater Reinhold's Mittheilungen über die Erde und ihre Bewohner; ein Lese- und Bilderbuch zur Belehrung und Unterhaltung der Jugend in der Völkerkunde und Erdbeschreibung | B68: Geissler, ...; Boettger, Gottlieb; Maukisch, Heinrich Eduard | C68: Kinder- und Jugendbücher; Historische Drucke | D68: Taubert | E68: monograph; text | F68: PPN77101631X | G68: PPN278734375 | H68: http://resolver.staatsbibliothek-berlin.de/SBB00010A6800000000 | I68: ger | J68: 1836 | K68: WegehauptDigital | L68: Leipzig | M68: empty | N68: no
A69: Lustige Bilder-Räthsel für kluge Kinder | B69: Breitschwert, W. | C69: Kinder- und Jugendbücher | D69: Hoffmann <Thienemann> | E69: monograph; text | F69: PPN745436269 | G69: PPN279375425 | H69: http://resolver.staatsbibliothek-berlin.de/SBB0000D6B000000000 | I69: ger | J69: 1875 | K69: WegehauptDigital | L69: Stuttgart | M69: https://content.staatsbibliothek-berlin.de/dc/745436269.ocr.zip | N69: yes
A70: Wie viel sind's?; Ein Bilderbuch | B70: Schmidhammer, Arpad; Holst, Adolf | C70: Kinder- und Jugendbücher | D70: Scholz | E70: monograph; text | F70: PPN770464904 | G70: PPN57409041X | H70: http://resolver.staatsbibliothek-berlin.de/SBB000104A500000000 | I70: ger | J70: 1913 | K70: WegehauptDigital | L70: Mainz | M70: https://content.staatsbibliothek-berlin.de/dc/770464904.ocr.zip | N70: yes
A71: Nun rath' einmal!; Illustrirtes Räthselbuch für artige Kinder | B71: Gerstenberg, Karl | C71: Kinder- und Jugendbücher | D71: Schreiber | E71: monograph; text | F71: PPN745435734 | G71: PPN558101321 | H71: http://resolver.staatsbibliothek-berlin.de/SBB0000D6AE00000000 | I71: ger | J71: 1878 | K71: WegehauptDigital | L71: Eßlingen | M71: https://content.staatsbibliothek-berlin.de/dc/745435734.ocr.zip | N71: yes
A72: Der Thiergarten zu Lilienthal; Ein unterhaltendes naturgeschichtliches Bilder- und Lesebuch für die Jugend ... (Mit 12 großen u. 82 kleineren Abbildungen in schönem Farbendruck.) | B72: Beumer, Philipp Jakob | C72: Kinder- und Jugendbücher; Historische Drucke | D72: Bagel | E72: monograph; text | F72: PPN770507050 | G72: PPN44513125X | H72: http://resolver.staatsbibliothek-berlin.de/SBB000104E500000000 | I72: ger | J72: 1850 | K72: WegehauptDigital | L72: Wesel | M72: https://content.staatsbibliothek-berlin.de/dc/770507050.ocr.zip | N72: yes
A73: Zoologie du jeune age ou histoire naturelle des animaux; écrite pour la jeunesse | B73: Lereboullet, Auguste | C73: Kinder- und Jugendbücher; Historische Drucke | D73: Derivaux | E73: monograph; text | F73: PPN749918349 | G73: PPN280187092 | H73: http://resolver.staatsbibliothek-berlin.de/SBB0000E19400000000 | I73: fre | J73: 1860 | K73: WegehauptDigital | L73: Strasbourg | M73: https://content.staatsbibliothek-berlin.de/dc/749918349.ocr.zip | N73: yes
A74: Naturgeschichte der reißenden Thiere; Thierschilderungen für Freunde der Natur u. die Jugend aller Stände ; Mit 36 colorierten Taf. Original-Abb. | B74: Mann, Gustav | C74: Kinder- und Jugendbücher; Historische Drucke | D74: Schweizerbart | E74: monograph; text | F74: PPN757120954 | G74: PPN566464845 | H74: http://resolver.staatsbibliothek-berlin.de/SBB0000ECEC00000000 | I74: ger | J74: 1857 | K74: WegehauptDigital | L74: Stuttgart | M74: https://content.staatsbibliothek-berlin.de/dc/757120954.ocr.zip | N74: yes
A75: Die Naturgeschichte für Kinder und Elementarschüler; oder erster Unterricht über das Mineralreich, Pflanzenreich und Thierreich. Mit über 300 color. Abb. | C75: Kinder- und Jugendbücher | D75: Schreiber & Schill | E75: monograph; text | F75: PPN770201407 | G75: PPN389491020 | H75: http://resolver.staatsbibliothek-berlin.de/SBB0001039700000000 | I75: ger | J75: 1855 | K75: WegehauptDigital | L75: Stuttgart [u.a.] | M75: https://content.staatsbibliothek-berlin.de/dc/770201407.ocr.zip | N75: yes
A76: Neuer Orbis Pictus für die Jugend oder Schauplatz der Natur, der Kunst und des Menschenlebens in 322 lithographischen Abbildungen mit genauer Erklärung in deutscher, lateinischer, französischer und englischer Sprache | B76: Gailer, Jacob E.; Comenius, Johann Amos | C76: Kinder- und Jugendbücher; Historische Drucke | D76: Mäcken | E76: monograph; text | F76: PPN767066812 | G76: PPN230802753 | H76: http://resolver.staatsbibliothek-berlin.de/SBB0000F20600000000 | I76: eng | J76: 1835 | K76: WegehauptDigital | L76: Reutlingen | M76: empty | N76: no
A77: Biblische Naturgeschichte für Schulen und Familien | B77: Barth, Christian Gottlob | C77: Kinder- und Jugendbücher | D77: Vereinsbuchhandl. [usw.] | E77: monograph; text | F77: PPN743860241 | G77: PPN54707901X | H77: http://resolver.staatsbibliothek-berlin.de/SBB0000D35E00000000 | I77: ger | J77: 1874 | K77: WegehauptDigital | L77: Calw | M77: https://content.staatsbibliothek-berlin.de/dc/743860241.ocr.zip | N77: yes
A78: Die Schwarzwald-Reise; Eine christliche Erzählung und zugleich eine landschaftliche Beschreibung, natürliche Geographie und Geognosie des würtembergischen Schwarzwaldes ; Für die Jugend der höheren Stände | B78: Schwarz, Eduard | C78: Kinder- und Jugendbücher; Historische Drucke | D78: Balz | E78: monograph; text | F78: PPN77096351X | G78: PPN319610543 | H78: http://resolver.staatsbibliothek-berlin.de/SBB00010A1100000000 | I78: ger | J78: 1836 | K78: WegehauptDigital | L78: Stuttgart | M78: empty | N78: no
A79: Der aufrichtige Kalendermann; Ein gar kurioses und nützliches Buch Für die Jugend und den gemeinen Bürger und Bauersmann verfertiget | B79: Steinbeck, Christoph Gottlieb | C79: Kinder- und Jugendbücher; Historische Drucke; VD18 digital | D79: Steinbeck; Fleischer | E79: monograph; text | F79: PPN766725251 | G79: PPN663601738 | H79: http://resolver.staatsbibliothek-berlin.de/SBB0000F0B200000000 | I79: ger | J79: 1792 | K79: WegehauptDigital; VD18 digital | L79: Langenberg ohnweit Gera; Leipzig | M79: empty | N79: no
A80: Naturgeschichte des Pflanzenreiches in Bildern; nach der Anordnung des allgemein bekannten u. beliebten Lehrbuchs der Naturgeschichte von G[otthilf] H[einrich] v. Schubert | B80: Schubert, Gotthilf Heinrich; Hochstetter, Christian Ferdinand | C80: Kinder- und Jugendbücher; Historische Drucke | D80: Schreiber | E80: monograph; text | F80: PPN749900172 | G80: PPN568822358 | H80: http://resolver.staatsbibliothek-berlin.de/SBB0000E16800000000 | I80: fre | J80: 1865 | K80: WegehauptDigital | L80: Eßlingen a. N. | M80: https://content.staatsbibliothek-berlin.de/dc/749900172.ocr.zip | N80: yes
A81: Die Hausthiere nebst ihrer Beschäftigung und Verwendung; Ein nützliches und unterhaltendes Bilderbuch für die Jugend ; Mit 80 Haupt- und Nebenbildern und erklärendem Text | C81: Kinder- und Jugendbücher; Historische Drucke | D81: Zeh | E81: monograph; text | F81: PPN756434564 | G81: PPN559169582 | H81: http://resolver.staatsbibliothek-berlin.de/SBB0000EA8E00000000 | I81: ger | J81: 1846 | K81: WegehauptDigital | L81: Nürnberg | M81: empty | N81: no
A82: Die Jugendspiele; ein Leitfaden bei der Einführung und Übung von Turn- und Jugendspielen | B82: Eitner, Gustav | C82: Kinder- und Jugendbücher | D82: Voigtländer | E82: monograph; text | F82: PPN745185738 | G82: PPN236366599 | H82: http://resolver.staatsbibliothek-berlin.de/SBB0000D64600000000 | I82: ger | J82: 1890 | K82: WegehauptDigital | L82: Kreuznach [u.a.] | M82: https://content.staatsbibliothek-berlin.de/dc/745185738.ocr.zip | N82: yes
A83: Das Mikroskop; mit 90 Abbildungen | B83: Schertel, Sigmund | C83: Kinder- und Jugendbücher; Historische Drucke | D83: Union Dt. Verlagsges. | E83: monograph; text | F83: PPN741301490 | G83: PPN573714444 | H83: http://resolver.staatsbibliothek-berlin.de/SBB0000CFB500000000 | I83: ger | J83: 1900 | K83: WegehauptDigital | L83: Stuttgart [u.a.] | M83: https://content.staatsbibliothek-berlin.de/dc/741301490.ocr.zip | N83: yes
A84: Naturgeschichte für Kinder | B84: Lippold, Georg Heinrich Christian; Funke, Carl Philipp | C84: Kinder- und Jugendbücher; Historische Drucke | D84: Kummer | E84: monograph; text | F84: PPN769508758 | G84: PPN239889762 | H84: http://resolver.staatsbibliothek-berlin.de/SBB0000F99B00000000 | I84: ger | J84: 1827 | K84: WegehauptDigital | L84: Leipzig | M84: empty | N84: no
A85: Der gewandte Zauberkünstler und Hexenmeister in Familien- und Gesellschaftskreisen; in Darstellung der lehreichsten und unterhaltendsten Kunststücke auf dem Gebiete der natürlichen Magie, der Taschen- und Kartenspieler und der Rechenkunst ; mit Bildern | B85: Ortleb, Alexander | C85: Kinder- und Jugendbücher; Historische Drucke | D85: Linser | E85: monograph; text | F85: PPN745827632 | G85: PPN569413095 | H85: http://resolver.staatsbibliothek-berlin.de/SBB0000D75C00000000 | I85: ger | J85: 1897 | K85: WegehauptDigital | L85: Pankow-Berlin | M85: https://content.staatsbibliothek-berlin.de/dc/745827632.ocr.zip | N85: yes
A86: Der Schmetterlingsfreund; Beschreibung d. vorzügl. mitteleurop. Schmetterlinge nebst Anl. dieselben zu fangen, deren Puppen u. Raupen aufzuziehen u. eine Samml. anzulegen ; für d. Jugend verf. ; mit 236 Abb. auf 23 Taf. | B86: Hofmann, Ernst | C86: Kinder- und Jugendbücher | D86: Hoffmann | E86: monograph; text | F86: PPN769120490 | G86: PPN559723946 | H86: http://resolver.staatsbibliothek-berlin.de/SBB0000F8B000000000 | I86: ger | J86: 1883 | K86: WegehauptDigital | L86: Stuttgart | M86: https://content.staatsbibliothek-berlin.de/dc/769120490.ocr.zip | N86: yes
A87: Naturgeschichte Der Amphibien, Fische, Weich- und Schaalenthiere, Insekten, Würmer und Strahlenthiere in Bildern ... zum Anschauungs-Unterricht für die Jugend ... nach der ...Naturgeschichte für Schulen; mit erklärendem Texte in deutscher und französischer Sprache | B87: Schubert, Gotthilf Heinrich | C87: Kinder- und Jugendbücher; Historische Drucke | D87: Schreiber & Schill | E87: monograph; text | F87: PPN769048684 | G87: PPN568791290 | H87: http://resolver.staatsbibliothek-berlin.de/SBB0000F82200000000 | I87: ger | J87: 1849 | K87: WegehauptDigital | L87: Eßlingen; Stuttgart | M87: empty | N87: no
A88: Wald und Meer; Schilderungen aus dem Naturleben der Thiere und Pflanzen | B88: Ramberg, Heinrich; Jury, Wilhelm; Schasler, Max | C88: Kinder- und Jugendbücher; Historische Drucke | D88: Hasselberg | E88: monograph; text | F88: PPN749886765 | G88: PPN27954653X | H88: http://resolver.staatsbibliothek-berlin.de/SBB0000E15200000000 | I88: ger | J88: 1853 | K88: WegehauptDigital | L88: Berlin | M88: https://content.staatsbibliothek-berlin.de/dc/749886765.ocr.zip | N88: yes
A89: Naturhistorisches Bilder- und Lese-Buch oder Erzählungen über Gegenstände aus den drei Reichen der Natur; Nebst 300 illuminirten Abbildungen von [Konrad] Horny und einer kurzen Erklärung derselben in Versen | B89: Horny, Konrad; Glatz, Jakob | C89: Kinder- und Jugendbücher; Historische Drucke | D89: Frommann | E89: monograph; text | F89: PPN769046053 | G89: PPN371007631 | H89: http://resolver.staatsbibliothek-berlin.de/SBB0000F81F00000000 | I89: ger | J89: 1803 | K89: WegehauptDigital | L89: Jena | M89: empty | N89: no
A90: Das Spiel im Zimmer; eine reichhaltige Sammlung ausgewählter Spiele zum Gebrauche für jung und alt, für den Einzelnen, wie für kleinere und größere Kreise | B90: Mittenzwey, L. | C90: Kinder- und Jugendbücher | D90: Merseburger | E90: monograph; text | F90: PPN745139965 | G90: PPN567083055 | H90: http://resolver.staatsbibliothek-berlin.de/SBB0000D5E900000000 | I90: ger | J90: 1887 | K90: WegehauptDigital | L90: Leipzig | M90: https://content.staatsbibliothek-berlin.de/dc/745139965.ocr.zip | N90: yes
A91: Der Weltumsegler. Oder Reise durch alle fünf Theile der Erde mit vorzüglicher Hinsicht auf ihre Bewohner, auf die Schönheiten und Merkwürdigkeiten der Natur und Kunst [et]c.; Zum Selbstunterricht der Jugend zweckmäßig abgefasst | B91: Schäfer, Daniel F. | C91: Kinder- und Jugendbücher | D91: Oehmigke | E91: multivolume_work; text | F91: PPN727852981 | G91: PPN032135513 | H91: http://resolver.staatsbibliothek-berlin.de/SBB0001554600000000 | I91: ger | J91: 1801 | K91: WegehauptDigital | L91: Berlin | M91: empty | N91: no
A92: Reise durch das Berner Oberland nach Unterwalden; für die Jugend beschrieben | B92: Lory, G.; Burgdorfer, D.; Meisner, Friedrich | C92: Kinder- und Jugendbücher | D92: Burgdorfer | E92: volume; text | F92: PPN770944965 | G92: PPN282315799 | H92: http://resolver.staatsbibliothek-berlin.de/SBB000109F000020000 | I92: ger | J92: 1821 | K92: WegehauptDigital | L92: Bern | M92: empty | N92: no
A93: Conversations-Lexicon für die Jugend | C93: Kinder- und Jugendbücher; Historische Drucke | D93: Goedsche | E93: volume; text | F93: PPN766562786 | G93: PPN562017402 | H93: http://resolver.staatsbibliothek-berlin.de/SBB0000EF8800020000 | I93: ger | J93: 1840 | K93: WegehauptDigital | L93: Meissen | M93: empty | N93: no
A94: Bilderbuch zum Nutzen und Vergnügen der Jugend; enthaltend eine angenehme Sammlung von Thieren, Pflanzen, Blumen, Früchten, Mineralien, Trachten und allerhand andern unterrichtenden Gegenständen aus dem Reiche der Natur, der Künste und Wissenschaften ; alle nach den besten Originalen gewählt gestochen, und mit einer kurzen wissenschaftlichen und den Verstandeskräften der Jugend angemessenen Erklärung begleitet | B94: Bertuch, Friedrich Justin | C94: Kinder- und Jugendbücher; Historische Drucke | D94: Bohmann | E94: multivolume_work; text | F94: PPN803797397 | G94: PPN364483261 | H94: http://resolver.staatsbibliothek-berlin.de/SBB0001793700000000 | I94: ger | J94: 1822 | K94: WegehauptDigital | L94: Prag | M94: empty | N94: no
A95: Der kleine Physiker, oder Unterhaltungen über natürliche Dinge, für Kinder | B95: Höpfner, Adolf Friedrich | C95: Kinder- und Jugendbücher | D95: Keyser | E95: volume; text | F95: PPN746626002 | G95: PPN746625758 | H95: http://resolver.staatsbibliothek-berlin.de/SBB0000DB6F00020000 | I95: ger | J95: 1804 | K95: WegehauptDigital | L95: Erfurt | M95: empty | N95: no
A96: Der technologische Jugendfreund oder Unterhaltende Wanderungen in die Werkstätte der Künstler und Handwerker, zur nöthigen Kenntniß derselben | B96: Blasche, Bernhard Heinrich | C96: Kinder- und Jugendbücher | D96: Wilmans | E96: volume; text | F96: PPN770196195 | G96: PPN335885187 | H96: http://resolver.staatsbibliothek-berlin.de/SBB0001038200010000 | I96: ger | J96: 1804 | K96: WegehauptDigital | L96: Frankfurt am Mayn | M96: empty | N96: no
A97: Tempel der Natur und Kunst | B97: Hirschmann, C. A. | C97: Kinder- und Jugendbücher | D97: Tauchnitz | E97: volume; text | F97: PPN781903688 | G97: PPN563410795 | H97: http://resolver.staatsbibliothek-berlin.de/SBB0001568700050000 | I97: ger | J97: 1805 | K97: WegehauptDigital | L97: Leipzig | M97: empty | N97: no
A98: Der mechanische Jugendfreund oder faßliche und unterhaltende Darstellung der Lehre vom Gleichgewicht und der Bewegung, mit der Beschreibung der dazu gehörigen Maschinen und selbst mit Beyfügung mancher belustigenden mechanischen Kunststücke; Zweyter Theil ; Mit sieben Kupfertafeln | B98: Poppe, Johann Heinrich Moritz | C98: Kinder- und Jugendbücher; Historische Drucke | D98: Wilmans | E98: volume; text | F98: PPN746345666 | G98: PPN236461788 | H98: http://resolver.staatsbibliothek-berlin.de/SBB0000D8D300010000 | I98: ger | J98: 1821 | K98: WegehauptDigital | L98: Frankfurt am Main | M98: empty | N98: no
A99: Naturgeschichte für die deutsche Jugend | B99: Hochstetter, Christian Ferdinand; Gebauer, Christian August | C99: Kinder- und Jugendbücher; Historische Drucke | D99: Löflund | E99: volume; text | F99: PPN769087779 | G99: PPN557898129 | H99: http://resolver.staatsbibliothek-berlin.de/SBB0000F85900010000 | I99: ger | J99: 1829 | K99: WegehauptDigital | L99: Stuttgart | M99: empty | N99: no
A100: Spiel und Sport; das Buch der gesellschaftlichen Unterhaltungen und Vergnügungen, der körperlichen Uebungen, ritterlichen Erholungen und Künste ; in zwei Abtheilungen | B100: Georgens, Jan Daniel | C100: Kinder- und Jugendbücher | D100: Spamer | E100: multivolume_work; text | F100: PPN745169724 | G100: PPN369019458 | H100: http://resolver.staatsbibliothek-berlin.de/SBB0000D62500000000 | I100: ger | J100: 1882 | K100: WegehauptDigital | L100: Leipzig; Berlin | M100: empty | N100: no
...

Sheet monographs_volumes titles
A3: Zeilenbeschriftungen | B3: Anzahl von title
A4: PPN387303650 | B4: 3
A5: Mit 20 Kupfertafeln | B5: 3
A6: PPN58178104X | B6: 2
A7: Was ein kleines Mädchen wissen muß | B7: 2
A8: PPN742529940 | B8: 2
A9: Physik in Bildern | B9: 2
A10: PPN582161126 | B10: 2
A11: July to december | B11: 2
A12: PPN574051384 | B12: 2
A13: Kurzes und leichtes Rechenbuch für Anfänger wie auch für Bürger- und Landschulen; Erster und zweiter Theil | B13: 2
A14: PPN766276414 | B14: 2
A15: Geschenk für meine Kinder, am Tage ihrer Verlobung oder Vollständiger Unterricht über die Erziehung der Jugend vom Keime an, bis in das mannbare Alter | B15: 2
... A3335: Gesamtergebnis | B3335: 1720

Sheet remove_dupl_monographs_vol
A1: title | B1: creator | C1: subject | D1: publisher | E1: type | F1: digital object identifier | G1: physical object identifier | H1: URL | I1: language | J1: date | K1: relation | L1: coverage | M1: OCR URL | N1: OCR found? | P1: Zeilenbeschriftungen | Q1: Anzahl von type
A2: Abrégé de toutes les sciences, ou encyclopédie des enfants; mise dans un nouvel ordre,... | B2: Buqcellos, ...; Blocquel, Simon | C2: Kinder- und Jugendbücher; Historische Drucke | D2: Delarue ;; Castiaux | E2: monograph; text | F2: PPN766849139 | G2: PPN548262071 | H2: http://resolver.staatsbibliothek-berlin.de/SBB0000F13000000000 | I2: fre | J2: 1816 | K2: WegehauptDigital | L2: Paris; Lille | M2: empty | N2: no | P2: monograph; text | Q2: 869
A3: Naturgeschichte für Kinder | B3: Raff, Georg Christian | C3: Kinder- und Jugendbücher; Historische Drucke | D3: Sammer | E3: monograph; text | F3: PPN749770333 | G3: PPN279536941 | H3: http://resolver.staatsbibliothek-berlin.de/SBB0000E0AE00000000 | I3: ger | J3: 1846 | K3: WegehauptDigital | L3: Wien | M3: empty | N3: no | P3: no | Q3: 395
A4: Die Entstehung der Erde | B4: Kranz, Wilhelm; Meyer, Max Wilhelm | C4: Kinder- und Jugendbücher; Historische Drucke | D4: Paetel | E4: monograph; text | F4: PPN741297272 | G4: PPN276525892 | H4: http://resolver.staatsbibliothek-berlin.de/SBB0000CFAB00000000 | I4: ger | J4: 1907 | K4: WegehauptDigital | L4: Berlin | M4: https://content.staatsbibliothek-berlin.de/dc/741297272.ocr.zip | N4: yes | P4: yes | Q4: 474
A5: Die Schulwerkstatt; ein Leitfaden zur Einführung der technischen Arbeiten in die Schule | B5: Barth, Ernst; Niederley, W. | C5: Kinder- und Jugendbücher; Historische Drucke | D5: Velhagen & Klasing | E5: monograph; text | F5: PPN745116574 | G5: PPN453868991 | H5: http://resolver.staatsbibliothek-berlin.de/SBB0000D59B00000000 | I5: ger | J5: 1882 | K5: WegehauptDigital | L5: Bielefeld [u.a.] | M5: https://content.staatsbibliothek-berlin.de/dc/745116574.ocr.zip | N5: yes | P5: periodical_volume; text | Q5: 5
A6: Der junge Eisenbahnbauer; eine Anleitung zur Selbstherstellung von Modelleisenbahnen ; mit 118 Abb. | B6: Hermuth, Paul | C6: Kinder- und Jugendbücher; Historische Drucke | D6: Union Dt. Verl.-Gesellsch. | E6: monograph; text | F6: PPN744069432 | G6: PPN559338228 | H6: http://resolver.staatsbibliothek-berlin.de/SBB0000D52F00000000 | I6: ger | J6: 1916 | K6: WegehauptDigital | L6: Stuttgart [u.a.] | M6: https://content.staatsbibliothek-berlin.de/dc/744069432.ocr.zip | N6: yes | P6: no | Q6: 5
A7: Neuer Räthselschatz; für die Jugend zur Übung im Denken und zur belehrenden Unterhaltung | B7: Schäffer, W. | C7: Kinder- und Jugendbücher; Historische Drucke | D7: Oehmigke | E7: monograph; text | F7: PPN745271243 | G7: PPN573465517 | H7: http://resolver.staatsbibliothek-berlin.de/SBB0000D67F00000000 | I7: ger | J7: 1865 | K7: WegehauptDigital | L7: Neu-Ruppin | M7: https://content.staatsbibliothek-berlin.de/dc/745271243.ocr.zip | N7: yes | P7: volume; text | Q7: 793
A8: Wander- und Spielbüchlein für Schüler und Schülerinnen | B8: Matzdorf, Paul | C8: Kinder- und Jugendbücher | D8: Strauch | E8: monograph; text | F8: PPN745123694 | G8: PPN56682809X | H8: http://resolver.staatsbibliothek-berlin.de/SBB0000D5AD00000000 | I8: ger | J8: 1910 | K8: WegehauptDigital | L8: Leipzig | M8: https://content.staatsbibliothek-berlin.de/dc/745123694.ocr.zip | N8: yes | P8: no | Q8: 599
A9: Causeries sur la science; illustrées de 94 gravures | B9: Tissandier, Gaston | C9: Kinder- und Jugendbücher; Historische Drucke | D9: Hachette | E9: monograph; text | F9: PPN745272312 | G9: PPN578011344 | H9: http://resolver.staatsbibliothek-berlin.de/SBB0000D68300000000 | I9: fre | J9: 1880 | K9: WegehauptDigital | L9: Paris | M9: https://content.staatsbibliothek-berlin.de/dc/745272312.ocr.zip | N9: yes | P9: yes | Q9: 194
A10: Der unerschöpfliche Maître de Plaisir; oder die Kunst, in allen Jahreszeiten, im Freien und zu Hause, so wie an allen nur denkbaren Freudentagen die unterhaltendsten und belustigendsten Parthieen anzuordnen ; Enthaltend die besten Spiele, Lieder, Declamir- und Kunststücke, Räthsel, Charaden [et]c. Ein unentbehrliches Haus- und Handbuch für alle lebensfrohe deutsche Familien | C10: Kinder- und Jugendbücher; Historische Drucke | D10: Voigt | E10: monograph; text | F10: PPN767042255 | G10: PPN280073852 | H10: http://resolver.staatsbibliothek-berlin.de/SBB0000F1B700000000 | I10: ger | J10: 1822 | K10: WegehauptDigital | L10: Nordhausen; Sondershausen | M10: empty | N10: no | P10: (Leer)
A11: Im Grünen oder Die kleinen Pflanzenfreunde; kleine Erzählungen aus dem Pflanzenreich | B11: Wagner, Hermann | C11: Kinder- und Jugendbücher | D11: Spamer | E11: monograph; text | F11: PPN743675703 | G11: PPN578788829 | H11: http://resolver.staatsbibliothek-berlin.de/SBB0000D31400000000 | I11: ger | J11: 1878 | K11: WegehauptDigital | L11: Leipzig | M11: https://content.staatsbibliothek-berlin.de/dc/743675703.ocr.zip | N11: yes | P11: (Leer)
A12: Das Buch der Gesellschaftsspiele | B12: Weller, Hermine | C12: Kinder- und Jugendbücher | D12: Fischer | E12: monograph; text | F12: PPN745213553 | G12: PPN581117719 | H12: http://resolver.staatsbibliothek-berlin.de/SBB0000D65A00000000 | I12: ger | J12: 1910 | K12: WegehauptDigital | L12: Dresden | M12: https://content.staatsbibliothek-berlin.de/dc/745213553.ocr.zip | N12: yes | P12: Gesamtergebnis | Q12: 1667
A13: Der gelehrte Spielkamerad; Anleitung für kleine Physiker, Chemiker, Botaniker und Naturfreunde zum Experimentieren, zur Anlage von Pflanzen-, Stein-, Muschel-, Insekten-, Schmetterling-, Vogel-, Briefmarken-Sammlungen ect. sowie zur Pflege der Hausthiere und des Hausgartens ; ein Supplement zum "Spielbuch für Knaben" | B13: Wagner, Hermann | C13: Kinder- und Jugendbücher | D13: Spamer | E13: monograph; text | F13: PPN74270906X | G13: PPN578814706 | H13: http://resolver.staatsbibliothek-berlin.de/SBB0000D2AA00000000 | I13: ger | J13: 1877 | K13: WegehauptDigital | L13: Leipzig | M13: https://content.staatsbibliothek-berlin.de/dc/74270906X.ocr.zip | N13: yes
A14: Des fleißigen Mädchens Koch-Büchlein für die Puppen-Küche | C14: Kinder- und Jugendbücher; Historische Drucke | D14: Meisel | E14: monograph; text | F14: PPN745432069 | G14: PPN278721036 | H14: http://resolver.staatsbibliothek-berlin.de/SBB0000D6A800000000 | I14: ger | J14: 1876 | K14: WegehauptDigital | L14: Leipzig; Herisau; Stuttgart | M14: https://content.staatsbibliothek-berlin.de/dc/745432069.ocr.zip | N14: yes
A15: Naturgeschichte für Kinder, von M. Georg Christian Raff, ordentlichen Lehrer der Geschichte und Geographie auf dem Lyceum zu Göttingen. Mit vierzehn Kupfertafeln | B15: Raff, Georg Christian | C15: Kinder- und Jugendbücher; Historische Drucke | E15: monograph; text | F15: PPN769119182 | G15: PPN571683770 | H15: http://resolver.staatsbibliothek-berlin.de/SBB0000F8A900000000 | I15: ger | J15: 1802 | K15: WegehauptDigital | L15: Frankfurt; Leipzig | M15: empty | N15: no
A16: Kleine Bilderschule für die Jugend | B16: Hausius, Karl Gottlob | C16: Kinder- und Jugendbücher; Historische Drucke | D16: Voß | E16: monograph; text | F16: PPN757417825 | G16: PPN55916422X | H16: http://resolver.staatsbibliothek-berlin.de/SBB0000ED8900000000 | I16: ger | J16: 1807 | K16: WegehauptDigital | L16: Leipzig | M16: empty | N16: no
A17: Vollständiges Giftbuch oder Unterricht, die Giftpflanzen, Giftminerale und Giftthiere kennen zu lernen, und Gesundheit und Leben gegen Vergiftungs-Gefahren sicher zu stellen | C17: Kinder- und Jugendbücher | D17: Voigt | E17: monograph; text | F17: PPN770137474 | G17: PPN406020620 | H17: http://resolver.staatsbibliothek-berlin.de/SBB0001031A00000000 | I17: ger | J17: 1817 | K17: WegehauptDigital | L17: Sondershausen | M17: empty | N17: no
A18: Schneiders Typen-Atlas; naturwissenschaftlich-geographischer Hand-Atlas für Schule und Haus | B18: Schneider, Oskar; Claudius, W.; Leutemann, H.; Mützel, G.; Seidel, C. F. | C18: Kinder- und Jugendbücher | D18: Meinhold | E18: monograph; text | F18: PPN743969359 | G18: PPN574227601 | H18: http://resolver.staatsbibliothek-berlin.de/SBB0000D4C500000000 | I18: ger | J18: 1885 | K18: WegehauptDigital | L18: Dresden | M18: https://content.staatsbibliothek-berlin.de/dc/743969359.ocr.zip | N18: yes
A19: Das Buch wunderbarer Erfindungen; in Schilderungen f. d. reifere Jugend : mit 125 Abb. u. 1 Titelbild. | B19: Thomas, Louis | C19: Kinder- und Jugendbücher; Historische Drucke | D19: Spamer | E19: monograph; text | F19: PPN756689090 | G19: PPN578154765 | H19: http://resolver.staatsbibliothek-berlin.de/SBB0000EBC100000000 | I19: ger | J19: 1860 | K19: WegehauptDigital | L19: Leipzig | M19: https://content.staatsbibliothek-berlin.de/dc/756689090.ocr.zip | N19: yes
A20: Naturgeschichte der Vögel; mit besonderer Berücksichtigung der in Deutschland vorkommenden Vögel und Belehrung über Zucht und Wartung der Haus- und Stubenvögel | B20: Abendroth, Carl | C20: Kinder- und Jugendbücher | D20: Baensch | E20: monograph; text | F20: PPN744053714 | G20: PPN538752823 | H20: http://resolver.staatsbibliothek-berlin.de/SBB0000D51E00000000 | I20: ger | J20: 1870 | K20: WegehauptDigital | L20: Leipzig | M20: https://content.staatsbibliothek-berlin.de/dc/744053714.ocr.zip | N20: yes
A21: Abrégé de toutes les sciences à l'usage des enfans de six ans jusqu' a douze; on y a joint un abrégé de l'histoire de Brandebourg | B21: Formey, Jean-Henri-Samuel | C21: Kinder- und Jugendbücher; Historische Drucke | D21: Horvath | E21: monograph; text | F21: PPN76623858X | G21: PPN557396433 | H21: http://resolver.staatsbibliothek-berlin.de/SBB0000EE5000000000 | I21: fre | J21: 1803 | K21: WegehauptDigital | L21: Potsdam | M21: empty | N21: no
A22: Jagden-Bilderbuch für die liebe Jugend; mit 9 lithographirten Darstellungen | C22: Kinder- und Jugendbücher | E22: monograph; text | F22: PPN770079113 | G22: PPN491349475 | H22: http://resolver.staatsbibliothek-berlin.de/SBB000102A700000000 | I22: ger | J22: 1860 | K22: WegehauptDigital | L22: [S.l.] | M22: https://content.staatsbibliothek-berlin.de/dc/770079113.ocr.zip | N22: yes
A23: Neues und bewährtes illustriertes Kochbuch für alle Stände; zuverlässige Anleitung zur Bereitung der verschiedenartigsten Speisen, Backwerke, Getränke etc. ; nach eigener, vieljähriger Erfahrung | B23: Davithis, H. | C23: Kinder- und Jugendbücher; Historische Drucke | D23: Enßlin und Laiblin | E23: monograph; text | F23: PPN745127495 | G23: PPN278540538 | H23: http://resolver.staatsbibliothek-berlin.de/SBB0000D5C100000000 | I23: ger | J23: 1905 | K23: WegehauptDigital | L23: Reutlingen | M23: https://content.staatsbibliothek-berlin.de/dc/745127495.ocr.zip | N23: yes
A24: An der Werkbank; Anleitung zur Handfertigkeit mit besonderer Berücksichtigung der Herstellung physikalischer Apparate ; für mittlere und reife Schüler | B24: Gscheidlen, Emanuel | C24: Kinder- und Jugendbücher; Historische Drucke | D24: Teubner | E24: monograph; text | F24: PPN745118615 | G24: PPN223999733 | H24: http://resolver.staatsbibliothek-berlin.de/SBB0000D59F00000000 | I24: ger | J24: 1912 | K24: WegehauptDigital | L24: Berlin; Leipzig | M24: https://content.staatsbibliothek-berlin.de/dc/745118615.ocr.zip | N24: yes
A25: Die Schöpfung der Erde; die Urwelt und die Urgeschöpfe bis zum Auftreten des Menschen ; Blicke in das Erdinnere ; Wanderungen in die Gebirgswelt, namentlich unsres Veterlandes, nach Kreuz und Quer ; mit reiferen Schülern unternommen | B25: Hintze, Eduard | C25: Kinder- und Jugendbücher | D25: Spamer | E25: monograph; text | F25: PPN742493695 | G25: PPN341499900 | H25: http://resolver.staatsbibliothek-berlin.de/SBB0000D1BE00000000 | I25: ger | J25: 1885 | K25: WegehauptDigital | L25: Leipzig, Berlin | M25: https://content.staatsbibliothek-berlin.de/dc/742493695.ocr.zip | N25: yes
A26: Der Weltspiegel; das Wissenswürdigste vom Weltgebäude, von der Erde, von den Völkern der Erde | B26: Hoffmann, Friedrich | C26: Kinder- und Jugendbücher; Historische Drucke | D26: Schmidt & Spring; Lithographische Anstalt von Engelhorn und Hochdanz | E26: monograph; text | F26: PPN766156990 | G26: PPN279154607 | H26: http://resolver.staatsbibliothek-berlin.de/SBB0000EE1D00000000 | I26: ger | J26: 1844 | K26: WegehauptDigital | L26: Stuttgart; Stuttgart | M26: empty | N26: no
A27: Naturgeschichte; der Jugend gewidmet | B27: Wagner, Hermann | C27: Kinder- und Jugendbücher | D27: Hoffmann | E27: monograph; text | F27: PPN770457983 | G27: PPN408013931 | H27: http://resolver.staatsbibliothek-berlin.de/SBB0001049700000000 | I27: ger | J27: 1870 | K27: WegehauptDigital | L27: Stuttgart | M27: https://content.staatsbibliothek-berlin.de/dc/770457983.ocr.zip | N27: yes
A28: Lehrbuch der Sternkunde; für Schulen und zum Selbstunterrichte | B28: Schubert, Gotthilf Heinrich | C28: Kinder- und Jugendbücher; Historische Drucke | D28: Weber | E28: monograph; text | F28: PPN750739150 | G28: PPN311822029 | H28: http://resolver.staatsbibliothek-berlin.de/SBB0000E3CF00000000 | I28: ger | J28: 1832 | K28: WegehauptDigital | L28: München | M28: empty | N28: no
A29: Leichte Künsteleien zum Vergnügen und zum Nutzen für Kinder und Nichtkinder; Ein Buch mannigfaltigen Inhaltes | B29: Rockstroh, Heinrich | C29: Kinder- und Jugendbücher; Historische Drucke | D29: Wittich | E29: monograph; text | F29: PPN767041380 | G29: PPN556113098 | H29: http://resolver.staatsbibliothek-berlin.de/SBB0000F1B600000000 | I29: ger | J29: 1819 | K29: WegehauptDigital | L29: Berlin | M29: empty | N29: no
A30: Europäische Bilder und Skizzen; zur Belehrung für die reifere Jugend | B30: Hoffmann, Julius; Hosemann, Theodor | C30: Kinder- und Jugendbücher | D30: Trewendt | E30: monograph; text | F30: PPN771014600 | G30: PPN265186358 | H30: http://resolver.staatsbibliothek-berlin.de/SBB00010A6400000000 | I30: ger | J30: 1858 | K30: WegehauptDigital | L30: Breslau | M30: https://content.staatsbibliothek-berlin.de/dc/771014600.ocr.zip | N30: yes
A31: Malerische Naturgeschichte der drei Reiche für Schule und Haus; Mit besonderer Beziehung auf das practische Leben bearbeitet von F[riedrich] W[ilhelm] Lindner; unter Mitwirkung von Dr. Fr. H. A. Lachmann | B31: Lachmann, Fr. H. A.; Lindner, Friedrich Wilhelm | C31: Kinder- und Jugendbücher; Historische Drucke | D31: Oehme & Müller | E31: monograph; text | F31: PPN770463371 | G31: PPN42077016X | H31: http://resolver.staatsbibliothek-berlin.de/SBB000104A200000000 | I31: ger | J31: 1840 | K31: WegehauptDigital | L31: Braunschweig | M31: empty | N31: no
A32: Allerlei schöne Bilderrätsel für Jung und Alt | C32: Kinder- und Jugendbücher; Historische Drucke | E32: monograph; text | F32: PPN74513548X | G32: PPN30847046X | H32: http://resolver.staatsbibliothek-berlin.de/SBB0000D5D100000000 | I32: ger | K32: WegehauptDigital | M32: https://content.staatsbibliothek-berlin.de/dc/74513548X.ocr.zip | N32: yes
A33: Der Hausbau; oder erste Begriffe von Staat und den vorzüglichsten Ständen, Handwerken, Fabriken, Künsten, Wissenschaften u. d. gl. für Kinder | B33: Werlich, August Karl Friedrich | C33: Kinder- und Jugendbücher; Historische Drucke | D33: Juniussische Buchhandlung | E33: monograph; text | F33: PPN756639891 | G33: PPN579566781 | H33: http://resolver.staatsbibliothek-berlin.de/SBB0000EB7900000000 | I33: ger | J33: 1804 | K33: WegehauptDigital | L33: Leipzig | M33: empty | N33: no
A34: Gemählde aus der Natur und dem Menschenleben, in einer Reihe von Schilderungen merkwürdiger Naturerscheinungen und gefahrvoller Reiseabentheuer; zum Nutzen und Vergnügen der Jugend | B34: Albertus, D. J. C. | C34: Kinder- und Jugendbücher | D34: Kaiser | E34: monograph; text | F34: PPN781283116 | G34: PPN541529498 | H34: http://resolver.staatsbibliothek-berlin.de/SBB0001555D00000000 | I34: ger | J34: 1830 | K34: WegehauptDigital | L34: Grätz | M34: empty | N34: no
A35: Kurzer Unterricht in der Naturwissenschaft für die Jugend | B35: Uihlein, Joseph | C35: Kinder- und Jugendbücher; Historische Drucke | D35: Andreä | E35: monograph; text | F35: PPN770157742 | G35: PPN366080202 | H35: http://resolver.staatsbibliothek-berlin.de/SBB0001033900000000 | I35: ger | J35: 1810 | K35: WegehauptDigital | L35: Frankfurt am Main | M35: empty | N35: no
A36: F. Martin's Naturgeschichte für die Jugend beiderlei Geschlechts; mit dreihundert Abbildungen und zwanzig Holzschnitten | B36: Kolb, Christian Friedrich August; Martin, F. | C36: Kinder- und Jugendbücher; Historische Drucke | D36: Schmidt & Spring | E36: monograph; text | F36: PPN741294397 | G36: PPN566740400 | H36: http://resolver.staatsbibliothek-berlin.de/SBB0000CFA500000000 | I36: ger | J36: 1880 | K36: WegehauptDigital | L36: Stuttgart | M36: https://content.staatsbibliothek-berlin.de/dc/741294397.ocr.zip | N36: yes
A37: Aus Werkstatt und Welt; eine Festgabe für die werkthätige Jugend dargereicht von Leipz. Fortbildungsschuldirektoren u.-Lehrern | C37: Kinder- und Jugendbücher; Historische Drucke | D37: Hahn; Schmidt | E37: monograph; text | F37: PPN770851347 | G37: PPN581182618 | H37: http://resolver.staatsbibliothek-berlin.de/SBB0001070300000000 | I37: ger | J37: 1901 | K37: WegehauptDigital | L37: Leipzig; Leipzig | M37: https://content.staatsbibliothek-berlin.de/dc/770851347.ocr.zip | N37: yes
A38: Mittheilungen aus dem Gebiet der Naturkunde und dem Menschenleben für die Jugend ; mit 25 col. Abb. | B38: Maukisch, Heinrich Eduard | C38: Kinder- und Jugendbücher; Historische Drucke | D38: Fischer u. Fuchs | E38: monograph; text | F38: PPN766619389 | G38: PPN566841444 | H38: http://resolver.staatsbibliothek-berlin.de/SBB0000F00A00000000 | I38: ger | J38: 1835 | K38: WegehauptDigital | L38: Leipzig | M38: empty | N38: no
A39: Čudesa bez čudesʹ; malenkaja fizika v priměnenii kʹ zabavamʹ/ sost. A. P. Nečaev. S 172 ris. | B39: Nečaev, A. P. | C39: Kinder- und Jugendbücher | D39: Lukovnikov | E39: monograph; text | F39: PPN742094227 | G39: PPN280334869 | H39: http://resolver.staatsbibliothek-berlin.de/SBB0000D0A100000000 | I39: rus | J39: 1911 | K39: WegehauptDigital | L39: Spb. [St. Petersburg] | M39: https://content.staatsbibliothek-berlin.de/dc/742094227.ocr.zip | N39: yes
A40: Nun rathe einmal!; Räthselbüchlein für Kinder von 5 - 10 Jahren | B40: Flinzer, Fedor | C40: Kinder- und Jugendbücher; Historische Drucke | D40: Focke | E40: monograph; text | F40: PPN745597041 | G40: PPN568651901 | H40: http://resolver.staatsbibliothek-berlin.de/SBB0000D6F200000000 | I40: ger | J40: 1864 | K40: WegehauptDigital | L40: Chemnitz | M40: https://content.staatsbibliothek-berlin.de/dc/745597041.ocr.zip | N40: yes
A41: Räthselkranz für Alt und Jung | B41: Ruhkopf, Julie | C41: Kinder- und Jugendbücher; Historische Drucke | D41: Flemming | E41: monograph; text | F41: PPN74623791X | G41: PPN476384494 | H41: http://resolver.staatsbibliothek-berlin.de/SBB0000D85700000000 | I41: ger | J41: 1861 | K41: WegehauptDigital | L41: Glogau | M41: https://content.staatsbibliothek-berlin.de/dc/74623791X.ocr.zip | N41: yes
A42: Merkwürdige Reisen der Gutmannschen Familie; ein Weihnachts- und Geburtstags-Geschenk für die Jugend | B42: Ramberg, H.; Boettger, G.; Dassel, Chr. | C42: Kinder- und Jugendbücher | D42: Brüder Hahn | E42: monograph; text | F42: PPN746870108 | G42: PPN363821880 | H42: http://resolver.staatsbibliothek-berlin.de/SBB0000DBD600000000 | I42: ger | J42: 1816 | K42: WegehauptDigital | L42: Hannover | M42: empty | N42: no
A43: Recipes | C43: Kinder- und Jugendbücher | D43: Orr | E43: monograph; text | F43: PPN746034628 | G43: PPN279781792 | H43: http://resolver.staatsbibliothek-berlin.de/SBB0000D7DD00000000 | I43: eng | J43: 1883 | K43: WegehauptDigital | L43: Springfield, Mass. | M43: https://content.staatsbibliothek-berlin.de/dc/746034628.ocr.zip | N43: yes
A44: Das Turnen in den Spielen der Mädchen; eine Auswahl nützlicher und passender Jugend- und Bewegungspiele ; zur geistigen und körperlichen Erholung des jüngeren Mädchenalters wie als Beitrag zu einer naturgemäßen Jugenderziehung | B44: Bürkner, Hugo; Kloss, Moritz | C44: Kinder- und Jugendbücher | D44: Schönfeld | E44: monograph; text | F44: PPN770493564 | G44: PPN27843424X | H44: http://resolver.staatsbibliothek-berlin.de/SBB000104D400000000 | I44: ger | J44: 1862 | K44: WegehauptDigital | L44: Dresden | M44: https://content.staatsbibliothek-berlin.de/dc/770493564.ocr.zip | N44: yes
A45: Das Ein-mal-Eins in Bilderpracht, wie es den Kindern Freude macht | B45: Reinhardt, Aug.; Reinhardt, V. | C45: Kinder- und Jugendbücher | D45: Kaufmann | E45: monograph; text | F45: PPN741360802 | G45: PPN572962495 | H45: http://resolver.staatsbibliothek-berlin.de/SBB0000CFF400000000 | I45: ger | J45: 1880 | K45: WegehauptDigital | L45: Dresden | M45: https://content.staatsbibliothek-berlin.de/dc/741360802.ocr.zip | N45: yes
A46: Natur-Paradoxe; ein Buch für die Jugend zur Erklärung von Erscheinungen, die mit der täglichen Erfahrung in Widerspruch zu stehen scheinen ; nach Dr. W. Hampson's 'Paradoxes of nature and science' | B46: Schäffer, C.; Hampson, William | C46: Kinder- und Jugendbücher | D46: Teubner | E46: monograph; text | F46: PPN741671417 | G46: PPN408347201 | H46: http://resolver.staatsbibliothek-berlin.de/SBB0000D04500000000 | I46: ger | J46: 1908 | K46: WegehauptDigital | L46: Leipzig; Berlin | M46: https://content.staatsbibliothek-berlin.de/dc/741671417.ocr.zip | N46: yes
A47: Die Meteorologie in Erklärungen und Erzählungen; ein nützliches und unterhaltendes Lesebuch für die reifere Jugend | B47: Moshamer, Joseph A. | C47: Kinder- und Jugendbücher | D47: Im Verl. der k. k. Schulbücher-Verschleiß-Administration | E47: monograph; text | F47: PPN770192904 | G47: PPN348919875 | H47: http://resolver.staatsbibliothek-berlin.de/SBB0001037500000000 | I47: ger | J47: 1844 | K47: WegehauptDigital | L47: Wien | M47: empty | N47: no
A48: Naturstudien im Hause; Plaudereien in der Dämmerstunde ; ein Buch für die Jugend | B48: Schwindrazheim, O.; Kraepelin, Karl | C48: Kinder- und Jugendbücher | D48: Teubner | E48: monograph; text | F48: PPN742265854 | G48: PPN075438097 | H48: http://resolver.staatsbibliothek-berlin.de/SBB0000D0DF00000000 | I48: ger | J48: 1901 | K48: WegehauptDigital | L48: Leipzig | M48: https://content.staatsbibliothek-berlin.de/dc/742265854.ocr.zip | N48: yes
A49: Peter Parley's Visit to London; during the coronation of Queen Victoria | B49: Viktoria < Großbritannien, Königin>; Parley, Peter | C49: Kinder- und Jugendbücher; Historische Drucke | D49: Tilt | E49: monograph; text | F49: PPN771192134 | G49: PPN27953969X | H49: http://resolver.staatsbibliothek-berlin.de/SBB0001262E00000000 | I49: eng | J49: 1839 | K49: WegehauptDigital | L49: London | M49: empty | N49: no
A50: Die kleinen Gärtner, oder Gartenbeschäftigungen für Kinder; enthält einen deutlichen Unterricht, wie Kinder einen kleinen Garten anlegen, behandeln und abwarten können, ohne dabey einen Gärtner zu Hülfe zu nehmen : mit Kupfern | B50: Poscharsky, Christian Friedrich | C50: Kinder- und Jugendbücher; Historische Drucke | D50: Friese | E50: monograph; text | F50: PPN769382053 | G50: PPN389953334 | H50: http://resolver.staatsbibliothek-berlin.de/SBB0000F96300000000 | I50: ger | J50: 1810 | K50: WegehauptDigital | L50: Pirna | M50: empty | N50: no
A51: Carl der Tausendkünstler, oder: Sammlung einfacher und künstlicher, großentheils neuer mechanischer, chemischer, magnetischer und Kartenkunststücke und arithmetischer Belustigungen zur angenehmen geselligen Unterhaltung | B51: Kerndörffer, Heinrich August | C51: Kinder- und Jugendbücher; Historische Drucke | D51: Cnobloch | E51: monograph; text | F51: PPN766428656 | G51: PPN560665571 | H51: http://resolver.staatsbibliothek-berlin.de/SBB0000EF3700000000 | I51: ger | J51: 1840 | K51: WegehauptDigital | L51: Leipzig | M51: empty | N51: no
A52: Der illustrirte Jugendfreund; Schilderungen des Weltgebäudes und seiner Wunder ; in Bilder aus der Natur, dem Leben der Menschen und der Thiere der Vergangenheit und Gegenwart | B52: Thomas, Louis | C52: Kinder- und Jugendbücher; Historische Drucke | D52: Spamer | E52: monograph; text | F52: PPN767132297 | G52: PPN578175231 | H52: http://resolver.staatsbibliothek-berlin.de/SBB0000F2BB00000000 | I52: ger | J52: 1852 | K52: WegehauptDigital | L52: Leipzig | M52: https://content.staatsbibliothek-berlin.de/dc/767132297.ocr.zip | N52: yes
A53: The Child's guide to knowledge; being a collection of useful and familiar questions and answers on every-day subjects; adapted for young persons, and arranged in the most simple and easy language ; by a Lady | C53: Kinder- und Jugendbücher; Historische Drucke | D53: Simpkin [u.a.] | E53: monograph; text | F53: PPN745137695 | G53: PPN550723854 | H53: http://resolver.staatsbibliothek-berlin.de/SBB0000D5D600000000 | I53: eng | J53: 1871 | K53: WegehauptDigital | L53: London | M53: https://content.staatsbibliothek-berlin.de/dc/745137695.ocr.zip | N53: yes
A54: Kleine Bilder-Encyclopedie; [für junge Knaben und Mädchen] | C54: Kinder- und Jugendbücher | D54: Rücker] | E54: monograph; text | F54: PPN770565247 | G54: PPN445549262 | H54: http://resolver.staatsbibliothek-berlin.de/SBB0001055A00000000 | I54: ger | J54: 1808 | K54: WegehauptDigital | L54: [Berlin | M54: empty | N54: no
A55: Naturgeschichte für Kinder | B55: Meyer, F. A. A.; Raff, Georg Christian | C55: Kinder- und Jugendbücher; Historische Drucke | D55: Dieterich | E55: monograph; text | F55: PPN769384986 | G55: PPN141087994 | H55: http://resolver.staatsbibliothek-berlin.de/SBB0000F96900000000 | I55: ger | J55: 1827 | K55: WegehauptDigital | L55: Göttingen | M55: empty | N55: no
A56: Kochbüchlein für die Puppenküche oder erste Anweisung zum Kochen; Für Mädchen von 8-14 Jahren | B56: Löffler, Henriette; Bimbach, Julie | C56: Kinder- und Jugendbücher | D56: Schreiber | E56: monograph; text | F56: PPN769117392 | G56: PPN548218307 | H56: http://resolver.staatsbibliothek-berlin.de/SBB0000F8A000000000 | I56: ger | J56: 1885 | K56: WegehauptDigital | L56: Eßlingen | M56: https://content.staatsbibliothek-berlin.de/dc/769117392.ocr.zip | N56: yes
A57: Naturgeschichte der deutschen Schmetterlinge für die Jugend; Nebst einer passenden Anweisung, sie zu fangen, zuzubereiten, zu ordnen und unbeschädigt zu erhalten | C57: Kinder- und Jugendbücher; Historische Drucke | D57: Groß | E57: monograph; text | F57: PPN75101611X | G57: PPN568829980 | H57: http://resolver.staatsbibliothek-berlin.de/SBB0000E42300000000 | I57: ger | J57: 1805 | K57: WegehauptDigital | L57: Halberstadt | M57: empty | N57: no
A58: Illustrirte Naturgeschichte für die Jugend; mit mehr als 200 color. Abb. | B58: Schubert, Ferdinand; Schubert, Carl | C58: Kinder- und Jugendbücher; Historische Drucke | D58: Sallmayer | E58: monograph; text | F58: PPN749885149 | G58: PPN574523774 | H58: http://resolver.staatsbibliothek-berlin.de/SBB0000E14B00000000 | I58: ger | J58: 1856 | K58: WegehauptDigital | L58: Wien | M58: https://content.staatsbibliothek-berlin.de/dc/749885149.ocr.zip | N58: yes
A59: Spielbuch; enthaltend Gesellschaftsspiele, Auslösen der Pfänder, Rätsel, Charaden | B59: Löwicke, Robert | C59: Kinder- und Jugendbücher; Historische Drucke | D59: Flemming | E59: monograph; text | F59: PPN745605478 | G59: PPN566420597 | H59: http://resolver.staatsbibliothek-berlin.de/SBB0000D71400000000 | I59: ger | J59: 1887 | K59: WegehauptDigital | L59: Glogau | M59: https://content.staatsbibliothek-berlin.de/dc/745605478.ocr.zip | N59: yes
A60: Reise einer Tante in vieler Herren Länder | B60: Bernhardi, Elisabeth Eleonore | C60: Kinder- und Jugendbücher | E60: monograph; text | F60: PPN77088976X | G60: PPN444747249 | H60: http://resolver.staatsbibliothek-berlin.de/SBB0001074200000000 | I60: ger | J60: 1817 | K60: WegehauptDigital | L60: [Freiberg] | M60: empty | N60: no
A61: Naturgeschichte der Insekten für die Jugend ; Mit Kupfern | C61: Kinder- und Jugendbücher | D61: Campe | E61: monograph; text | F61: PPN770372821 | G61: PPN32489211X | H61: http://resolver.staatsbibliothek-berlin.de/SBB0001046000000000 | I61: ger | J61: 1820 | K61: WegehauptDigital | L61: Nürnberg | M61: empty | N61: no
A62: Kleines Käferbuch für Knaben; eine Anleitung zur Kenntniß der Käfer im Allgemeinen wie auch zur Anlage und zweckmäßigen Einrichtung von Käfersammlungen ; mit 72 illuminierten Abbildungen auf 5 Tafeln | C62: Kinder- und Jugendbücher; Historische Drucke | D62: Hendel | E62: monograph; text | F62: PPN742562549 | G62: PPN560569718 | H62: http://resolver.staatsbibliothek-berlin.de/SBB0000D21A00000000 | I62: ger | J62: 1862 | K62: WegehauptDigital | L62: Halle | M62: https://content.staatsbibliothek-berlin.de/dc/742562549.ocr.zip | N62: yes
A63: Entdeckungsreisen in Haus und Hof; mit seinen jungen Freunden unternommen | B63: Wagner, H. | C63: Kinder- und Jugendbücher | D63: Spamer | E63: monograph; text | F63: PPN74364154X | G63: PPN270201556 | H63: http://resolver.staatsbibliothek-berlin.de/SBB0000D30500000000 | I63: ger | J63: 1866 | K63: WegehauptDigital | L63: Leipzig | M63: https://content.staatsbibliothek-berlin.de/dc/74364154X.ocr.zip | N63: yes
A64: [Rätselbuch] | C64: Kinder- und Jugendbücher; Historische Drucke | E64: monograph; text | F64: PPN766622541 | G64: PPN571694535 | H64: http://resolver.staatsbibliothek-berlin.de/SBB0000F01000000000 | I64: ger | J64: 1830 | K64: WegehauptDigital | L64: [S.l.] | M64: empty | N64: no
A65: Naturstudien im Garten; Plaudereien am Sonntag Nachmittag ; ein Buch für die Jugend | B65: Schwindrazheim, O.; Kraepelin, Karl | C65: Kinder- und Jugendbücher | D65: Teubner | E65: monograph; text | F65: PPN742297330 | G65: PPN075795655 | H65: http://resolver.staatsbibliothek-berlin.de/SBB0000D0EF00000000 | I65: ger | J65: 1901 | K65: WegehauptDigital | L65: Leipzig | M65: https://content.staatsbibliothek-berlin.de/dc/742297330.ocr.zip | N65: yes
A66: Charakterbilder aus der Thierwelt verschiedener Welttheile; zur Belehrung und Unterhaltung der Jugend | B66: Hoffmann, W. | C66: Kinder- und Jugendbücher | D66: Nitzschke | E66: monograph; text | F66: PPN743630491 | G66: PPN26518777X | H66: http://resolver.staatsbibliothek-berlin.de/SBB0000D2F600000000 | I66: ger | J66: 1862 | K66: WegehauptDigital | L66: Stuttgart | M66: https://content.staatsbibliothek-berlin.de/dc/743630491.ocr.zip | N66: yes
A67: Neue Wanderungen durch die Thierwelt; ein Buch für Knaben und Mädchen | B67: Kirchhoff, Johann; Reichenbach, A. B. | C67: Kinder- und Jugendbücher | D67: Kretzschmar | E67: monograph; text | F67: PPN770577199 | G67: PPN311107745 | H67: http://resolver.staatsbibliothek-berlin.de/SBB0001057F00000000 | I67: ger | J67: 1848 | K67: WegehauptDigital | L67: Leipzig | M67: empty | N67: no
A68: Reisen in die Ferne oder Vater Reinhold's Mittheilungen über die Erde und ihre Bewohner; ein Lese- und Bilderbuch zur Belehrung und Unterhaltung der Jugend in der Völkerkunde und Erdbeschreibung | B68: Geissler, ...; Boettger, Gottlieb; Maukisch, Heinrich Eduard | C68: Kinder- und Jugendbücher; Historische Drucke | D68: Taubert | E68: monograph; text | F68: PPN77101631X | G68: PPN278734375 | H68: http://resolver.staatsbibliothek-berlin.de/SBB00010A6800000000 | I68: ger | J68: 1836 | K68: WegehauptDigital | L68: Leipzig | M68: empty | N68: no
A69: Lustige Bilder-Räthsel für kluge Kinder | B69: Breitschwert, W. | C69: Kinder- und Jugendbücher | D69: Hoffmann <Thienemann> | E69: monograph; text | F69: PPN745436269 | G69: PPN279375425 | H69: http://resolver.staatsbibliothek-berlin.de/SBB0000D6B000000000 | I69: ger | J69: 1875 | K69: WegehauptDigital | L69: Stuttgart | M69: https://content.staatsbibliothek-berlin.de/dc/745436269.ocr.zip | N69: yes
A70: Wie viel sind's?; Ein Bilderbuch | B70: Schmidhammer, Arpad; Holst, Adolf | C70: Kinder- und Jugendbücher | D70: Scholz | E70: monograph; text | F70: PPN770464904 | G70: PPN57409041X | H70: http://resolver.staatsbibliothek-berlin.de/SBB000104A500000000 | I70: ger | J70: 1913 | K70: WegehauptDigital | L70: Mainz | M70: https://content.staatsbibliothek-berlin.de/dc/770464904.ocr.zip | N70: yes
A71: Nun rath' einmal!; Illustrirtes Räthselbuch für artige Kinder | B71: Gerstenberg, Karl | C71: Kinder- und Jugendbücher | D71: Schreiber | E71: monograph; text | F71: PPN745435734 | G71: PPN558101321 | H71: http://resolver.staatsbibliothek-berlin.de/SBB0000D6AE00000000 | I71: ger | J71: 1878 | K71: WegehauptDigital | L71: Eßlingen | M71: https://content.staatsbibliothek-berlin.de/dc/745435734.ocr.zip | N71: yes
A72: Der Thiergarten zu Lilienthal; Ein unterhaltendes naturgeschichtliches Bilder- und Lesebuch für die Jugend ... (Mit 12 großen u. 82 kleineren Abbildungen in schönem Farbendruck.) | B72: Beumer, Philipp Jakob | C72: Kinder- und Jugendbücher; Historische Drucke | D72: Bagel | E72: monograph; text | F72: PPN770507050 | G72: PPN44513125X | H72: http://resolver.staatsbibliothek-berlin.de/SBB000104E500000000 | I72: ger | J72: 1850 | K72: WegehauptDigital | L72: Wesel | M72: https://content.staatsbibliothek-berlin.de/dc/770507050.ocr.zip | N72: yes
A73: Zoologie du jeune age ou histoire naturelle des animaux; écrite pour la jeunesse | B73: Lereboullet, Auguste | C73: Kinder- und Jugendbücher; Historische Drucke | D73: Derivaux | E73: monograph; text | F73: PPN749918349 | G73: PPN280187092 | H73: http://resolver.staatsbibliothek-berlin.de/SBB0000E19400000000 | I73: fre | J73: 1860 | K73: WegehauptDigital | L73: Strasbourg | M73: https://content.staatsbibliothek-berlin.de/dc/749918349.ocr.zip | N73: yes
A74: Naturgeschichte der reißenden Thiere; Thierschilderungen für Freunde der Natur u. die Jugend aller Stände ; Mit 36 colorierten Taf. Original-Abb. | B74: Mann, Gustav | C74: Kinder- und Jugendbücher; Historische Drucke | D74: Schweizerbart | E74: monograph; text | F74: PPN757120954 | G74: PPN566464845 | H74: http://resolver.staatsbibliothek-berlin.de/SBB0000ECEC00000000 | I74: ger | J74: 1857 | K74: WegehauptDigital | L74: Stuttgart | M74: https://content.staatsbibliothek-berlin.de/dc/757120954.ocr.zip | N74: yes
A75: Die Naturgeschichte für Kinder und Elementarschüler; oder erster Unterricht über das Mineralreich, Pflanzenreich und Thierreich. Mit über 300 color. Abb. | C75: Kinder- und Jugendbücher | D75: Schreiber & Schill | E75: monograph; text | F75: PPN770201407 | G75: PPN389491020 | H75: http://resolver.staatsbibliothek-berlin.de/SBB0001039700000000 | I75: ger | J75: 1855 | K75: WegehauptDigital | L75: Stuttgart [u.a.] | M75: https://content.staatsbibliothek-berlin.de/dc/770201407.ocr.zip | N75: yes
A76: Neuer Orbis Pictus für die Jugend oder Schauplatz der Natur, der Kunst und des Menschenlebens in 322 lithographischen Abbildungen mit genauer Erklärung in deutscher, lateinischer, französischer und englischer Sprache | B76: Gailer, Jacob E.; Comenius, Johann Amos | C76: Kinder- und Jugendbücher; Historische Drucke | D76: Mäcken | E76: monograph; text | F76: PPN767066812 | G76: PPN230802753 | H76: http://resolver.staatsbibliothek-berlin.de/SBB0000F20600000000 | I76: eng | J76: 1835 | K76: WegehauptDigital | L76: Reutlingen | M76: empty | N76: no
A77: Biblische Naturgeschichte für Schulen und Familien | B77: Barth, Christian Gottlob | C77: Kinder- und Jugendbücher | D77: Vereinsbuchhandl. [usw.] | E77: monograph; text | F77: PPN743860241 | G77: PPN54707901X | H77: http://resolver.staatsbibliothek-berlin.de/SBB0000D35E00000000 | I77: ger | J77: 1874 | K77: WegehauptDigital | L77: Calw | M77: https://content.staatsbibliothek-berlin.de/dc/743860241.ocr.zip | N77: yes
A78: Die Schwarzwald-Reise; Eine christliche Erzählung und zugleich eine landschaftliche Beschreibung, natürliche Geographie und Geognosie des würtembergischen Schwarzwaldes ; Für die Jugend der höheren Stände | B78: Schwarz, Eduard | C78: Kinder- und Jugendbücher; Historische Drucke | D78: Balz | E78: monograph; text | F78: PPN77096351X | G78: PPN319610543 | H78: http://resolver.staatsbibliothek-berlin.de/SBB00010A1100000000 | I78: ger | J78: 1836 | K78: WegehauptDigital | L78: Stuttgart | M78: empty | N78: no
A79: Der aufrichtige Kalendermann; Ein gar kurioses und nützliches Buch Für die Jugend und den gemeinen Bürger und Bauersmann verfertiget | B79: Steinbeck, Christoph Gottlieb | C79: Kinder- und Jugendbücher; Historische Drucke; VD18 digital | D79: Steinbeck; Fleischer | E79: monograph; text | F79: PPN766725251 | G79: PPN663601738 | H79: http://resolver.staatsbibliothek-berlin.de/SBB0000F0B200000000 | I79: ger | J79: 1792 | K79: WegehauptDigital; VD18 digital | L79: Langenberg ohnweit Gera; Leipzig | M79: empty | N79: no
A80: Naturgeschichte des Pflanzenreiches in Bildern; nach der Anordnung des allgemein bekannten u. beliebten Lehrbuchs der Naturgeschichte von G[otthilf] H[einrich] v. Schubert | B80: Schubert, Gotthilf Heinrich; Hochstetter, Christian Ferdinand | C80: Kinder- und Jugendbücher; Historische Drucke | D80: Schreiber | E80: monograph; text | F80: PPN749900172 | G80: PPN568822358 | H80: http://resolver.staatsbibliothek-berlin.de/SBB0000E16800000000 | I80: fre | J80: 1865 | K80: WegehauptDigital | L80: Eßlingen a. N. | M80: https://content.staatsbibliothek-berlin.de/dc/749900172.ocr.zip | N80: yes
A81: Die Hausthiere nebst ihrer Beschäftigung und Verwendung; Ein nützliches und unterhaltendes Bilderbuch für die Jugend ; Mit 80 Haupt- und Nebenbildern und erklärendem Text | C81: Kinder- und Jugendbücher; Historische Drucke | D81: Zeh | E81: monograph; text | F81: PPN756434564 | G81: PPN559169582 | H81: http://resolver.staatsbibliothek-berlin.de/SBB0000EA8E00000000 | I81: ger | J81: 1846 | K81: WegehauptDigital | L81: Nürnberg | M81: empty | N81: no
A82: Die Jugendspiele; ein Leitfaden bei der Einführung und Übung von Turn- und Jugendspielen | B82: Eitner, Gustav | C82: Kinder- und Jugendbücher | D82: Voigtländer | E82: monograph; text | F82: PPN745185738 | G82: PPN236366599 | H82: http://resolver.staatsbibliothek-berlin.de/SBB0000D64600000000 | I82: ger | J82: 1890 | K82: WegehauptDigital | L82: Kreuznach [u.a.] | M82: https://content.staatsbibliothek-berlin.de/dc/745185738.ocr.zip | N82: yes
A83: Das Mikroskop; mit 90 Abbildungen | B83: Schertel, Sigmund | C83: Kinder- und Jugendbücher; Historische Drucke | D83: Union Dt. Verlagsges. | E83: monograph; text | F83: PPN741301490 | G83: PPN573714444 | H83: http://resolver.staatsbibliothek-berlin.de/SBB0000CFB500000000 | I83: ger | J83: 1900 | K83: WegehauptDigital | L83: Stuttgart [u.a.] | M83: https://content.staatsbibliothek-berlin.de/dc/741301490.ocr.zip | N83: yes
A84: Naturgeschichte für Kinder | B84: Lippold, Georg Heinrich Christian; Funke, Carl Philipp | C84: Kinder- und Jugendbücher; Historische Drucke | D84: Kummer | E84: monograph; text | F84: PPN769508758 | G84: PPN239889762 | H84: http://resolver.staatsbibliothek-berlin.de/SBB0000F99B00000000 | I84: ger | J84: 1827 | K84: WegehauptDigital | L84: Leipzig | M84: empty | N84: no
A85: Der gewandte Zauberkünstler und Hexenmeister in Familien- und Gesellschaftskreisen; in Darstellung der lehreichsten und unterhaltendsten Kunststücke auf dem Gebiete der natürlichen Magie, der Taschen- und Kartenspieler und der Rechenkunst ; mit Bildern | B85: Ortleb, Alexander | C85: Kinder- und Jugendbücher; Historische Drucke | D85: Linser | E85: monograph; text | F85: PPN745827632 | G85: PPN569413095 | H85: http://resolver.staatsbibliothek-berlin.de/SBB0000D75C00000000 | I85: ger | J85: 1897 | K85: WegehauptDigital | L85: Pankow-Berlin | M85: https://content.staatsbibliothek-berlin.de/dc/745827632.ocr.zip | N85: yes
A86: Der Schmetterlingsfreund; Beschreibung d. vorzügl. mitteleurop. Schmetterlinge nebst Anl. dieselben zu fangen, deren Puppen u. Raupen aufzuziehen u. eine Samml. anzulegen ; für d. Jugend verf. ; mit 236 Abb. auf 23 Taf. | B86: Hofmann, Ernst | C86: Kinder- und Jugendbücher | D86: Hoffmann | E86: monograph; text | F86: PPN769120490 | G86: PPN559723946 | H86: http://resolver.staatsbibliothek-berlin.de/SBB0000F8B000000000 | I86: ger | J86: 1883 | K86: WegehauptDigital | L86: Stuttgart | M86: https://content.staatsbibliothek-berlin.de/dc/769120490.ocr.zip | N86: yes
A87: Naturgeschichte Der Amphibien, Fische, Weich- und Schaalenthiere, Insekten, Würmer und Strahlenthiere in Bildern ... zum Anschauungs-Unterricht für die Jugend ... nach der ...Naturgeschichte für Schulen; mit erklärendem Texte in deutscher und französischer Sprache | B87: Schubert, Gotthilf Heinrich | C87: Kinder- und Jugendbücher; Historische Drucke | D87: Schreiber & Schill | E87: monograph; text | F87: PPN769048684 | G87: PPN568791290 | H87: http://resolver.staatsbibliothek-berlin.de/SBB0000F82200000000 | I87: ger | J87: 1849 | K87: WegehauptDigital | L87: Eßlingen; Stuttgart | M87: empty | N87: no
A88: Wald und Meer; Schilderungen aus dem Naturleben der Thiere und Pflanzen | B88: Ramberg, Heinrich; Jury, Wilhelm; Schasler, Max | C88: Kinder- und Jugendbücher; Historische Drucke | D88: Hasselberg | E88: monograph; text | F88: PPN749886765 | G88: PPN27954653X | H88: http://resolver.staatsbibliothek-berlin.de/SBB0000E15200000000 | I88: ger | J88: 1853 | K88: WegehauptDigital | L88: Berlin | M88: https://content.staatsbibliothek-berlin.de/dc/749886765.ocr.zip | N88: yes
A89: Naturhistorisches Bilder- und Lese-Buch oder Erzählungen über Gegenstände aus den drei Reichen der Natur; Nebst 300 illuminirten Abbildungen von [Konrad] Horny und einer kurzen Erklärung derselben in Versen | B89: Horny, Konrad; Glatz, Jakob | C89: Kinder- und Jugendbücher; Historische Drucke | D89: Frommann | E89: monograph; text | F89: PPN769046053 | G89: PPN371007631 | H89: http://resolver.staatsbibliothek-berlin.de/SBB0000F81F00000000 | I89: ger | J89: 1803 | K89: WegehauptDigital | L89: Jena | M89: empty | N89: no
A90: Das Spiel im Zimmer; eine reichhaltige Sammlung ausgewählter Spiele zum Gebrauche für jung und alt, für den Einzelnen, wie für kleinere und größere Kreise | B90: Mittenzwey, L. | C90: Kinder- und Jugendbücher | D90: Merseburger | E90: monograph; text | F90: PPN745139965 | G90: PPN567083055 | H90: http://resolver.staatsbibliothek-berlin.de/SBB0000D5E900000000 | I90: ger | J90: 1887 | K90: WegehauptDigital | L90: Leipzig | M90: https://content.staatsbibliothek-berlin.de/dc/745139965.ocr.zip | N90: yes
A91: Reise durch das Berner Oberland nach Unterwalden; für die Jugend beschrieben | B91: Lory, G.; Burgdorfer, D.; Meisner, Friedrich | C91: Kinder- und Jugendbücher | D91: Burgdorfer | E91: volume; text | F91: PPN770944965 | G91: PPN282315799 | H91: http://resolver.staatsbibliothek-berlin.de/SBB000109F000020000 | I91: ger | J91: 1821 | K91: WegehauptDigital | L91: Bern | M91: empty | N91: no
A92: Conversations-Lexicon für die Jugend | C92: Kinder- und Jugendbücher; Historische Drucke | D92: Goedsche | E92: volume; text | F92: PPN766562786 | G92: PPN562017402 | H92: http://resolver.staatsbibliothek-berlin.de/SBB0000EF8800020000 | I92: ger | J92: 1840 | K92: WegehauptDigital | L92: Meissen | M92: empty | N92: no
A93: Der kleine Physiker, oder Unterhaltungen über natürliche Dinge, für Kinder | B93: Höpfner, Adolf Friedrich | C93: Kinder- und Jugendbücher | D93: Keyser | E93: volume; text | F93: PPN746626002 | G93: PPN746625758 | H93: http://resolver.staatsbibliothek-berlin.de/SBB0000DB6F00020000 | I93: ger | J93: 1804 | K93: WegehauptDigital | L93: Erfurt | M93: empty | N93: no
A94: Der technologische Jugendfreund oder Unterhaltende Wanderungen in die Werkstätte der Künstler und Handwerker, zur nöthigen Kenntniß derselben | B94: Blasche, Bernhard Heinrich | C94: Kinder- und Jugendbücher | D94: Wilmans | E94: volume; text | F94: PPN770196195 | G94: PPN335885187 | H94: http://resolver.staatsbibliothek-berlin.de/SBB0001038200010000 | I94: ger | J94: 1804 | K94: WegehauptDigital | L94: Frankfurt am Mayn | M94: empty | N94: no
A95: Tempel der Natur und Kunst | B95: Hirschmann, C. A. | C95: Kinder- und Jugendbücher | D95: Tauchnitz | E95: volume; text | F95: PPN781903688 | G95: PPN563410795 | H95: http://resolver.staatsbibliothek-berlin.de/SBB0001568700050000 | I95: ger | J95: 1805 | K95: WegehauptDigital | L95: Leipzig | M95: empty | N95: no
A96: Der mechanische Jugendfreund oder faßliche und unterhaltende Darstellung der Lehre vom Gleichgewicht und der Bewegung, mit der Beschreibung der dazu gehörigen Maschinen und selbst mit Beyfügung mancher belustigenden mechanischen Kunststücke; Zweyter Theil ; Mit sieben Kupfertafeln | B96: Poppe, Johann Heinrich Moritz | C96: Kinder- und Jugendbücher; Historische Drucke | D96: Wilmans | E96: volume; text | F96: PPN746345666 | G96: PPN236461788 | H96: http://resolver.staatsbibliothek-berlin.de/SBB0000D8D300010000 | I96: ger | J96: 1821 | K96: WegehauptDigital | L96: Frankfurt am Main | M96: empty | N96: no
A97: Naturgeschichte für die deutsche Jugend | B97: Hochstetter, Christian Ferdinand; Gebauer, Christian August | C97: Kinder- und Jugendbücher; Historische Drucke | D97: Löflund | E97: volume; text | F97: PPN769087779 | G97: PPN557898129 | H97: http://resolver.staatsbibliothek-berlin.de/SBB0000F85900010000 | I97: ger | J97: 1829 | K97: WegehauptDigital | L97: Stuttgart | M97: empty | N97: no
A98: Reisen in dem Mittelmeere und in einigen der angränzenden Länder ; Theil 4 | B98: Richter, Theodor Friedrich Maximilian | C98: Kinder- und Jugendbücher | D98: Arnold | E98: volume; text | F98: PPN781607434 | G98: PPN246368152 | H98: http://resolver.staatsbibliothek-berlin.de/SBB000155EB00090000 | I98: ger | J98: 1829 | K98: WegehauptDigital | L98: Dresden | M98: empty | N98: no
A99: Physikalischer Kinderfreund | B99: Vieth, Gerhard Ulrich Anton | C99: Kinder- und Jugendbücher; Historische Drucke | D99: Barth | E99: volume; text | F99: PPN751110981 | G99: PPN345242955 | H99: http://resolver.staatsbibliothek-berlin.de/SBB0000E47700000000 | I99: ger | J99: 1801 | K99: WegehauptDigital | L99: Leipzig | M99: empty | N99: no
A100: Orbis pictus | B100: Lauckhard, Carl F. | C100: Kinder- und Jugendbücher | D100: Günther | E100: volume; text | F100: PPN746212909 | G100: PPN620970413 | H100: http://resolver.staatsbibliothek-berlin.de/SBB0000D82E00010000 | I100: ger | J100: 1872 | K100: WegehauptDigital | L100: Leipzig | M100: https://content.staatsbibliothek-berlin.de/dc/746212909.ocr.zip | N100: yes
...

Sheet publishers_total
A1: language | B1: ger | O1: language | P1: ger | R1: Andere | S1: 896
R2: Spamer | S2: 85
A3: Zeilenbeschriftungen | B3: Anzahl von publisher | O3: Zeilenbeschriftungen | P3: Anzahl von publisher | R3: Fleischer | S3: 36
A4: Andere | B4: 896 | O4: May | P4: 1 | R4: Industrie-Comptoir | S4: 31
A5: Spamer | B5: 85 | O5: [Basedow] | P5: 3 | R5: Arnold | S5: 24
A6: Fleischer | B6: 36 | O6: A. W. Hayn's Erben | P6: 1 | R6: Schreiber | S6: 23
A7: Industrie-Comptoir | B7: 31 | O7: A. Weichert | P7: 1 | R7: Grözinger | S7: 20
A8: Arnold | B8: 24 | O8: Adler | P8: 1 | R8: Teubner | S8: 20
A9: Schreiber | B9: 23 | O9: Agentur des Rauhen Hauses | P9: 1 | R9: Barth | S9: 18
A10: Grözinger | B10: 20 | O10: Amelang | P10: 16 | R10: Oehmigke | S10: 18
A11: Teubner | B11: 20 | O11: Andrea | P11: 1 | R11: Campe | S11: 18
A12: Campe | B12: 18 | O12: Andreä | P12: 1 | R12: Velhagen & Klasing | S12: 16
A13: Oehmigke | B13: 18 | O13: Andreäische Buchhandlung | P13: 1 | R13: Amelang | S13: 16
A14: Barth | B14: 18 | O14: Anich | P14: 1 | R14: Monath | S14: 16
A15: Velhagen & Klasing | B15: 16 | O15: Anton | P15: 1 | R15: Hoffmann | S15: 15
... A24: Wilmans | B24: 11 | O24: Bagel | P24: 9 | R24: Dieterich | S24: 10
A25: Vogel | B25: 11 | O25: Bagel] | P25: 1
A26: Flemming | B26: 10 | O26: Balz | P26: 6
A27: Dieterich | B27: 10 | O27: Balz und Schramm | P27: 2
A28: Gesamtergebnis | B28: 1358 | O28: Barth | P28: 18
O29: Barth & Hamberger | P29: 1
O30: Bartholomäi | P30: 1
O31: Bartholomäus | P31: 2
O32: Basse | P32: 2
O33: Bauer u. Raspe | P33: 1
O34: Bauer und Raspe | P34: 2
O35: Baukasten-Verl.] | P35: 2
O36: Baumeister | P36: 6
O37: Baumgaertner | P37: 1
O38: Baumgärtner | P38: 3
O39: Beck | P39: 2
O40: Benziger | P40: 1
... O498: Zieger | P498: 2
O499: (Leer)
O500: Gesamtergebnis | P500: 1358

Sheet languages
A1: Zeilenbeschriftungen | B1: Anzahl von language
A2: ger | B2: 1401
A3: fre | B3: 160
A4: eng | B4: 65
A5: lat | B5: 9
A6: rus | B6: 4
A7: ita | B7: 4
A8: dut | B8: 2
A9: dan | B9: 1
A10: swe | B10: 1
A11: pol | B11: 1
A12: Gesamtergebnis | B12: 1648
A14: Zeilenbeschriftungen | B14: Anzahl von language
A15: ger | B15: 1401
A16: no | B16: 803
A17: yes | B17: 598
A18: fre | B18: 160
A19: no | B19: 129
A20: yes | B20: 31
A21: eng | B21: 65
A22: no | B22: 34
A23: yes | B23: 31
A24: lat | B24: 9
A25: no | B25: 9
A26: rus | B26: 4
... A38: Gesamtergebnis | B38: 1648
A40: Zeilenbeschriftungen | B40: Anzahl von language
A41: dan | B41: 1
A42: dut | B42: 2
A43: eng | B43: 65
A44: fre | B44: 160
A45: fre; ger; lat; ita | B45: 1
A46: fre; lat; rus; ger; ita | B46: 1
A47: ger | B47: 1401
A48: ger; fre | B48: 10
A49: ger; fre; eng; ita | B49: 2
A50: ita | B50: 4
A51: lat | B51: 9
A52: lat; cze; ger; fre | B52: 1
... A57: swe | B57: 1
A58: (Leer)
A59: Gesamtergebnis | B59: 1666

Sheet OCR_ger
A1: title | B1: creator | C1: subject | D1: publisher | E1: type | F1: digital object identifier | G1: physical object identifier | H1: URL | I1: language | J1: date | K1: relation | L1: coverage | M1: OCR URL | N1: OCR found?
A2: Abrégé de toutes les sciences, ou encyclopédie des enfants; mise dans un nouvel ordre,... | B2: Buqcellos, ...; Blocquel, Simon | C2: Kinder- und Jugendbücher; Historische Drucke | D2: Delarue ;; Castiaux | E2: monograph; text | F2: PPN766849139 | G2: PPN548262071 | H2: http://resolver.staatsbibliothek-berlin.de/SBB0000F13000000000 | I2: fre | J2: 1816 | K2: WegehauptDigital | L2: Paris; Lille | M2: empty | N2: no
A3: Naturgeschichte für Kinder | B3: Raff, Georg Christian | C3: Kinder- und Jugendbücher; Historische Drucke | D3: Sammer | E3: monograph; text | F3: PPN749770333 | G3: PPN279536941 | H3: http://resolver.staatsbibliothek-berlin.de/SBB0000E0AE00000000 | I3: ger | J3: 1846 | K3: WegehauptDigital | L3: Wien | M3: empty | N3: no
A4: Die Entstehung der Erde | B4: Kranz, Wilhelm; Meyer, Max Wilhelm | C4: Kinder- und Jugendbücher; Historische Drucke | D4: Paetel | E4: monograph; text | F4: PPN741297272 | G4: PPN276525892 | H4: http://resolver.staatsbibliothek-berlin.de/SBB0000CFAB00000000 | I4: ger | J4: 1907 | K4: WegehauptDigital | L4: Berlin | M4: https://content.staatsbibliothek-berlin.de/dc/741297272.ocr.zip | N4: yes
A5: Die Schulwerkstatt; ein Leitfaden zur Einführung der technischen Arbeiten in die Schule | B5: Barth, Ernst; Niederley, W. | C5: Kinder- und Jugendbücher; Historische Drucke | D5: Velhagen & Klasing | E5: monograph; text | F5: PPN745116574 | G5: PPN453868991 | H5: http://resolver.staatsbibliothek-berlin.de/SBB0000D59B00000000 | I5: ger | J5: 1882 | K5: WegehauptDigital | L5: Bielefeld [u.a.] | M5: https://content.staatsbibliothek-berlin.de/dc/745116574.ocr.zip | N5: yes
A6: Der junge Eisenbahnbauer; eine Anleitung zur Selbstherstellung von Modelleisenbahnen ; mit 118 Abb. | B6: Hermuth, Paul | C6: Kinder- und Jugendbücher; Historische Drucke | D6: Union Dt. Verl.-Gesellsch. | E6: monograph; text | F6: PPN744069432 | G6: PPN559338228 | H6: http://resolver.staatsbibliothek-berlin.de/SBB0000D52F00000000 | I6: ger | J6: 1916 | K6: WegehauptDigital | L6: Stuttgart [u.a.] | M6: https://content.staatsbibliothek-berlin.de/dc/744069432.ocr.zip | N6: yes
A7: Neuer Räthselschatz; für die Jugend zur Übung im Denken und zur belehrenden Unterhaltung | B7: Schäffer, W. | C7: Kinder- und Jugendbücher; Historische Drucke | D7: Oehmigke | E7: monograph; text | F7: PPN745271243 | G7: PPN573465517 | H7: http://resolver.staatsbibliothek-berlin.de/SBB0000D67F00000000 | I7: ger | J7: 1865 | K7: WegehauptDigital | L7: Neu-Ruppin | M7: https://content.staatsbibliothek-berlin.de/dc/745271243.ocr.zip | N7: yes
A8: Wander- und Spielbüchlein für Schüler und Schülerinnen | B8: Matzdorf, Paul | C8: Kinder- und Jugendbücher | D8: Strauch | E8: monograph; text | F8: PPN745123694 | G8: PPN56682809X | H8: http://resolver.staatsbibliothek-berlin.de/SBB0000D5AD00000000 | I8: ger | J8: 1910 | K8: WegehauptDigital | L8: Leipzig | M8: https://content.staatsbibliothek-berlin.de/dc/745123694.ocr.zip | N8: yes
A9: Causeries sur la science; illustrées de 94 gravures | B9: Tissandier, Gaston | C9: Kinder- und Jugendbücher; Historische Drucke | D9: Hachette | E9: monograph; text | F9: PPN745272312 | G9: PPN578011344 | H9: http://resolver.staatsbibliothek-berlin.de/SBB0000D68300000000 | I9: fre | J9: 1880 | K9: WegehauptDigital | L9: Paris | M9: https://content.staatsbibliothek-berlin.de/dc/745272312.ocr.zip | N9: yes
A10: Der unerschöpfliche Maître de Plaisir; oder die Kunst, in allen Jahreszeiten, im Freien und zu Hause, so wie an allen nur denkbaren Freudentagen die unterhaltendsten und belustigendsten Parthieen anzuordnen ; Enthaltend die besten Spiele, Lieder, Declamir- und Kunststücke, Räthsel, Charaden [et]c. Ein unentbehrliches Haus- und Handbuch für alle lebensfrohe deutsche Familien | C10: Kinder- und Jugendbücher; Historische Drucke | D10: Voigt | E10: monograph; text | F10: PPN767042255 | G10: PPN280073852 | H10: http://resolver.staatsbibliothek-berlin.de/SBB0000F1B700000000 | I10: ger | J10: 1822 | K10: WegehauptDigital | L10: Nordhausen; Sondershausen | M10: empty | N10: no
A11: Im Grünen oder Die kleinen Pflanzenfreunde; kleine Erzählungen aus dem Pflanzenreich | B11: Wagner, Hermann | C11: Kinder- und Jugendbücher | D11: Spamer | E11: monograph; text | F11: PPN743675703 | G11: PPN578788829 | H11: http://resolver.staatsbibliothek-berlin.de/SBB0000D31400000000 | I11: ger | J11: 1878 | K11: WegehauptDigital | L11: Leipzig | M11: https://content.staatsbibliothek-berlin.de/dc/743675703.ocr.zip | N11: yes
A12: Das Buch der Gesellschaftsspiele | B12: Weller, Hermine | C12: Kinder- und Jugendbücher | D12: Fischer | E12: monograph; text | F12: PPN745213553 | G12: PPN581117719 | H12: http://resolver.staatsbibliothek-berlin.de/SBB0000D65A00000000 | I12: ger | J12: 1910 | K12: WegehauptDigital | L12: Dresden | M12: https://content.staatsbibliothek-berlin.de/dc/745213553.ocr.zip | N12: yes
A13: Der gelehrte Spielkamerad; Anleitung für kleine Physiker, Chemiker, Botaniker und Naturfreunde zum Experimentieren, zur Anlage von Pflanzen-, Stein-, Muschel-, Insekten-, Schmetterling-, Vogel-, Briefmarken-Sammlungen ect. sowie zur Pflege der Hausthiere und des Hausgartens ; ein Supplement zum "Spielbuch für Knaben" | B13: Wagner, Hermann | C13: Kinder- und Jugendbücher | D13: Spamer | E13: monograph; text | F13: PPN74270906X | G13: PPN578814706 | H13: http://resolver.staatsbibliothek-berlin.de/SBB0000D2AA00000000 | I13: ger | J13: 1877 | K13: WegehauptDigital | L13: Leipzig | M13: https://content.staatsbibliothek-berlin.de/dc/74270906X.ocr.zip | N13: yes
A14: Des fleißigen Mädchens Koch-Büchlein für die Puppen-Küche | C14: Kinder- und Jugendbücher; Historische Drucke | D14: Meisel | E14: monograph; text | F14: PPN745432069 | G14: PPN278721036 | H14: http://resolver.staatsbibliothek-berlin.de/SBB0000D6A800000000 | I14: ger | J14: 1876 | K14: WegehauptDigital | L14: Leipzig; Herisau; Stuttgart | M14: https://content.staatsbibliothek-berlin.de/dc/745432069.ocr.zip | N14: yes
A15: Naturgeschichte für Kinder, von M. Georg Christian Raff, ordentlichen Lehrer der Geschichte und Geographie auf dem Lyceum zu Göttingen. Mit vierzehn Kupfertafeln | B15: Raff, Georg Christian | C15: Kinder- und Jugendbücher; Historische Drucke | E15: monograph; text | F15: PPN769119182 | G15: PPN571683770 | H15: http://resolver.staatsbibliothek-berlin.de/SBB0000F8A900000000 | I15: ger | J15: 1802 | K15: WegehauptDigital | L15: Frankfurt; Leipzig | M15: empty | N15: no
A16: Kleine Bilderschule für die Jugend | B16: Hausius, Karl Gottlob | C16: Kinder- und Jugendbücher; Historische Drucke | D16: Voß | E16: monograph; text | F16: PPN757417825 | G16: PPN55916422X | H16: http://resolver.staatsbibliothek-berlin.de/SBB0000ED8900000000 | I16: ger | J16: 1807 | K16: WegehauptDigital | L16: Leipzig | M16: empty | N16: no
A17: Vollständiges Giftbuch oder Unterricht, die Giftpflanzen, Giftminerale und Giftthiere kennen zu lernen, und Gesundheit und Leben gegen Vergiftungs-Gefahren sicher zu stellen | C17: Kinder- und Jugendbücher | D17: Voigt | E17: monograph; text | F17: PPN770137474 | G17: PPN406020620 | H17: http://resolver.staatsbibliothek-berlin.de/SBB0001031A00000000 | I17: ger | J17: 1817 | K17: WegehauptDigital | L17: Sondershausen | M17: empty | N17: no
A18: Schneiders Typen-Atlas; naturwissenschaftlich-geographischer Hand-Atlas für Schule und Haus | B18: Schneider, Oskar; Claudius, W.; Leutemann, H.; Mützel, G.; Seidel, C. F. | C18: Kinder- und Jugendbücher | D18: Meinhold | E18: monograph; text | F18: PPN743969359 | G18: PPN574227601 | H18: http://resolver.staatsbibliothek-berlin.de/SBB0000D4C500000000 | I18: ger | J18: 1885 | K18: WegehauptDigital | L18: Dresden | M18: https://content.staatsbibliothek-berlin.de/dc/743969359.ocr.zip | N18: yes
A19: Das Buch wunderbarer Erfindungen; in Schilderungen f. d. reifere Jugend : mit 125 Abb. u. 1 Titelbild. | B19: Thomas, Louis | C19: Kinder- und Jugendbücher; Historische Drucke | D19: Spamer | E19: monograph; text | F19: PPN756689090 | G19: PPN578154765 | H19: http://resolver.staatsbibliothek-berlin.de/SBB0000EBC100000000 | I19: ger | J19: 1860 | K19: WegehauptDigital | L19: Leipzig | M19: https://content.staatsbibliothek-berlin.de/dc/756689090.ocr.zip | N19: yes
A20: Naturgeschichte der Vögel; mit besonderer Berücksichtigung der in Deutschland vorkommenden Vögel und Belehrung über Zucht und Wartung der Haus- und Stubenvögel | B20: Abendroth, Carl | C20: Kinder- und Jugendbücher | D20: Baensch | E20: monograph; text | F20: PPN744053714 | G20: PPN538752823 | H20: http://resolver.staatsbibliothek-berlin.de/SBB0000D51E00000000 | I20: ger | J20: 1870 | K20: WegehauptDigital | L20: Leipzig | M20: https://content.staatsbibliothek-berlin.de/dc/744053714.ocr.zip | N20: yes
A21: Abrégé de toutes les sciences à l'usage des enfans de six ans jusqu' a douze; on y a joint un abrégé de l'histoire de Brandebourg | B21: Formey, Jean-Henri-Samuel | C21: Kinder- und Jugendbücher; Historische Drucke | D21: Horvath | E21: monograph; text | F21: PPN76623858X | G21: PPN557396433 | H21: http://resolver.staatsbibliothek-berlin.de/SBB0000EE5000000000 | I21: fre | J21: 1803 | K21: WegehauptDigital | L21: Potsdam | M21: empty | N21: no
A22: Jagden-Bilderbuch für die liebe Jugend; mit 9 lithographirten Darstellungen | C22: Kinder- und Jugendbücher | E22: monograph; text | F22: PPN770079113 | G22: PPN491349475 | H22: http://resolver.staatsbibliothek-berlin.de/SBB000102A700000000 | I22: ger | J22: 1860 | K22: WegehauptDigital | L22: [S.l.] | M22: https://content.staatsbibliothek-berlin.de/dc/770079113.ocr.zip | N22: yes
A23: Neues und bewährtes illustriertes Kochbuch für alle Stände; zuverlässige Anleitung zur Bereitung der verschiedenartigsten Speisen, Backwerke, Getränke etc. ; nach eigener, vieljähriger Erfahrung | B23: Davithis, H. | C23: Kinder- und Jugendbücher; Historische Drucke | D23: Enßlin und Laiblin | E23: monograph; text | F23: PPN745127495 | G23: PPN278540538 | H23: http://resolver.staatsbibliothek-berlin.de/SBB0000D5C100000000 | I23: ger | J23: 1905 | K23: WegehauptDigital | L23: Reutlingen | M23: https://content.staatsbibliothek-berlin.de/dc/745127495.ocr.zip | N23: yes
A24: An der Werkbank; Anleitung zur Handfertigkeit mit besonderer Berücksichtigung der Herstellung physikalischer Apparate ; für mittlere und reife Schüler | B24: Gscheidlen, Emanuel | C24: Kinder- und Jugendbücher; Historische Drucke | D24: Teubner | E24: monograph; text | F24: PPN745118615 | G24: PPN223999733 | H24: http://resolver.staatsbibliothek-berlin.de/SBB0000D59F00000000 | I24: ger | J24: 1912 | K24: WegehauptDigital | L24: Berlin; Leipzig | M24: https://content.staatsbibliothek-berlin.de/dc/745118615.ocr.zip | N24: yes
A25: Die Schöpfung der Erde; die Urwelt und die Urgeschöpfe bis zum Auftreten des Menschen ; Blicke in das Erdinnere ; Wanderungen in die Gebirgswelt, namentlich unsres Veterlandes, nach Kreuz und Quer ; mit reiferen Schülern unternommen | B25: Hintze, Eduard | C25: Kinder- und Jugendbücher | D25: Spamer | E25: monograph; text | F25: PPN742493695 | G25: PPN341499900 | H25: http://resolver.staatsbibliothek-berlin.de/SBB0000D1BE00000000 | I25: ger | J25: 1885 | K25: WegehauptDigital | L25: Leipzig, Berlin | M25: https://content.staatsbibliothek-berlin.de/dc/742493695.ocr.zip | N25: yes
A26: Der Weltspiegel; das Wissenswürdigste vom Weltgebäude, von der Erde, von den Völkern der Erde | B26: Hoffmann, Friedrich | C26: Kinder- und Jugendbücher; Historische Drucke | D26: Schmidt & Spring; Lithographische Anstalt von Engelhorn und Hochdanz | E26: monograph; text | F26: PPN766156990 | G26: PPN279154607 | H26: http://resolver.staatsbibliothek-berlin.de/SBB0000EE1D00000000 | I26: ger | J26: 1844 | K26: WegehauptDigital | L26: Stuttgart; Stuttgart | M26: empty | N26: no
A27: Naturgeschichte; der Jugend gewidmet | B27: Wagner, Hermann | C27: Kinder- und Jugendbücher | D27: Hoffmann | E27: monograph; text | F27: PPN770457983 | G27: PPN408013931 | H27: http://resolver.staatsbibliothek-berlin.de/SBB0001049700000000 | I27: ger | J27: 1870 | K27: WegehauptDigital | L27: Stuttgart | M27: https://content.staatsbibliothek-berlin.de/dc/770457983.ocr.zip | N27: yes
A28: Lehrbuch der Sternkunde; für Schulen und zum Selbstunterrichte | B28: Schubert, Gotthilf Heinrich | C28: Kinder- und Jugendbücher; Historische Drucke | D28: Weber | E28: monograph; text | F28: PPN750739150 | G28: PPN311822029 | H28: http://resolver.staatsbibliothek-berlin.de/SBB0000E3CF00000000 | I28: ger | J28: 1832 | K28: WegehauptDigital | L28: München | M28: empty | N28: no
A29: Leichte Künsteleien zum Vergnügen und zum Nutzen für Kinder und Nichtkinder; Ein Buch mannigfaltigen Inhaltes | B29: Rockstroh, Heinrich | C29: Kinder- und Jugendbücher; Historische Drucke | D29: Wittich | E29: monograph; text | F29: PPN767041380 | G29: PPN556113098 | H29: http://resolver.staatsbibliothek-berlin.de/SBB0000F1B600000000 | I29: ger | J29: 1819 | K29: WegehauptDigital | L29: Berlin | M29: empty | N29: no
A30: Europäische Bilder und Skizzen; zur Belehrung für die reifere Jugend | B30: Hoffmann, Julius; Hosemann, Theodor | C30: Kinder- und Jugendbücher | D30: Trewendt | E30: monograph; text | F30: PPN771014600 | G30: PPN265186358 | H30: http://resolver.staatsbibliothek-berlin.de/SBB00010A6400000000 | I30: ger | J30: 1858 | K30: WegehauptDigital | L30: Breslau | M30: https://content.staatsbibliothek-berlin.de/dc/771014600.ocr.zip | N30: yes
A31: Malerische Naturgeschichte der drei Reiche für Schule und Haus; Mit besonderer Beziehung auf das practische Leben bearbeitet von F[riedrich] W[ilhelm] Lindner; unter Mitwirkung von Dr. Fr. H. A. Lachmann | B31: Lachmann, Fr. H. A.; Lindner, Friedrich Wilhelm | C31: Kinder- und Jugendbücher; Historische Drucke | D31: Oehme & Müller | E31: monograph; text | F31: PPN770463371 | G31: PPN42077016X | H31: http://resolver.staatsbibliothek-berlin.de/SBB000104A200000000 | I31: ger | J31: 1840 | K31: WegehauptDigital | L31: Braunschweig | M31: empty | N31: no
A32: Allerlei schöne Bilderrätsel für Jung und Alt | C32: Kinder- und Jugendbücher; Historische Drucke | E32: monograph; text | F32: PPN74513548X | G32: PPN30847046X | H32: http://resolver.staatsbibliothek-berlin.de/SBB0000D5D100000000 | I32: ger | K32: WegehauptDigital | M32: https://content.staatsbibliothek-berlin.de/dc/74513548X.ocr.zip | N32: yes
A33: Der Hausbau; oder erste Begriffe von Staat und den vorzüglichsten Ständen, Handwerken, Fabriken, Künsten, Wissenschaften u. d. gl. für Kinder | B33: Werlich, August Karl Friedrich | C33: Kinder- und Jugendbücher; Historische Drucke | D33: Juniussische Buchhandlung | E33: monograph; text | F33: PPN756639891 | G33: PPN579566781 | H33: http://resolver.staatsbibliothek-berlin.de/SBB0000EB7900000000 | I33: ger | J33: 1804 | K33: WegehauptDigital | L33: Leipzig | M33: empty | N33: no
A34: Gemählde aus der Natur und dem Menschenleben, in einer Reihe von Schilderungen merkwürdiger Naturerscheinungen und gefahrvoller Reiseabentheuer; zum Nutzen und Vergnügen der Jugend | B34: Albertus, D. J. C. | C34: Kinder- und Jugendbücher | D34: Kaiser | E34: monograph; text | F34: PPN781283116 | G34: PPN541529498 | H34: http://resolver.staatsbibliothek-berlin.de/SBB0001555D00000000 | I34: ger | J34: 1830 | K34: WegehauptDigital | L34: Grätz | M34: empty | N34: no
A35: Kurzer Unterricht in der Naturwissenschaft für die Jugend | B35: Uihlein, Joseph | C35: Kinder- und Jugendbücher; Historische Drucke | D35: Andreä | E35: monograph; text | F35: PPN770157742 | G35: PPN366080202 | H35: http://resolver.staatsbibliothek-berlin.de/SBB0001033900000000 | I35: ger | J35: 1810 | K35: WegehauptDigital | L35: Frankfurt am Main | M35: empty | N35: no
A36: F. Martin's Naturgeschichte für die Jugend beiderlei Geschlechts; mit dreihundert Abbildungen und zwanzig Holzschnitten | B36: Kolb, Christian Friedrich August; Martin, F. | C36: Kinder- und Jugendbücher; Historische Drucke | D36: Schmidt & Spring | E36: monograph; text | F36: PPN741294397 | G36: PPN566740400 | H36: http://resolver.staatsbibliothek-berlin.de/SBB0000CFA500000000 | I36: ger | J36: 1880 | K36: WegehauptDigital | L36: Stuttgart | M36: https://content.staatsbibliothek-berlin.de/dc/741294397.ocr.zip | N36: yes
A37: Aus Werkstatt und Welt; eine Festgabe für die werkthätige Jugend dargereicht von Leipz. Fortbildungsschuldirektoren u.-Lehrern | C37: Kinder- und Jugendbücher; Historische Drucke | D37: Hahn; Schmidt | E37: monograph; text | F37: PPN770851347 | G37: PPN581182618 | H37: http://resolver.staatsbibliothek-berlin.de/SBB0001070300000000 | I37: ger | J37: 1901 | K37: WegehauptDigital | L37: Leipzig; Leipzig | M37: https://content.staatsbibliothek-berlin.de/dc/770851347.ocr.zip | N37: yes
A38: Mittheilungen aus dem Gebiet der Naturkunde und dem Menschenleben für die Jugend ; mit 25 col. Abb. | B38: Maukisch, Heinrich Eduard | C38: Kinder- und Jugendbücher; Historische Drucke | D38: Fischer u. Fuchs | E38: monograph; text | F38: PPN766619389 | G38: PPN566841444 | H38: http://resolver.staatsbibliothek-berlin.de/SBB0000F00A00000000 | I38: ger | J38: 1835 | K38: WegehauptDigital | L38: Leipzig | M38: empty | N38: no
A39: Čudesa bez čudesʹ; malenkaja fizika v priměnenii kʹ zabavamʹ/ sost. A. P. Nečaev. S 172 ris. | B39: Nečaev, A. P. | C39: Kinder- und Jugendbücher | D39: Lukovnikov | E39: monograph; text | F39: PPN742094227 | G39: PPN280334869 | H39: http://resolver.staatsbibliothek-berlin.de/SBB0000D0A100000000 | I39: rus | J39: 1911 | K39: WegehauptDigital | L39: Spb. [St. Petersburg] | M39: https://content.staatsbibliothek-berlin.de/dc/742094227.ocr.zip | N39: yes
A40: Nun rathe einmal!; Räthselbüchlein für Kinder von 5 - 10 Jahren | B40: Flinzer, Fedor | C40: Kinder- und Jugendbücher; Historische Drucke | D40: Focke | E40: monograph; text | F40: PPN745597041 | G40: PPN568651901 | H40: http://resolver.staatsbibliothek-berlin.de/SBB0000D6F200000000 | I40: ger | J40: 1864 | K40: WegehauptDigital | L40: Chemnitz | M40: https://content.staatsbibliothek-berlin.de/dc/745597041.ocr.zip | N40: yes
A41: Räthselkranz für Alt und Jung | B41: Ruhkopf, Julie | C41: Kinder- und Jugendbücher; Historische Drucke | D41: Flemming | E41: monograph; text | F41: PPN74623791X | G41: PPN476384494 | H41: http://resolver.staatsbibliothek-berlin.de/SBB0000D85700000000 | I41: ger | J41: 1861 | K41: WegehauptDigital | L41: Glogau | M41: https://content.staatsbibliothek-berlin.de/dc/74623791X.ocr.zip | N41: yes
A42: Merkwürdige Reisen der Gutmannschen Familie; ein Weihnachts- und Geburtstags-Geschenk für die Jugend | B42: Ramberg, H.; Boettger, G.; Dassel, Chr. | C42: Kinder- und Jugendbücher | D42: Brüder Hahn | E42: monograph; text | F42: PPN746870108 | G42: PPN363821880 | H42: http://resolver.staatsbibliothek-berlin.de/SBB0000DBD600000000 | I42: ger | J42: 1816 | K42: WegehauptDigital | L42: Hannover | M42: empty | N42: no
A43: Recipes | C43: Kinder- und Jugendbücher | D43: Orr | E43: monograph; text | F43: PPN746034628 | G43: PPN279781792 | H43: http://resolver.staatsbibliothek-berlin.de/SBB0000D7DD00000000 | I43: eng | J43: 1883 | K43: WegehauptDigital | L43: Springfield, Mass. | M43: https://content.staatsbibliothek-berlin.de/dc/746034628.ocr.zip | N43: yes
A44: Das Turnen in den Spielen der Mädchen; eine Auswahl nützlicher und passender Jugend- und Bewegungspiele ; zur geistigen und körperlichen Erholung des jüngeren Mädchenalters wie als Beitrag zu einer naturgemäßen Jugenderziehung | B44: Bürkner, Hugo; Kloss, Moritz | C44: Kinder- und Jugendbücher | D44: Schönfeld | E44: monograph; text | F44: PPN770493564 | G44: PPN27843424X | H44: http://resolver.staatsbibliothek-berlin.de/SBB000104D400000000 | I44: ger | J44: 1862 | K44: WegehauptDigital | L44: Dresden | M44: https://content.staatsbibliothek-berlin.de/dc/770493564.ocr.zip | N44: yes
A45: Das Ein-mal-Eins in Bilderpracht, wie es den Kindern Freude macht | B45: Reinhardt, Aug.; Reinhardt, V. | C45: Kinder- und Jugendbücher | D45: Kaufmann | E45: monograph; text | F45: PPN741360802 | G45: PPN572962495 | H45: http://resolver.staatsbibliothek-berlin.de/SBB0000CFF400000000 | I45: ger | J45: 1880 | K45: WegehauptDigital | L45: Dresden | M45: https://content.staatsbibliothek-berlin.de/dc/741360802.ocr.zip | N45: yes
A46: Natur-Paradoxe; ein Buch für die Jugend zur Erklärung von Erscheinungen, die mit der täglichen Erfahrung in Widerspruch zu stehen scheinen ; nach Dr. W. Hampson's 'Paradoxes of nature and science' | B46: Schäffer, C.; Hampson, William | C46: Kinder- und Jugendbücher | D46: Teubner | E46: monograph; text | F46: PPN741671417 | G46: PPN408347201 | H46: http://resolver.staatsbibliothek-berlin.de/SBB0000D04500000000 | I46: ger | J46: 1908 | K46: WegehauptDigital | L46: Leipzig; Berlin | M46: https://content.staatsbibliothek-berlin.de/dc/741671417.ocr.zip | N46: yes
A47: Die Meteorologie in Erklärungen und Erzählungen; ein nützliches und unterhaltendes Lesebuch für die reifere Jugend | B47: Moshamer, Joseph A. | C47: Kinder- und Jugendbücher | D47: Im Verl. der k. k. Schulbücher-Verschleiß-Administration | E47: monograph; text | F47: PPN770192904 | G47: PPN348919875 | H47: http://resolver.staatsbibliothek-berlin.de/SBB0001037500000000 | I47: ger | J47: 1844 | K47: WegehauptDigital | L47: Wien | M47: empty | N47: no
A48: Naturstudien im Hause; Plaudereien in der Dämmerstunde ; ein Buch für die Jugend | B48: Schwindrazheim, O.; Kraepelin, Karl | C48: Kinder- und Jugendbücher | D48: Teubner | E48: monograph; text | F48: PPN742265854 | G48: PPN075438097 | H48: http://resolver.staatsbibliothek-berlin.de/SBB0000D0DF00000000 | I48: ger | J48: 1901 | K48: WegehauptDigital | L48: Leipzig | M48: https://content.staatsbibliothek-berlin.de/dc/742265854.ocr.zip | N48: yes
A49: Peter Parley's Visit to London; during the coronation of Queen Victoria | B49: Viktoria < Großbritannien, Königin>; Parley, Peter | C49: Kinder- und Jugendbücher; Historische Drucke | D49: Tilt | E49: monograph; text | F49: PPN771192134 | G49: PPN27953969X | H49: http://resolver.staatsbibliothek-berlin.de/SBB0001262E00000000 | I49: eng | J49: 1839 | K49: WegehauptDigital | L49: London | M49: empty | N49: no
A50: Die kleinen Gärtner, oder Gartenbeschäftigungen für Kinder; enthält einen deutlichen Unterricht, wie Kinder einen kleinen Garten anlegen, behandeln und abwarten können, ohne dabey einen Gärtner zu Hülfe zu nehmen : mit Kupfern | B50: Poscharsky, Christian Friedrich | C50: Kinder- und Jugendbücher; Historische Drucke | D50: Friese | E50: monograph; text | F50: PPN769382053 | G50: PPN389953334 | H50: http://resolver.staatsbibliothek-berlin.de/SBB0000F96300000000 | I50: ger | J50: 1810 | K50: WegehauptDigital | L50: Pirna | M50: empty | N50: no
A51: Carl der Tausendkünstler, oder: Sammlung einfacher und künstlicher, großentheils neuer mechanischer, chemischer, magnetischer und Kartenkunststücke und arithmetischer Belustigungen zur angenehmen geselligen Unterhaltung | B51: Kerndörffer, Heinrich August | C51: Kinder- und Jugendbücher; Historische Drucke | D51: Cnobloch | E51: monograph; text | F51: PPN766428656 | G51: PPN560665571 | H51: http://resolver.staatsbibliothek-berlin.de/SBB0000EF3700000000 | I51: ger | J51: 1840 | K51: WegehauptDigital | L51: Leipzig | M51: empty | N51: no
A52: Der illustrirte Jugendfreund; Schilderungen des Weltgebäudes und seiner Wunder ; in Bilder aus der Natur, dem Leben der Menschen und der Thiere der Vergangenheit und Gegenwart | B52: Thomas, Louis | C52: Kinder- und Jugendbücher; Historische Drucke | D52: Spamer | E52: monograph; text | F52: PPN767132297 | G52: PPN578175231 | H52: http://resolver.staatsbibliothek-berlin.de/SBB0000F2BB00000000 | I52: ger | J52: 1852 | K52: WegehauptDigital | L52: Leipzig | M52: https://content.staatsbibliothek-berlin.de/dc/767132297.ocr.zip | N52: yes
A53: The Child's guide to knowledge; being a collection of useful and familiar questions and answers on every-day subjects; adapted for young persons, and arranged in the most simple and easy language ; by a Lady | C53: Kinder- und Jugendbücher; Historische Drucke | D53: Simpkin [u.a.] | E53: monograph; text | F53: PPN745137695 | G53: PPN550723854 | H53: http://resolver.staatsbibliothek-berlin.de/SBB0000D5D600000000 | I53: eng | J53: 1871 | K53: WegehauptDigital | L53: London | M53: https://content.staatsbibliothek-berlin.de/dc/745137695.ocr.zip | N53: yes
A54: Kleine Bilder-Encyclopedie; [für junge Knaben und Mädchen] | C54: Kinder- und Jugendbücher | D54: Rücker] | E54: monograph; text | F54: PPN770565247 | G54: PPN445549262 | H54: http://resolver.staatsbibliothek-berlin.de/SBB0001055A00000000 | I54: ger | J54: 1808 | K54: WegehauptDigital | L54: [Berlin | M54: empty | N54: no
A55: Naturgeschichte für Kinder | B55: Meyer, F. A. A.; Raff, Georg Christian | C55: Kinder- und Jugendbücher; Historische Drucke | D55: Dieterich | E55: monograph; text | F55: PPN769384986 | G55: PPN141087994 | H55: http://resolver.staatsbibliothek-berlin.de/SBB0000F96900000000 | I55: ger | J55: 1827 | K55: WegehauptDigital | L55: Göttingen | M55: empty | N55: no
A56: Kochbüchlein für die Puppenküche oder erste Anweisung zum Kochen; Für Mädchen von 8-14 Jahren | B56: Löffler, Henriette; Bimbach, Julie | C56: Kinder- und Jugendbücher | D56: Schreiber | E56: monograph; text | F56: PPN769117392 | G56: PPN548218307 | H56: http://resolver.staatsbibliothek-berlin.de/SBB0000F8A000000000 | I56: ger | J56: 1885 | K56: WegehauptDigital | L56: Eßlingen | M56: https://content.staatsbibliothek-berlin.de/dc/769117392.ocr.zip | N56: yes
A57: Naturgeschichte der deutschen Schmetterlinge für die Jugend; Nebst einer passenden Anweisung, sie zu fangen, zuzubereiten, zu ordnen und unbeschädigt zu erhalten | C57: Kinder- und Jugendbücher; Historische Drucke | D57: Groß | E57: monograph; text | F57: PPN75101611X | G57: PPN568829980 | H57: http://resolver.staatsbibliothek-berlin.de/SBB0000E42300000000 | I57: ger | J57: 1805 | K57: WegehauptDigital | L57: Halberstadt | M57: empty | N57: no
A58: Illustrirte Naturgeschichte für die Jugend; mit mehr als 200 color. Abb. | B58: Schubert, Ferdinand; Schubert, Carl | C58: Kinder- und Jugendbücher; Historische Drucke | D58: Sallmayer | E58: monograph; text | F58: PPN749885149 | G58: PPN574523774 | H58: http://resolver.staatsbibliothek-berlin.de/SBB0000E14B00000000 | I58: ger | J58: 1856 | K58: WegehauptDigital | L58: Wien | M58: https://content.staatsbibliothek-berlin.de/dc/749885149.ocr.zip | N58: yes
A59: Spielbuch; enthaltend Gesellschaftsspiele, Auslösen der Pfänder, Rätsel, Charaden | B59: Löwicke, Robert | C59: Kinder- und Jugendbücher; Historische Drucke | D59: Flemming | E59: monograph; text | F59: PPN745605478 | G59: PPN566420597 | H59: http://resolver.staatsbibliothek-berlin.de/SBB0000D71400000000 | I59: ger | J59: 1887 | K59: WegehauptDigital | L59: Glogau | M59: https://content.staatsbibliothek-berlin.de/dc/745605478.ocr.zip | N59: yes
A60: Reise einer Tante in vieler Herren Länder | B60: Bernhardi, Elisabeth Eleonore | C60: Kinder- und Jugendbücher | E60: monograph; text | F60: PPN77088976X | G60: PPN444747249 | H60: http://resolver.staatsbibliothek-berlin.de/SBB0001074200000000 | I60: ger | J60: 1817 | K60: WegehauptDigital | L60: [Freiberg] | M60: empty | N60: no
A61: Naturgeschichte der Insekten für die Jugend ; Mit Kupfern | C61: Kinder- und Jugendbücher | D61: Campe | E61: monograph; text | F61: PPN770372821 | G61: PPN32489211X | H61: http://resolver.staatsbibliothek-berlin.de/SBB0001046000000000 | I61: ger | J61: 1820 | K61: WegehauptDigital | L61: Nürnberg | M61: empty | N61: no
A62: Kleines Käferbuch für Knaben; eine Anleitung zur Kenntniß der Käfer im Allgemeinen wie auch zur Anlage und zweckmäßigen Einrichtung von Käfersammlungen ; mit 72 illuminierten Abbildungen auf 5 Tafeln | C62: Kinder- und Jugendbücher; Historische Drucke | D62: Hendel | E62: monograph; text | F62: PPN742562549 | G62: PPN560569718 | H62: http://resolver.staatsbibliothek-berlin.de/SBB0000D21A00000000 | I62: ger | J62: 1862 | K62: WegehauptDigital | L62: Halle | M62: https://content.staatsbibliothek-berlin.de/dc/742562549.ocr.zip | N62: yes
A63: Entdeckungsreisen in Haus und Hof; mit seinen jungen Freunden unternommen | B63: Wagner, H. | C63: Kinder- und Jugendbücher | D63: Spamer | E63: monograph; text | F63: PPN74364154X | G63: PPN270201556 | H63: http://resolver.staatsbibliothek-berlin.de/SBB0000D30500000000 | I63: ger | J63: 1866 | K63: WegehauptDigital | L63: Leipzig | M63: https://content.staatsbibliothek-berlin.de/dc/74364154X.ocr.zip | N63: yes
A64: [Rätselbuch] | C64: Kinder- und Jugendbücher; Historische Drucke | E64: monograph; text | F64: PPN766622541 | G64: PPN571694535 | H64: http://resolver.staatsbibliothek-berlin.de/SBB0000F01000000000 | I64: ger | J64: 1830 | K64: WegehauptDigital | L64: [S.l.] | M64: empty | N64: no
A65: Naturstudien im Garten; Plaudereien am Sonntag Nachmittag ; ein Buch für die Jugend | B65: Schwindrazheim, O.; Kraepelin, Karl | C65: Kinder- und Jugendbücher | D65: Teubner | E65: monograph; text | F65: PPN742297330 | G65: PPN075795655 | H65: http://resolver.staatsbibliothek-berlin.de/SBB0000D0EF00000000 | I65: ger | J65: 1901 | K65: WegehauptDigital | L65: Leipzig | M65: https://content.staatsbibliothek-berlin.de/dc/742297330.ocr.zip | N65: yes
A66: Charakterbilder aus der Thierwelt verschiedener Welttheile; zur Belehrung und Unterhaltung der Jugend | B66: Hoffmann, W. | C66: Kinder- und Jugendbücher | D66: Nitzschke | E66: monograph; text | F66: PPN743630491 | G66: PPN26518777X | H66: http://resolver.staatsbibliothek-berlin.de/SBB0000D2F600000000 | I66: ger | J66: 1862 | K66: WegehauptDigital | L66: Stuttgart | M66: https://content.staatsbibliothek-berlin.de/dc/743630491.ocr.zip | N66: yes
A67: Neue Wanderungen durch die Thierwelt; ein Buch für Knaben und Mädchen | B67: Kirchhoff, Johann; Reichenbach, A. B. | C67: Kinder- und Jugendbücher | D67: Kretzschmar | E67: monograph; text | F67: PPN770577199 | G67: PPN311107745 | H67: http://resolver.staatsbibliothek-berlin.de/SBB0001057F00000000 | I67: ger | J67: 1848 | K67: WegehauptDigital | L67: Leipzig | M67: empty | N67: no
A68: Reisen in die Ferne oder Vater Reinhold's Mittheilungen über die Erde und ihre Bewohner; ein Lese- und Bilderbuch zur Belehrung und Unterhaltung der Jugend in der Völkerkunde und Erdbeschreibung | B68: Geissler, ...; Boettger, Gottlieb; Maukisch, Heinrich Eduard | C68: Kinder- und Jugendbücher; Historische Drucke | D68: Taubert | E68: monograph; text | F68: PPN77101631X | G68: PPN278734375 | H68: http://resolver.staatsbibliothek-berlin.de/SBB00010A6800000000 | I68: ger | J68: 1836 | K68: WegehauptDigital | L68: Leipzig | M68: empty | N68: no
A69: Lustige Bilder-Räthsel für kluge Kinder | B69: Breitschwert, W. | C69: Kinder- und Jugendbücher | D69: Hoffmann <Thienemann> | E69: monograph; text | F69: PPN745436269 | G69: PPN279375425 | H69: http://resolver.staatsbibliothek-berlin.de/SBB0000D6B000000000 | I69: ger | J69: 1875 | K69: WegehauptDigital | L69: Stuttgart | M69: https://content.staatsbibliothek-berlin.de/dc/745436269.ocr.zip | N69: yes
A70: Wie viel sind's?; Ein Bilderbuch | B70: Schmidhammer, Arpad; Holst, Adolf | C70: Kinder- und Jugendbücher | D70: Scholz | E70: monograph; text | F70: PPN770464904 | G70: PPN57409041X | H70: http://resolver.staatsbibliothek-berlin.de/SBB000104A500000000 | I70: ger | J70: 1913 | K70: WegehauptDigital | L70: Mainz | M70: https://content.staatsbibliothek-berlin.de/dc/770464904.ocr.zip | N70: yes
A71: Nun rath' einmal!; Illustrirtes Räthselbuch für artige Kinder | B71: Gerstenberg, Karl | C71: Kinder- und Jugendbücher | D71: Schreiber | E71: monograph; text | F71: PPN745435734 | G71: PPN558101321 | H71: http://resolver.staatsbibliothek-berlin.de/SBB0000D6AE00000000 | I71: ger | J71: 1878 | K71: WegehauptDigital | L71: Eßlingen | M71: https://content.staatsbibliothek-berlin.de/dc/745435734.ocr.zip | N71: yes
A72: Der Thiergarten zu Lilienthal; Ein unterhaltendes naturgeschichtliches Bilder- und Lesebuch für die Jugend ... (Mit 12 großen u. 82 kleineren Abbildungen in schönem Farbendruck.) | B72: Beumer, Philipp Jakob | C72: Kinder- und Jugendbücher; Historische Drucke | D72: Bagel | E72: monograph; text | F72: PPN770507050 | G72: PPN44513125X | H72: http://resolver.staatsbibliothek-berlin.de/SBB000104E500000000 | I72: ger | J72: 1850 | K72: WegehauptDigital | L72: Wesel | M72: https://content.staatsbibliothek-berlin.de/dc/770507050.ocr.zip | N72: yes
A73: Zoologie du jeune age ou histoire naturelle des animaux; écrite pour la jeunesse | B73: Lereboullet, Auguste | C73: Kinder- und Jugendbücher; Historische Drucke | D73: Derivaux | E73: monograph; text | F73: PPN749918349 | G73: PPN280187092 | H73: http://resolver.staatsbibliothek-berlin.de/SBB0000E19400000000 | I73: fre | J73: 1860 | K73: WegehauptDigital | L73: Strasbourg | M73: https://content.staatsbibliothek-berlin.de/dc/749918349.ocr.zip | N73: yes
A74: Naturgeschichte der reißenden Thiere; Thierschilderungen für Freunde der Natur u. die Jugend aller Stände ; Mit 36 colorierten Taf. Original-Abb. | B74: Mann, Gustav | C74: Kinder- und Jugendbücher; Historische Drucke | D74: Schweizerbart | E74: monograph; text | F74: PPN757120954 | G74: PPN566464845 | H74: http://resolver.staatsbibliothek-berlin.de/SBB0000ECEC00000000 | I74: ger | J74: 1857 | K74: WegehauptDigital | L74: Stuttgart | M74: https://content.staatsbibliothek-berlin.de/dc/757120954.ocr.zip | N74: yes
A75: Die Naturgeschichte für Kinder und Elementarschüler; oder erster Unterricht über das Mineralreich, Pflanzenreich und Thierreich. Mit über 300 color. Abb. | C75: Kinder- und Jugendbücher | D75: Schreiber & Schill | E75: monograph; text | F75: PPN770201407 | G75: PPN389491020 | H75: http://resolver.staatsbibliothek-berlin.de/SBB0001039700000000 | I75: ger | J75: 1855 | K75: WegehauptDigital | L75: Stuttgart [u.a.] | M75: https://content.staatsbibliothek-berlin.de/dc/770201407.ocr.zip | N75: yes
A76: Neuer Orbis Pictus für die Jugend oder Schauplatz der Natur, der Kunst und des Menschenlebens in 322 lithographischen Abbildungen mit genauer Erklärung in deutscher, lateinischer, französischer und englischer Sprache | B76: Gailer, Jacob E.; Comenius, Johann Amos | C76: Kinder- und Jugendbücher; Historische Drucke | D76: Mäcken | E76: monograph; text | F76: PPN767066812 | G76: PPN230802753 | H76: http://resolver.staatsbibliothek-berlin.de/SBB0000F20600000000 | I76: eng | J76: 1835 | K76: WegehauptDigital | L76: Reutlingen | M76: empty | N76: no
A77: Biblische Naturgeschichte für Schulen und Familien | B77: Barth, Christian Gottlob | C77: Kinder- und Jugendbücher | D77: Vereinsbuchhandl. [usw.] | E77: monograph; text | F77: PPN743860241 | G77: PPN54707901X | H77: http://resolver.staatsbibliothek-berlin.de/SBB0000D35E00000000 | I77: ger | J77: 1874 | K77: WegehauptDigital | L77: Calw | M77: https://content.staatsbibliothek-berlin.de/dc/743860241.ocr.zip | N77: yes
A78: Die Schwarzwald-Reise; Eine christliche Erzählung und zugleich eine landschaftliche Beschreibung, natürliche Geographie und Geognosie des würtembergischen Schwarzwaldes ; Für die Jugend der höheren Stände | B78: Schwarz, Eduard | C78: Kinder- und Jugendbücher; Historische Drucke | D78: Balz | E78: monograph; text | F78: PPN77096351X | G78: PPN319610543 | H78: http://resolver.staatsbibliothek-berlin.de/SBB00010A1100000000 | I78: ger | J78: 1836 | K78: WegehauptDigital | L78: Stuttgart | M78: empty | N78: no
A79: Der aufrichtige Kalendermann; Ein gar kurioses und nützliches Buch Für die Jugend und den gemeinen Bürger und Bauersmann verfertiget | B79: Steinbeck, Christoph Gottlieb | C79: Kinder- und Jugendbücher; Historische Drucke; VD18 digital | D79: Steinbeck; Fleischer | E79: monograph; text | F79: PPN766725251 | G79: PPN663601738 | H79: http://resolver.staatsbibliothek-berlin.de/SBB0000F0B200000000 | I79: ger | J79: 1792 | K79: WegehauptDigital; VD18 digital | L79: Langenberg ohnweit Gera; Leipzig | M79: empty | N79: no
A80: Naturgeschichte des Pflanzenreiches in Bildern; nach der Anordnung des allgemein bekannten u. beliebten Lehrbuchs der Naturgeschichte von G[otthilf] H[einrich] v. Schubert | B80: Schubert, Gotthilf Heinrich; Hochstetter, Christian Ferdinand | C80: Kinder- und Jugendbücher; Historische Drucke | D80: Schreiber | E80: monograph; text | F80: PPN749900172 | G80: PPN568822358 | H80: http://resolver.staatsbibliothek-berlin.de/SBB0000E16800000000 | I80: fre | J80: 1865 | K80: WegehauptDigital | L80: Eßlingen a. N. | M80: https://content.staatsbibliothek-berlin.de/dc/749900172.ocr.zip | N80: yes
A81: Die Hausthiere nebst ihrer Beschäftigung und Verwendung; Ein nützliches und unterhaltendes Bilderbuch für die Jugend ; Mit 80 Haupt- und Nebenbildern und erklärendem Text | C81: Kinder- und Jugendbücher; Historische Drucke | D81: Zeh | E81: monograph; text | F81: PPN756434564 | G81: PPN559169582 | H81: http://resolver.staatsbibliothek-berlin.de/SBB0000EA8E00000000 | I81: ger | J81: 1846 | K81: WegehauptDigital | L81: Nürnberg | M81: empty | N81: no
A82: Die Jugendspiele; ein Leitfaden bei der Einführung und Übung von Turn- und Jugendspielen | B82: Eitner, Gustav | C82: Kinder- und Jugendbücher | D82: Voigtländer | E82: monograph; text | F82: PPN745185738 | G82: PPN236366599 | H82: http://resolver.staatsbibliothek-berlin.de/SBB0000D64600000000 | I82: ger | J82: 1890 | K82: WegehauptDigital | L82: Kreuznach [u.a.] | M82: https://content.staatsbibliothek-berlin.de/dc/745185738.ocr.zip | N82: yes
A83: Das Mikroskop; mit 90 Abbildungen | B83: Schertel, Sigmund | C83: Kinder- und Jugendbücher; Historische Drucke | D83: Union Dt. Verlagsges. | E83: monograph; text | F83: PPN741301490 | G83: PPN573714444 | H83: http://resolver.staatsbibliothek-berlin.de/SBB0000CFB500000000 | I83: ger | J83: 1900 | K83: WegehauptDigital | L83: Stuttgart [u.a.] | M83: https://content.staatsbibliothek-berlin.de/dc/741301490.ocr.zip | N83: yes
A84: Naturgeschichte für Kinder | B84: Lippold, Georg Heinrich Christian; Funke, Carl Philipp | C84: Kinder- und Jugendbücher; Historische Drucke | D84: Kummer | E84: monograph; text | F84: PPN769508758 | G84: PPN239889762 | H84: http://resolver.staatsbibliothek-berlin.de/SBB0000F99B00000000 | I84: ger | J84: 1827 | K84: WegehauptDigital | L84: Leipzig | M84: empty | N84: no
A85: Der gewandte Zauberkünstler und Hexenmeister in Familien- und Gesellschaftskreisen; in Darstellung der lehreichsten und unterhaltendsten Kunststücke auf dem Gebiete der natürlichen Magie, der Taschen- und Kartenspieler und der Rechenkunst ; mit Bildern | B85: Ortleb, Alexander | C85: Kinder- und Jugendbücher; Historische Drucke | D85: Linser | E85: monograph; text | F85: PPN745827632 | G85: PPN569413095 | H85: http://resolver.staatsbibliothek-berlin.de/SBB0000D75C00000000 | I85: ger | J85: 1897 | K85: WegehauptDigital | L85: Pankow-Berlin | M85: https://content.staatsbibliothek-berlin.de/dc/745827632.ocr.zip | N85: yes
A86: Der Schmetterlingsfreund; Beschreibung d. vorzügl. mitteleurop. Schmetterlinge nebst Anl. dieselben zu fangen, deren Puppen u. Raupen aufzuziehen u. eine Samml. anzulegen ; für d. Jugend verf. ; mit 236 Abb. auf 23 Taf. | B86: Hofmann, Ernst | C86: Kinder- und Jugendbücher | D86: Hoffmann | E86: monograph; text | F86: PPN769120490 | G86: PPN559723946 | H86: http://resolver.staatsbibliothek-berlin.de/SBB0000F8B000000000 | I86: ger | J86: 1883 | K86: WegehauptDigital | L86: Stuttgart | M86: https://content.staatsbibliothek-berlin.de/dc/769120490.ocr.zip | N86: yes
A87: Naturgeschichte Der Amphibien, Fische, Weich- und Schaalenthiere, Insekten, Würmer und Strahlenthiere in Bildern ... zum Anschauungs-Unterricht für die Jugend ... nach der ...Naturgeschichte für Schulen; mit erklärendem Texte in deutscher und französischer Sprache | B87: Schubert, Gotthilf Heinrich | C87: Kinder- und Jugendbücher; Historische Drucke | D87: Schreiber & Schill | E87: monograph; text | F87: PPN769048684 | G87: PPN568791290 | H87: http://resolver.staatsbibliothek-berlin.de/SBB0000F82200000000 | I87: ger | J87: 1849 | K87: WegehauptDigital | L87: Eßlingen; Stuttgart | M87: empty | N87: no
A88: Wald und Meer; Schilderungen aus dem Naturleben der Thiere und Pflanzen | B88: Ramberg, Heinrich; Jury, Wilhelm; Schasler, Max | C88: Kinder- und Jugendbücher; Historische Drucke | D88: Hasselberg | E88: monograph; text | F88: PPN749886765 | G88: PPN27954653X | H88: http://resolver.staatsbibliothek-berlin.de/SBB0000E15200000000 | I88: ger | J88: 1853 | K88: WegehauptDigital | L88: Berlin | M88: https://content.staatsbibliothek-berlin.de/dc/749886765.ocr.zip | N88: yes
A89: Naturhistorisches Bilder- und Lese-Buch oder Erzählungen über Gegenstände aus den drei Reichen der Natur; Nebst 300 illuminirten Abbildungen von [Konrad] Horny und einer kurzen Erklärung derselben in Versen | B89: Horny, Konrad; Glatz, Jakob | C89: Kinder- und Jugendbücher; Historische Drucke | D89: Frommann | E89: monograph; text | F89: PPN769046053 | G89: PPN371007631 | H89: http://resolver.staatsbibliothek-berlin.de/SBB0000F81F00000000 | I89: ger | J89: 1803 | K89: WegehauptDigital | L89: Jena | M89: empty | N89: no
A90: Das Spiel im Zimmer; eine reichhaltige Sammlung ausgewählter Spiele zum Gebrauche für jung und alt, für den Einzelnen, wie für kleinere und größere Kreise | B90: Mittenzwey, L. | C90: Kinder- und Jugendbücher | D90: Merseburger | E90: monograph; text | F90: PPN745139965 | G90: PPN567083055 | H90: http://resolver.staatsbibliothek-berlin.de/SBB0000D5E900000000 | I90: ger | J90: 1887 | K90: WegehauptDigital | L90: Leipzig | M90: https://content.staatsbibliothek-berlin.de/dc/745139965.ocr.zip | N90: yes
A91: Reise durch das Berner Oberland nach Unterwalden; für die Jugend beschrieben | B91: Lory, G.; Burgdorfer, D.; Meisner, Friedrich | C91: Kinder- und Jugendbücher | D91: Burgdorfer | E91: volume; text | F91: PPN770944965 | G91: PPN282315799 | H91: http://resolver.staatsbibliothek-berlin.de/SBB000109F000020000 | I91: ger | J91: 1821 | K91: WegehauptDigital | L91: Bern | M91: empty | N91: no
A92: Conversations-Lexicon für die Jugend | C92: Kinder- und Jugendbücher; Historische Drucke | D92: Goedsche | E92: volume; text | F92: PPN766562786 | G92: PPN562017402 | H92: http://resolver.staatsbibliothek-berlin.de/SBB0000EF8800020000 | I92: ger | J92: 1840 | K92: WegehauptDigital | L92: Meissen | M92: empty | N92: no
A93: Der kleine Physiker, oder Unterhaltungen über natürliche Dinge, für Kinder | B93: Höpfner, Adolf Friedrich | C93: Kinder- und Jugendbücher | D93: Keyser | E93: volume; text | F93: PPN746626002 | G93: PPN746625758 | H93: http://resolver.staatsbibliothek-berlin.de/SBB0000DB6F00020000 | I93: ger | J93: 1804 | K93: WegehauptDigital | L93: Erfurt | M93: empty | N93: no
A94: Der technologische Jugendfreund oder Unterhaltende Wanderungen in die Werkstätte der Künstler und Handwerker, zur nöthigen Kenntniß derselben | B94: Blasche, Bernhard Heinrich | C94: Kinder- und Jugendbücher | D94: Wilmans | E94: volume; text | F94: PPN770196195 | G94: PPN335885187 | H94: http://resolver.staatsbibliothek-berlin.de/SBB0001038200010000 | I94: ger | J94: 1804 | K94: WegehauptDigital | L94: Frankfurt am Mayn | M94: empty | N94: no
A95: Tempel der Natur und Kunst | B95: Hirschmann, C. A. | C95: Kinder- und Jugendbücher | D95: Tauchnitz | E95: volume; text | F95: PPN781903688 | G95: PPN563410795 | H95: http://resolver.staatsbibliothek-berlin.de/SBB0001568700050000 | I95: ger | J95: 1805 | K95: WegehauptDigital | L95: Leipzig | M95: empty | N95: no
A96: Der mechanische Jugendfreund oder faßliche und unterhaltende Darstellung der Lehre vom Gleichgewicht und der Bewegung, mit der Beschreibung der dazu gehörigen Maschinen und selbst mit Beyfügung mancher belustigenden mechanischen Kunststücke; Zweyter Theil ; Mit sieben Kupfertafeln | B96: Poppe, Johann Heinrich Moritz | C96: Kinder- und Jugendbücher; Historische Drucke | D96: Wilmans | E96: volume; text | F96: PPN746345666 | G96: PPN236461788 | H96: http://resolver.staatsbibliothek-berlin.de/SBB0000D8D300010000 | I96: ger | J96: 1821 | K96: WegehauptDigital | L96: Frankfurt am Main | M96: empty | N96: no
A97: Naturgeschichte für die deutsche Jugend | B97: Hochstetter, Christian Ferdinand; Gebauer, Christian August | C97: Kinder- und Jugendbücher; Historische Drucke | D97: Löflund | E97: volume; text | F97: PPN769087779 | G97: PPN557898129 | H97: http://resolver.staatsbibliothek-berlin.de/SBB0000F85900010000 | I97: ger | J97: 1829 | K97: WegehauptDigital | L97: Stuttgart | M97: empty | N97: no
A98: Reisen in dem Mittelmeere und in einigen der angränzenden Länder ; Theil 4 | B98: Richter, Theodor Friedrich Maximilian | C98: Kinder- und Jugendbücher | D98: Arnold | E98: volume; text | F98: PPN781607434 | G98: PPN246368152 | H98: http://resolver.staatsbibliothek-berlin.de/SBB000155EB00090000 | I98: ger | J98: 1829 | K98: WegehauptDigital | L98: Dresden | M98: empty | N98: no
A99: Physikalischer Kinderfreund | B99: Vieth, Gerhard Ulrich Anton | C99: Kinder- und Jugendbücher; Historische Drucke | D99: Barth | E99: volume; text | F99: PPN751110981 | G99: PPN345242955 | H99: http://resolver.staatsbibliothek-berlin.de/SBB0000E47700000000 | I99: ger | J99: 1801 | K99: WegehauptDigital | L99: Leipzig | M99: empty | N99: no
A100: Orbis pictus | B100: Lauckhard, Carl F. | C100: Kinder- und Jugendbücher | D100: Günther | E100: volume; text | F100: PPN746212909 | G100: PPN620970413 | H100: http://resolver.staatsbibliothek-berlin.de/SBB0000D82E00010000 | I100: ger | J100: 1872 | K100: WegehauptDigital | L100: Leipzig | M100: https://content.staatsbibliothek-berlin.de/dc/746212909.ocr.zip | N100: yes
...

Sheet ger_filtered
A1: title | B1: creator | C1: subject | D1: publisher | E1: type | F1: digital object identifier | G1: physical object identifier | H1: URL | I1: language | J1: date | K1: relation | L1: coverage | M1: OCR URL | N1: OCR found?
A2: Naturgeschichte für Kinder | B2: Raff, Georg Christian | C2: Kinder- und Jugendbücher; Historische Drucke | D2: Sammer | E2: monograph; text | F2: PPN749770333 | G2: PPN279536941 | H2: http://resolver.staatsbibliothek-berlin.de/SBB0000E0AE00000000 | I2: ger | J2: 1846 | K2: WegehauptDigital | L2: Wien | M2: empty | N2: no
A3: Die Entstehung der Erde | B3: Kranz, Wilhelm; Meyer, Max Wilhelm | C3: Kinder- und Jugendbücher; Historische Drucke | D3: Paetel | E3: monograph; text | F3: PPN741297272 | G3: PPN276525892 | H3: http://resolver.staatsbibliothek-berlin.de/SBB0000CFAB00000000 | I3: ger | J3: 1907 | K3: WegehauptDigital | L3: Berlin | M3: https://content.staatsbibliothek-berlin.de/dc/741297272.ocr.zip | N3: yes
A4: Die Schulwerkstatt; ein Leitfaden zur Einführung der technischen Arbeiten in die Schule | B4: Barth, Ernst; Niederley, W. | C4: Kinder- und Jugendbücher; Historische Drucke | D4: Velhagen & Klasing | E4: monograph; text | F4: PPN745116574 | G4: PPN453868991 | H4: http://resolver.staatsbibliothek-berlin.de/SBB0000D59B00000000 | I4: ger | J4: 1882 | K4: WegehauptDigital | L4: Bielefeld [u.a.] | M4: https://content.staatsbibliothek-berlin.de/dc/745116574.ocr.zip | N4: yes
A5: Der junge Eisenbahnbauer; eine Anleitung zur Selbstherstellung von Modelleisenbahnen ; mit 118 Abb. | B5: Hermuth, Paul | C5: Kinder- und Jugendbücher; Historische Drucke | D5: Union Dt. Verl.-Gesellsch. | E5: monograph; text | F5: PPN744069432 | G5: PPN559338228 | H5: http://resolver.staatsbibliothek-berlin.de/SBB0000D52F00000000 | I5: ger | J5: 1916 | K5: WegehauptDigital | L5: Stuttgart [u.a.] | M5: https://content.staatsbibliothek-berlin.de/dc/744069432.ocr.zip | N5: yes
A6: Neuer Räthselschatz; für die Jugend zur Übung im Denken und zur belehrenden Unterhaltung | B6: Schäffer, W. | C6: Kinder- und Jugendbücher; Historische Drucke | D6: Oehmigke | E6: monograph; text | F6: PPN745271243 | G6: PPN573465517 | H6: http://resolver.staatsbibliothek-berlin.de/SBB0000D67F00000000 | I6: ger | J6: 1865 | K6: WegehauptDigital | L6: Neu-Ruppin | M6: https://content.staatsbibliothek-berlin.de/dc/745271243.ocr.zip | N6: yes
A7: Wander- und Spielbüchlein für Schüler und Schülerinnen | B7: Matzdorf, Paul | C7: Kinder- und Jugendbücher | D7: Strauch | E7: monograph; text | F7: PPN745123694 | G7: PPN56682809X | H7: http://resolver.staatsbibliothek-berlin.de/SBB0000D5AD00000000 | I7: ger | J7: 1910 | K7: WegehauptDigital | L7: Leipzig | M7: https://content.staatsbibliothek-berlin.de/dc/745123694.ocr.zip | N7: yes
A8: Der unerschöpfliche Maître de Plaisir; oder die Kunst, in allen Jahreszeiten, im Freien und zu Hause, so wie an allen nur denkbaren Freudentagen die unterhaltendsten und belustigendsten Parthieen anzuordnen ; Enthaltend die besten Spiele, Lieder, Declamir- und Kunststücke, Räthsel, Charaden [et]c. Ein unentbehrliches Haus- und Handbuch für alle lebensfrohe deutsche Familien | C8: Kinder- und Jugendbücher; Historische Drucke | D8: Voigt | E8: monograph; text | F8: PPN767042255 | G8: PPN280073852 | H8: http://resolver.staatsbibliothek-berlin.de/SBB0000F1B700000000 | I8: ger | J8: 1822 | K8: WegehauptDigital | L8: Nordhausen; Sondershausen | M8: empty | N8: no
A9: Im Grünen oder Die kleinen Pflanzenfreunde; kleine Erzählungen aus dem Pflanzenreich | B9: Wagner, Hermann | C9: Kinder- und Jugendbücher | D9: Spamer | E9: monograph; text | F9: PPN743675703 | G9: PPN578788829 | H9: http://resolver.staatsbibliothek-berlin.de/SBB0000D31400000000 | I9: ger | J9: 1878 | K9: WegehauptDigital | L9: Leipzig | M9: https://content.staatsbibliothek-berlin.de/dc/743675703.ocr.zip | N9: yes
A10: Das Buch der Gesellschaftsspiele | B10: Weller, Hermine | C10: Kinder- und Jugendbücher | D10: Fischer | E10: monograph; text | F10: PPN745213553 | G10: PPN581117719 | H10: http://resolver.staatsbibliothek-berlin.de/SBB0000D65A00000000 | I10: ger | J10: 1910 | K10: WegehauptDigital | L10: Dresden | M10: https://content.staatsbibliothek-berlin.de/dc/745213553.ocr.zip | N10: yes
A11: Der gelehrte Spielkamerad; Anleitung für kleine Physiker, Chemiker, Botaniker und Naturfreunde zum Experimentieren, zur Anlage von Pflanzen-, Stein-, Muschel-, Insekten-, Schmetterling-, Vogel-, Briefmarken-Sammlungen ect. sowie zur Pflege der Hausthiere und des Hausgartens ; ein Supplement zum "Spielbuch für Knaben" | B11: Wagner, Hermann | C11: Kinder- und Jugendbücher | D11: Spamer | E11: monograph; text | F11: PPN74270906X | G11: PPN578814706 | H11: http://resolver.staatsbibliothek-berlin.de/SBB0000D2AA00000000 | I11: ger | J11: 1877 | K11: WegehauptDigital | L11: Leipzig | M11: https://content.staatsbibliothek-berlin.de/dc/74270906X.ocr.zip | N11: yes
A12: Des fleißigen Mädchens Koch-Büchlein für die Puppen-Küche | C12: Kinder- und Jugendbücher; Historische Drucke | D12: Meisel | E12: monograph; text | F12: PPN745432069 | G12: PPN278721036 | H12: http://resolver.staatsbibliothek-berlin.de/SBB0000D6A800000000 | I12: ger | J12: 1876 | K12: WegehauptDigital | L12: Leipzig; Herisau; Stuttgart | M12: https://content.staatsbibliothek-berlin.de/dc/745432069.ocr.zip | N12: yes
A13: Naturgeschichte für Kinder, von M. Georg Christian Raff, ordentlichen Lehrer der Geschichte und Geographie auf dem Lyceum zu Göttingen. Mit vierzehn Kupfertafeln | B13: Raff, Georg Christian | C13: Kinder- und Jugendbücher; Historische Drucke | E13: monograph; text | F13: PPN769119182 | G13: PPN571683770 | H13: http://resolver.staatsbibliothek-berlin.de/SBB0000F8A900000000 | I13: ger | J13: 1802 | K13: WegehauptDigital | L13: Frankfurt; Leipzig | M13: empty | N13: no
A14: Kleine Bilderschule für die Jugend | B14: Hausius, Karl Gottlob | C14: Kinder- und Jugendbücher; Historische Drucke | D14: Voß | E14: monograph; text | F14: PPN757417825 | G14: PPN55916422X | H14: http://resolver.staatsbibliothek-berlin.de/SBB0000ED8900000000 | I14: ger | J14: 1807 | K14: WegehauptDigital | L14: Leipzig | M14: empty | N14: no
A15: Vollständiges Giftbuch oder Unterricht, die Giftpflanzen, Giftminerale und Giftthiere kennen zu lernen, und Gesundheit und Leben gegen Vergiftungs-Gefahren sicher zu stellen | C15: Kinder- und Jugendbücher | D15: Voigt | E15: monograph; text | F15: PPN770137474 | G15: PPN406020620 | H15: http://resolver.staatsbibliothek-berlin.de/SBB0001031A00000000 | I15: ger | J15: 1817 | K15: WegehauptDigital | L15: Sondershausen | M15: empty | N15: no
A16: Schneiders Typen-Atlas; naturwissenschaftlich-geographischer Hand-Atlas für Schule und Haus | B16: Schneider, Oskar; Claudius, W.; Leutemann, H.; Mützel, G.; Seidel, C. F. | C16: Kinder- und Jugendbücher | D16: Meinhold | E16: monograph; text | F16: PPN743969359 | G16: PPN574227601 | H16: http://resolver.staatsbibliothek-berlin.de/SBB0000D4C500000000 | I16: ger | J16: 1885 | K16: WegehauptDigital | L16: Dresden | M16: https://content.staatsbibliothek-berlin.de/dc/743969359.ocr.zip | N16: yes
A17: Das Buch wunderbarer Erfindungen; in Schilderungen f. d. reifere Jugend : mit 125 Abb. u. 1 Titelbild. | B17: Thomas, Louis | C17: Kinder- und Jugendbücher; Historische Drucke | D17: Spamer | E17: monograph; text | F17: PPN756689090 | G17: PPN578154765 | H17: http://resolver.staatsbibliothek-berlin.de/SBB0000EBC100000000 | I17: ger | J17: 1860 | K17: WegehauptDigital | L17: Leipzig | M17: https://content.staatsbibliothek-berlin.de/dc/756689090.ocr.zip | N17: yes
A18: Naturgeschichte der Vögel; mit besonderer Berücksichtigung der in Deutschland vorkommenden Vögel und Belehrung über Zucht und Wartung der Haus- und Stubenvögel | B18: Abendroth, Carl | C18: Kinder- und Jugendbücher | D18: Baensch | E18: monograph; text | F18: PPN744053714 | G18: PPN538752823 | H18: http://resolver.staatsbibliothek-berlin.de/SBB0000D51E00000000 | I18: ger | J18: 1870 | K18: WegehauptDigital | L18: Leipzig | M18: https://content.staatsbibliothek-berlin.de/dc/744053714.ocr.zip | N18: yes
A19: Jagden-Bilderbuch für die liebe Jugend; mit 9 lithographirten Darstellungen | C19: Kinder- und Jugendbücher | E19: monograph; text | F19: PPN770079113 | G19: PPN491349475 | H19: http://resolver.staatsbibliothek-berlin.de/SBB000102A700000000 | I19: ger | J19: 1860 | K19: WegehauptDigital | L19: [S.l.] | M19: https://content.staatsbibliothek-berlin.de/dc/770079113.ocr.zip | N19: yes
A20: Neues und bewährtes illustriertes Kochbuch für alle Stände; zuverlässige Anleitung zur Bereitung der verschiedenartigsten Speisen, Backwerke, Getränke etc. ; nach eigener, vieljähriger Erfahrung | B20: Davithis, H. | C20: Kinder- und Jugendbücher; Historische Drucke | D20: Enßlin und Laiblin | E20: monograph; text | F20: PPN745127495 | G20: PPN278540538 | H20: http://resolver.staatsbibliothek-berlin.de/SBB0000D5C100000000 | I20: ger | J20: 1905 | K20: WegehauptDigital | L20: Reutlingen | M20: https://content.staatsbibliothek-berlin.de/dc/745127495.ocr.zip | N20: yes
A21: An der Werkbank; Anleitung zur Handfertigkeit mit besonderer Berücksichtigung der Herstellung physikalischer Apparate ; für mittlere und reife Schüler | B21: Gscheidlen, Emanuel | C21: Kinder- und Jugendbücher; Historische Drucke | D21: Teubner | E21: monograph; text | F21: PPN745118615 | G21: PPN223999733 | H21: http://resolver.staatsbibliothek-berlin.de/SBB0000D59F00000000 | I21: ger | J21: 1912 | K21: WegehauptDigital | L21: Berlin; Leipzig | M21: https://content.staatsbibliothek-berlin.de/dc/745118615.ocr.zip | N21: yes
A22: Die Schöpfung der Erde; die Urwelt und die Urgeschöpfe bis zum Auftreten des Menschen ; Blicke in das Erdinnere ; Wanderungen in die Gebirgswelt, namentlich unsres Veterlandes, nach Kreuz und Quer ; mit reiferen Schülern unternommen | B22: Hintze, Eduard | C22: Kinder- und Jugendbücher | D22: Spamer | E22: monograph; text | F22: PPN742493695 | G22: PPN341499900 | H22: http://resolver.staatsbibliothek-berlin.de/SBB0000D1BE00000000 | I22: ger | J22: 1885 | K22: WegehauptDigital | L22: Leipzig, Berlin | M22: https://content.staatsbibliothek-berlin.de/dc/742493695.ocr.zip | N22: yes
A23: Der Weltspiegel; das Wissenswürdigste vom Weltgebäude, von der Erde, von den Völkern der Erde | B23: Hoffmann, Friedrich | C23: Kinder- und Jugendbücher; Historische Drucke | D23: Schmidt & Spring; Lithographische Anstalt von Engelhorn und Hochdanz | E23: monograph; text | F23: PPN766156990 | G23: PPN279154607 | H23: http://resolver.staatsbibliothek-berlin.de/SBB0000EE1D00000000 | I23: ger | J23: 1844 | K23: WegehauptDigital | L23: Stuttgart; Stuttgart | M23: empty | N23: no
A24: Naturgeschichte; der Jugend gewidmet | B24: Wagner, Hermann | C24: Kinder- und Jugendbücher | D24: Hoffmann | E24: monograph; text | F24: PPN770457983 | G24: PPN408013931 | H24: http://resolver.staatsbibliothek-berlin.de/SBB0001049700000000 | I24: ger | J24: 1870 | K24: WegehauptDigital | L24: Stuttgart | M24: https://content.staatsbibliothek-berlin.de/dc/770457983.ocr.zip | N24: yes
